[
  {
    "link_it": "https://github.com/lmbstudiocontact/cb_dmean_5000_it_5/raw/main/vet_cb_dmean_5000_it.json",
    "id_item": "vet_cb_dmean_5000_it",
    "id_album": "109468095",
    "english": "vet",
    "list_mean": [
      "xem xét chặt chẽ"
    ],
    "hash_code_list_mean": "-1631934698",
    "list_img": [
      {
        "link_thumb": "https://live.staticflickr.com/65535/51810082935_a2579b2688_n.jpg",
        "link_img": "https://live.staticflickr.com/65535/51810082935_fa24ddfaf6_o.png",
        "id_image": "vet_2934976"
      },
      {
        "link_thumb": "https://live.staticflickr.com/65535/51809345466_8804903168_n.jpg",
        "link_img": "https://live.staticflickr.com/65535/51809345466_c094732fea_o.png",
        "id_image": "vet_2935039"
      }
    ],
    "hash_code_list_img": "854891195",
    "list_definition_mean": [
      {
        "mean_english": "xem xét chặt chẽ",
        "definition": "to investigate carefully (and pass as satisfactory)",
        "ex_of_definition_list": [
          "Every member of staff has been vetted by our security department before he starts work here."
        ]
      }
    ],
    "hash_code_list_definition_mean": "1037367612"
  },
  {
    "link_it": "https://github.com/lmbstudiocontact/cb_dmean_5000_it_5/raw/main/vibrate_cb_dmean_5000_it.json",
    "id_item": "vibrate_cb_dmean_5000_it",
    "id_album": "109468095",
    "english": "vibrate",
    "list_mean": [
      "chuyển động, rung, lắc"
    ],
    "hash_code_list_mean": "-844787282",
    "list_img": [
      {
        "link_thumb": "https://live.staticflickr.com/65535/51809460033_aea479d0e8_n.jpg",
        "link_img": "https://live.staticflickr.com/65535/51809460033_b0d3f223c6_o.png",
        "id_image": "vibrate_2313572"
      }
    ],
    "hash_code_list_img": "191520020",
    "list_definition_mean": [
      {
        "mean_english": "chuyển động, rung, lắc",
        "definition": "to (cause to) shake, tremble, or move rapidly back and forth",
        "ex_of_definition_list": [
          "Every sound that we hear is making part of our ear vibrate",
          "The engine has stopped vibrating."
        ]
      }
    ],
    "hash_code_list_definition_mean": "292307955"
  },
  {
    "link_it": "https://github.com/lmbstudiocontact/cb_dmean_5000_it_5/raw/main/vibration_cb_dmean_5000_it.json",
    "id_item": "vibration_cb_dmean_5000_it",
    "id_album": "109468095",
    "english": "vibration",
    "list_mean": [
      "sự rung động, sự chuyển động"
    ],
    "hash_code_list_mean": "-1116568511",
    "list_img": [
      {
        "link_thumb": "https://live.staticflickr.com/65535/51808390137_94bdee9e52_n.jpg",
        "link_img": "https://live.staticflickr.com/65535/51808390137_0476361ed3_o.png",
        "id_image": "vibration_2646891"
      },
      {
        "link_thumb": "https://live.staticflickr.com/65535/51809345151_27b7d706d8_n.jpg",
        "link_img": "https://live.staticflickr.com/65535/51809345151_aa5837453d_o.png",
        "id_image": "vibration_6254024"
      }
    ],
    "hash_code_list_img": "605301311",
    "list_definition_mean": [
      {
        "mean_english": "sự rung động, sự chuyển động",
        "definition": "(an) act of vibrating",
        "ex_of_definition_list": [
          "This building is badly affected by the vibration of all the heavy traffic that passes."
        ]
      }
    ],
    "hash_code_list_definition_mean": "1864083071"
  },
  {
    "link_it": "https://github.com/lmbstudiocontact/cb_dmean_5000_it_5/raw/main/victim_cb_dmean_5000_it.json",
    "id_item": "victim_cb_dmean_5000_it",
    "id_album": "109468095",
    "english": "victim",
    "list_mean": [
      "nạn nhân"
    ],
    "hash_code_list_mean": "-1607872182",
    "list_img": [
      {
        "link_thumb": "https://live.staticflickr.com/65535/51809345036_385caec6f5_n.jpg",
        "link_img": "https://live.staticflickr.com/65535/51809345036_f6c648404d_o.png",
        "id_image": "victim_2117465"
      },
      {
        "link_thumb": "https://live.staticflickr.com/65535/51808389982_3f09b0ddbf_n.jpg",
        "link_img": "https://live.staticflickr.com/65535/51808389982_f6628e3942_o.png",
        "id_image": "victim_2155410"
      },
      {
        "link_thumb": "https://live.staticflickr.com/65535/51810082475_f12663411a_n.jpg",
        "link_img": "https://live.staticflickr.com/65535/51810082475_efcbc55887_o.png",
        "id_image": "victim_5781221"
      }
    ],
    "hash_code_list_img": "-1924536720",
    "list_definition_mean": [
      {
        "mean_english": "nạn nhân",
        "definition": "a person who receives ill-treatment, injury etc",
        "ex_of_definition_list": [
          "a murder victim",
          "Food is being sent to the victims of the disaster."
        ]
      }
    ],
    "hash_code_list_definition_mean": "1887005504"
  },
  {
    "link_it": "https://github.com/lmbstudiocontact/cb_dmean_5000_it_5/raw/main/victory_cb_dmean_5000_it.json",
    "id_item": "victory_cb_dmean_5000_it",
    "id_album": "109468095",
    "english": "victory",
    "list_mean": [
      "chiến thắng"
    ],
    "hash_code_list_mean": "2133388454",
    "list_img": [
      {
        "link_thumb": "https://live.staticflickr.com/65535/51810082405_b99f8d6ac4_n.jpg",
        "link_img": "https://live.staticflickr.com/65535/51810082405_88cc54db32_o.png",
        "id_image": "victory_1403214"
      },
      {
        "link_thumb": "https://live.staticflickr.com/65535/51810082375_7b267c2744_n.jpg",
        "link_img": "https://live.staticflickr.com/65535/51810082375_a2854d678a_o.png",
        "id_image": "victory_1610509"
      },
      {
        "link_thumb": "https://live.staticflickr.com/65535/51809459763_e5b92e649a_n.jpg",
        "link_img": "https://live.staticflickr.com/65535/51809459763_95918b5f3f_o.png",
        "id_image": "victory_366452"
      },
      {
        "link_thumb": "https://live.staticflickr.com/65535/51809699984_ffda313828_n.jpg",
        "link_img": "https://live.staticflickr.com/65535/51809699984_7719978654_o.png",
        "id_image": "victory_5521329"
      }
    ],
    "hash_code_list_img": "1757250289",
    "list_definition_mean": [
      {
        "mean_english": "chiến thắng",
        "definition": "(a) defeat of an enemy or rival",
        "ex_of_definition_list": [
          "Our team has had two defeats and eight victories",
          "At last they experienced the joy of victory."
        ]
      }
    ],
    "hash_code_list_definition_mean": "106291267"
  },
  {
    "link_it": "https://github.com/lmbstudiocontact/cb_dmean_5000_it_5/raw/main/videotape_cb_dmean_5000_it.json",
    "id_item": "videotape_cb_dmean_5000_it",
    "id_album": "109468095",
    "english": "videotape",
    "list_mean": [
      "băng viđêô",
      "thâu vào băng viđêô"
    ],
    "hash_code_list_mean": "408104053",
    "list_img": [
      {
        "link_thumb": "https://live.staticflickr.com/65535/51809344651_171cf6daf5_n.jpg",
        "link_img": "https://live.staticflickr.com/65535/51809344651_1996001784_o.png",
        "id_image": "videotape_2621279"
      },
      {
        "link_thumb": "https://live.staticflickr.com/65535/51809459418_595671d0d3_n.jpg",
        "link_img": "https://live.staticflickr.com/65535/51809459418_affab0d1dc_o.png",
        "id_image": "videotape_3172558"
      },
      {
        "link_thumb": "https://live.staticflickr.com/65535/51809699679_e530fbd12e_n.jpg",
        "link_img": "https://live.staticflickr.com/65535/51809699679_c75bed08ab_o.png",
        "id_image": "videotape_4028458"
      },
      {
        "link_thumb": "https://live.staticflickr.com/65535/51809459353_f63a1e624c_n.jpg",
        "link_img": "https://live.staticflickr.com/65535/51809459353_9ea112659a_o.png",
        "id_image": "videotape_4321497"
      }
    ],
    "hash_code_list_img": "1881014751",
    "list_definition_mean": [
      {
        "mean_english": "băng viđêô",
        "definition": "a magnetic tape for recording video films",
        "ex_of_definition_list": [
          "The thieves were caught on videotape."
        ]
      }
    ],
    "hash_code_list_definition_mean": "1788961078"
  },
  {
    "link_it": "https://github.com/lmbstudiocontact/cb_dmean_5000_it_5/raw/main/video_cb_dmean_5000_it.json",
    "id_item": "video_cb_dmean_5000_it",
    "id_album": "109468095",
    "english": "video",
    "list_mean": [
      "viđêô",
      "băng viđêô",
      "đầu máy viđêô",
      "thu vào băng viđêô"
    ],
    "hash_code_list_mean": "744093003",
    "list_img": [
      {
        "link_thumb": "https://live.staticflickr.com/65535/51809699869_547130c2be_n.jpg",
        "link_img": "https://live.staticflickr.com/65535/51809699869_860b935a05_o.png",
        "id_image": "video_1246622"
      },
      {
        "link_thumb": "https://live.staticflickr.com/65535/51808389742_d3e9e3fbbc_n.jpg",
        "link_img": "https://live.staticflickr.com/65535/51808389742_c8a45350e0_o.png",
        "id_image": "video_183606"
      },
      {
        "link_thumb": "https://live.staticflickr.com/65535/51809699899_152ef15491_n.jpg",
        "link_img": "https://live.staticflickr.com/65535/51809699899_8a7d9ded37_o.png",
        "id_image": "video_563034"
      }
    ],
    "hash_code_list_img": "-901671445",
    "list_definition_mean": [
      {
        "mean_english": "viđêô",
        "definition": "the recording or broadcasting (by means of a video recorder) of television pictures and sound",
        "ex_of_definition_list": [
          "The police sometimes use video to record interviews."
        ]
      },
      {
        "mean_english": "băng viđêô",
        "definition": "a videotape",
        "ex_of_definition_list": [
          "There’s a great video I want to show you."
        ]
      },
      {
        "mean_english": "thu vào băng viđêô",
        "definition": "to record on a video recorder or videotape",
        "ex_of_definition_list": [
          "He videoed a television programme on volcanoes."
        ]
      }
    ],
    "hash_code_list_definition_mean": "-1160329271"
  },
  {
    "link_it": "https://github.com/lmbstudiocontact/cb_dmean_5000_it_5/raw/main/viewer_cb_dmean_5000_it.json",
    "id_item": "viewer_cb_dmean_5000_it",
    "id_album": "109468095",
    "english": "viewer",
    "list_mean": [
      "người xem",
      "dụng cụ xem phim đèn chiếu"
    ],
    "hash_code_list_mean": "-594279645",
    "list_img": [
      {
        "link_thumb": "https://live.staticflickr.com/65535/51809699599_267efd8e86_n.jpg",
        "link_img": "https://live.staticflickr.com/65535/51809699599_2cc55893d0_o.png",
        "id_image": "viewer_1390265"
      },
      {
        "link_thumb": "https://live.staticflickr.com/65535/51810081885_0a32f0036b_n.jpg",
        "link_img": "https://live.staticflickr.com/65535/51810081885_57ce061105_o.png",
        "id_image": "viewer_2201281"
      },
      {
        "link_thumb": "https://live.staticflickr.com/65535/51809699504_5b3277e5a1_n.jpg",
        "link_img": "https://live.staticflickr.com/65535/51809699504_45c4f3e74e_o.png",
        "id_image": "viewer_4443792"
      },
      {
        "link_thumb": "https://live.staticflickr.com/65535/51810081795_581f51fc3d_n.jpg",
        "link_img": "https://live.staticflickr.com/65535/51810081795_47a786f672_o.png",
        "id_image": "viewer_5853632"
      }
    ],
    "hash_code_list_img": "-1360336128",
    "list_definition_mean": [
      {
        "mean_english": "người xem",
        "definition": "a person who watches television",
        "ex_of_definition_list": [
          "This programme regularly has five million viewers."
        ]
      }
    ],
    "hash_code_list_definition_mean": "1049646034"
  },
  {
    "link_it": "https://github.com/lmbstudiocontact/cb_dmean_5000_it_5/raw/main/view_cb_dmean_5000_it.json",
    "id_item": "view_cb_dmean_5000_it",
    "id_album": "109468095",
    "english": "view",
    "list_mean": [
      "quang cảnh",
      "quan điểm",
      "sự nhìn, tầm mắt",
      "nhìn, đánh giá"
    ],
    "hash_code_list_mean": "-1770499571",
    "list_img": [
      {
        "link_thumb": "https://live.staticflickr.com/65535/51809699634_d45ed68c92_n.jpg",
        "link_img": "https://live.staticflickr.com/65535/51809699634_dc0ac8ba52_o.png",
        "id_image": "view_2033280"
      },
      {
        "link_thumb": "https://live.staticflickr.com/65535/51808389442_9bc2ffd822_n.jpg",
        "link_img": "https://live.staticflickr.com/65535/51808389442_2179cbf243_o.png",
        "id_image": "view_4470917"
      }
    ],
    "hash_code_list_img": "-1355321318",
    "list_definition_mean": [
      {
        "mean_english": "quang cảnh",
        "definition": "(an outlook on to, or picture of) a scene",
        "ex_of_definition_list": [
          "Your house has a fine view of the hills",
          "He painted a view of the harbour."
        ]
      },
      {
        "mean_english": "quan điểm",
        "definition": "an opinion",
        "ex_of_definition_list": [
          "Tell me your view/views on the subject."
        ]
      },
      {
        "mean_english": "sự nhìn, tầm mắt",
        "definition": "an act of seeing or inspecting",
        "ex_of_definition_list": [
          "We were given a private view of the exhibition before it was opened to the public."
        ]
      },
      {
        "mean_english": "nhìn, đánh giá",
        "definition": "to look at, or regard (something)",
        "ex_of_definition_list": [
          "She viewed the scene with astonishment."
        ]
      }
    ],
    "hash_code_list_definition_mean": "-841280068"
  },
  {
    "link_it": "https://github.com/lmbstudiocontact/cb_dmean_5000_it_5/raw/main/vigilance_cb_dmean_5000_it.json",
    "id_item": "vigilance_cb_dmean_5000_it",
    "id_album": "109468095",
    "english": "vigilance",
    "list_mean": [
      "sự cảnh giác"
    ],
    "hash_code_list_mean": "1118557031",
    "list_img": [
      {
        "link_thumb": "https://live.staticflickr.com/65535/51809458888_163cacaa90_n.jpg",
        "link_img": "https://live.staticflickr.com/65535/51809458888_ff54c0e4c8_o.png",
        "id_image": "vigilance_1088917"
      },
      {
        "link_thumb": "https://live.staticflickr.com/65535/51810081525_a9dc5c4f8e_n.jpg",
        "link_img": "https://live.staticflickr.com/65535/51810081525_fd0e851341_o.png",
        "id_image": "vigilance_4310484"
      },
      {
        "link_thumb": "https://live.staticflickr.com/65535/51810081460_c9e4b4f197_n.jpg",
        "link_img": "https://live.staticflickr.com/65535/51810081460_595f2e99ee_o.png",
        "id_image": "vigilance_4412774"
      },
      {
        "link_thumb": "https://live.staticflickr.com/65535/51808389117_e4fc973ac8_n.jpg",
        "link_img": "https://live.staticflickr.com/65535/51808389117_a952491c79_o.png",
        "id_image": "vigilance_708645"
      }
    ],
    "hash_code_list_img": "756478598",
    "list_definition_mean": [
      {
        "mean_english": "sự cảnh giác",
        "definition": "watchfulness or readiness for danger",
        "ex_of_definition_list": [
          "He watched her with the vigilance of a hawk."
        ]
      }
    ],
    "hash_code_list_definition_mean": "1690105512"
  },
  {
    "link_it": "https://github.com/lmbstudiocontact/cb_dmean_5000_it_5/raw/main/village_cb_dmean_5000_it.json",
    "id_item": "village_cb_dmean_5000_it",
    "id_album": "109468095",
    "english": "village",
    "list_mean": [
      "ngôi làng",
      "dân làng"
    ],
    "hash_code_list_mean": "-1778704609",
    "list_img": [
      {
        "link_thumb": "https://live.staticflickr.com/65535/51808388752_cc107d4cf2_n.jpg",
        "link_img": "https://live.staticflickr.com/65535/51808388752_675d56fc03_o.png",
        "id_image": "village_1151658"
      },
      {
        "link_thumb": "https://live.staticflickr.com/65535/51809343901_2b7371a385_n.jpg",
        "link_img": "https://live.staticflickr.com/65535/51809343901_237ca55d3b_o.png",
        "id_image": "village_804540"
      }
    ],
    "hash_code_list_img": "-1682236579",
    "list_definition_mean": [
      {
        "mean_english": "ngôi làng",
        "definition": "a group of houses etc which is smaller than a town",
        "ex_of_definition_list": [
          "They live in a little village",
          "(also adjective) a village school."
        ]
      },
      {
        "mean_english": "dân làng",
        "definition": "the people who live in such a group of houses",
        "ex_of_definition_list": [
          "The whole village turned out to see the celebrations."
        ]
      }
    ],
    "hash_code_list_definition_mean": "-950240182"
  },
  {
    "link_it": "https://github.com/lmbstudiocontact/cb_dmean_5000_it_5/raw/main/villain_cb_dmean_5000_it.json",
    "id_item": "villain_cb_dmean_5000_it",
    "id_album": "109468095",
    "english": "villain",
    "list_mean": [
      "tên côn đồ"
    ],
    "hash_code_list_mean": "770592332",
    "list_img": [
      {
        "link_thumb": "https://live.staticflickr.com/65535/51810081125_7157e9dc39_n.jpg",
        "link_img": "https://live.staticflickr.com/65535/51810081125_32b9a4dd18_o.png",
        "id_image": "villain_2155380"
      },
      {
        "link_thumb": "https://live.staticflickr.com/65535/51809343701_49c68eb333_n.jpg",
        "link_img": "https://live.staticflickr.com/65535/51809343701_e8f619c3c7_o.png",
        "id_image": "villain_5039273"
      },
      {
        "link_thumb": "https://live.staticflickr.com/65535/51809698854_b45dab208f_n.jpg",
        "link_img": "https://live.staticflickr.com/65535/51809698854_e34c5ea8ed_o.png",
        "id_image": "villain_5039320"
      }
    ],
    "hash_code_list_img": "517081837",
    "list_definition_mean": [
      {
        "mean_english": "tên côn đồ",
        "definition": "a person who is wicked or of very bad character",
        "ex_of_definition_list": [
          "the villain of the play/story."
        ]
      }
    ],
    "hash_code_list_definition_mean": "829057098"
  },
  {
    "link_it": "https://github.com/lmbstudiocontact/cb_dmean_5000_it_5/raw/main/villa_cb_dmean_5000_it.json",
    "id_item": "villa_cb_dmean_5000_it",
    "id_album": "109468095",
    "english": "villa",
    "list_mean": [
      "biệt thự"
    ],
    "hash_code_list_mean": "34312720",
    "list_img": [
      {
        "link_thumb": "https://live.staticflickr.com/65535/51809458693_bd7f6ac509_n.jpg",
        "link_img": "https://live.staticflickr.com/65535/51809458693_23e1e9e80a_o.png",
        "id_image": "villa_2038457"
      },
      {
        "link_thumb": "https://live.staticflickr.com/65535/51809458668_e220e82b3c_n.jpg",
        "link_img": "https://live.staticflickr.com/65535/51809458668_9c329f4d38_o.png",
        "id_image": "villa_6250457"
      }
    ],
    "hash_code_list_img": "1349531612",
    "list_definition_mean": [
      {
        "mean_english": "biệt thự",
        "definition": "a type of detached or semi-detached (usually luxury) house, in the country or suburbs, or used for holidays at the seaside",
        "ex_of_definition_list": [
          "They have a villa at the seaside."
        ]
      }
    ],
    "hash_code_list_definition_mean": "1896206992"
  },
  {
    "link_it": "https://github.com/lmbstudiocontact/cb_dmean_5000_it_5/raw/main/vinegar_cb_dmean_5000_it.json",
    "id_item": "vinegar_cb_dmean_5000_it",
    "id_album": "109468095",
    "english": "vinegar",
    "list_mean": [
      "giấm"
    ],
    "hash_code_list_mean": "3412713",
    "list_img": [
      {
        "link_thumb": "https://live.staticflickr.com/65535/51809698814_c2abd31ec8_n.jpg",
        "link_img": "https://live.staticflickr.com/65535/51809698814_149de92783_o.png",
        "id_image": "vinegar_129206"
      },
      {
        "link_thumb": "https://live.staticflickr.com/65535/51808388517_2aecb73436_n.jpg",
        "link_img": "https://live.staticflickr.com/65535/51808388517_2436c620af_o.png",
        "id_image": "vinegar_184494"
      },
      {
        "link_thumb": "https://live.staticflickr.com/65535/51809458258_e0aba577f9_n.jpg",
        "link_img": "https://live.staticflickr.com/65535/51809458258_1bbc0290de_o.png",
        "id_image": "vinegar_2166168"
      }
    ],
    "hash_code_list_img": "131913826",
    "list_definition_mean": [
      {
        "mean_english": "giấm",
        "definition": "a sour liquid made from wine, beer etc, used in seasoning or preparing food",
        "ex_of_definition_list": [
          "Mix some oil and vinegar as a dressing for the salad."
        ]
      }
    ],
    "hash_code_list_definition_mean": "1919349077"
  },
  {
    "link_it": "https://github.com/lmbstudiocontact/cb_dmean_5000_it_5/raw/main/vineyard_cb_dmean_5000_it.json",
    "id_item": "vineyard_cb_dmean_5000_it",
    "id_album": "109468095",
    "english": "vineyard",
    "list_mean": [
      "vườn nho"
    ],
    "hash_code_list_mean": "-689004769",
    "list_img": [
      {
        "link_thumb": "https://live.staticflickr.com/65535/51809458248_891aef42ec_n.jpg",
        "link_img": "https://live.staticflickr.com/65535/51809458248_fa7fb08778_o.png",
        "id_image": "vineyard_2036713"
      },
      {
        "link_thumb": "https://live.staticflickr.com/65535/51809458208_01a0779922_n.jpg",
        "link_img": "https://live.staticflickr.com/65535/51809458208_0f5623624a_o.png",
        "id_image": "vineyard_4252578"
      },
      {
        "link_thumb": "https://live.staticflickr.com/65535/51809343471_9e11c8166b_n.jpg",
        "link_img": "https://live.staticflickr.com/65535/51809343471_30f920e681_o.png",
        "id_image": "vineyard_4698460"
      }
    ],
    "hash_code_list_img": "-383821163",
    "list_definition_mean": [
      {
        "mean_english": "vườn nho",
        "definition": "an area which is planted with grape vines",
        "ex_of_definition_list": [
          "We spent the summer touring the French vineyards."
        ]
      }
    ],
    "hash_code_list_definition_mean": "1454675257"
  },
  {
    "link_it": "https://github.com/lmbstudiocontact/cb_dmean_5000_it_5/raw/main/vintage_cb_dmean_5000_it.json",
    "id_item": "vintage_cb_dmean_5000_it",
    "id_album": "109468095",
    "english": "vintage",
    "list_mean": [
      "mùa hái nho"
    ],
    "hash_code_list_mean": "775233177",
    "list_img": [
      {
        "link_thumb": "https://live.staticflickr.com/65535/51810080795_9336d5ba53_n.jpg",
        "link_img": "https://live.staticflickr.com/65535/51810080795_ebc5e6f1d2_o.png",
        "id_image": "vintage_2454188"
      },
      {
        "link_thumb": "https://live.staticflickr.com/65535/51808388257_e4640bdf8f_n.jpg",
        "link_img": "https://live.staticflickr.com/65535/51808388257_5e11663371_o.png",
        "id_image": "vintage_2569980"
      },
      {
        "link_thumb": "https://live.staticflickr.com/65535/51809698504_8b51a362a5_n.jpg",
        "link_img": "https://live.staticflickr.com/65535/51809698504_da60d282d5_o.png",
        "id_image": "vintage_2818433"
      },
      {
        "link_thumb": "https://live.staticflickr.com/65535/51810080890_7160f6935b_n.jpg",
        "link_img": "https://live.staticflickr.com/65535/51810080890_5529716dab_o.png",
        "id_image": "vintage_948501"
      },
      {
        "link_thumb": "https://live.staticflickr.com/65535/51809458083_94d08ee4cf_n.jpg",
        "link_img": "https://live.staticflickr.com/65535/51809458083_9ec254627a_o.png",
        "id_image": "vintage_964029"
      }
    ],
    "hash_code_list_img": "1446646866",
    "list_definition_mean": [
      {
        "mean_english": "mùa hái nho",
        "definition": "(a wine from) the grape-harvest of a certain (particularly good) year",
        "ex_of_definition_list": [
          "What vintage is this wine?",
          "a vintage year (= a year in which good wine was produced)",
          "vintage port (= port from a vintage year)."
        ]
      }
    ],
    "hash_code_list_definition_mean": "123788418"
  },
  {
    "link_it": "https://github.com/lmbstudiocontact/cb_dmean_5000_it_5/raw/main/viola_cb_dmean_5000_it.json",
    "id_item": "viola_cb_dmean_5000_it",
    "id_album": "109468095",
    "english": "viola",
    "list_mean": [
      "đàn viôla"
    ],
    "hash_code_list_mean": "-96706828",
    "list_img": [
      {
        "link_thumb": "https://live.staticflickr.com/65535/51810080705_29dff42c2e_n.jpg",
        "link_img": "https://live.staticflickr.com/65535/51810080705_a0240e8c23_o.png",
        "id_image": "viola_3754961"
      }
    ],
    "hash_code_list_img": "1250128941",
    "list_definition_mean": [
      {
        "mean_english": "đàn viôla",
        "definition": "a type of musical instrument very similar to, but slightly larger than, the violin",
        "ex_of_definition_list": [
          "She plays the viola in the school orchestra."
        ]
      }
    ],
    "hash_code_list_definition_mean": "1313126194"
  },
  {
    "link_it": "https://github.com/lmbstudiocontact/cb_dmean_5000_it_5/raw/main/violence_cb_dmean_5000_it.json",
    "id_item": "violence_cb_dmean_5000_it",
    "id_album": "109468095",
    "english": "violence",
    "list_mean": [
      "sự hung dữ"
    ],
    "hash_code_list_mean": "-1644254014",
    "list_img": [
      {
        "link_thumb": "https://live.staticflickr.com/65535/51810080690_eee7bca708_n.jpg",
        "link_img": "https://live.staticflickr.com/65535/51810080690_c492f29cd8_o.png",
        "id_image": "violence_5020360"
      },
      {
        "link_thumb": "https://live.staticflickr.com/65535/51810080635_ab199447da_n.jpg",
        "link_img": "https://live.staticflickr.com/65535/51810080635_e1c5130a2e_o.png",
        "id_image": "violence_5020981"
      }
    ],
    "hash_code_list_img": "-1855510596",
    "list_definition_mean": [
      {
        "mean_english": "sự hung dữ",
        "definition": "great roughness and force, often causing severe physical injury or damage",
        "ex_of_definition_list": [
          "I was amazed at the violence of his temper",
          "She was terrified by the violence of the storm."
        ]
      }
    ],
    "hash_code_list_definition_mean": "1568872902"
  },
  {
    "link_it": "https://github.com/lmbstudiocontact/cb_dmean_5000_it_5/raw/main/violent_cb_dmean_5000_it.json",
    "id_item": "violent_cb_dmean_5000_it",
    "id_album": "109468095",
    "english": "violent",
    "list_mean": [
      "hung dữ"
    ],
    "hash_code_list_mean": "1265410564",
    "list_img": [
      {
        "link_thumb": "https://live.staticflickr.com/65535/51809698354_7333cb8509_n.jpg",
        "link_img": "https://live.staticflickr.com/65535/51809698354_ef0c32bdb5_o.png",
        "id_image": "violent_6305773"
      }
    ],
    "hash_code_list_img": "7318083",
    "list_definition_mean": [
      {
        "mean_english": "hung dữ",
        "definition": "having, using, or showing, great force",
        "ex_of_definition_list": [
          "There was a violent storm at sea",
          "a violent earthquake",
          "He has a violent temper."
        ]
      },
      {
        "mean_english": "hung dữ",
        "definition": "caused by force",
        "ex_of_definition_list": [
          "a violent death."
        ]
      }
    ],
    "hash_code_list_definition_mean": "-1246156322"
  },
  {
    "link_it": "https://github.com/lmbstudiocontact/cb_dmean_5000_it_5/raw/main/violinist_cb_dmean_5000_it.json",
    "id_item": "violinist_cb_dmean_5000_it",
    "id_album": "109468095",
    "english": "violinist",
    "list_mean": [
      "người chơi vĩ cầm"
    ],
    "hash_code_list_mean": "950437777",
    "list_img": [
      {
        "link_thumb": "https://live.staticflickr.com/65535/51810080460_85214d8521_n.jpg",
        "link_img": "https://live.staticflickr.com/65535/51810080460_6727b9532e_o.png",
        "id_image": "violinist_4780244"
      }
    ],
    "hash_code_list_img": "1087052276",
    "list_definition_mean": [
      {
        "mean_english": "người chơi vĩ cầm",
        "definition": "a violin player",
        "ex_of_definition_list": [
          "She is a leading violinist."
        ]
      }
    ],
    "hash_code_list_definition_mean": "1875849649"
  },
  {
    "link_it": "https://github.com/lmbstudiocontact/cb_dmean_5000_it_5/raw/main/violin_cb_dmean_5000_it.json",
    "id_item": "violin_cb_dmean_5000_it",
    "id_album": "109468095",
    "english": "violin",
    "list_mean": [
      "vĩ cầm"
    ],
    "hash_code_list_mean": "-641149893",
    "list_img": [
      {
        "link_thumb": "https://live.staticflickr.com/65535/51809343066_3d71893ba8_n.jpg",
        "link_img": "https://live.staticflickr.com/65535/51809343066_763128ff76_o.png",
        "id_image": "violin_2776318"
      },
      {
        "link_thumb": "https://live.staticflickr.com/65535/51808387992_2d575c6aa1_n.jpg",
        "link_img": "https://live.staticflickr.com/65535/51808387992_920a1829c5_o.png",
        "id_image": "violin_4424670"
      }
    ],
    "hash_code_list_img": "-1585007199",
    "list_definition_mean": [
      {
        "mean_english": "vĩ cầm",
        "definition": "a type of musical instrument with four strings, played with a bow",
        "ex_of_definition_list": [
          "She played the violin in the school orchestra",
          "Can you play that on the violin?"
        ]
      }
    ],
    "hash_code_list_definition_mean": "1910056102"
  },
  {
    "link_it": "https://github.com/lmbstudiocontact/cb_dmean_5000_it_5/raw/main/viral_cb_dmean_5000_it.json",
    "id_item": "viral_cb_dmean_5000_it",
    "id_album": "109468095",
    "english": "viral",
    "list_mean": [
      "thuộc virus",
      "lan truyền rất nhanh"
    ],
    "hash_code_list_mean": "14077009",
    "list_img": [
      {
        "link_thumb": "https://live.staticflickr.com/65535/51810080325_65ab871123_n.jpg",
        "link_img": "https://live.staticflickr.com/65535/51810080325_0c3955f022_o.png",
        "id_image": "viral_1999369"
      },
      {
        "link_thumb": "https://live.staticflickr.com/65535/51810080280_723b5e6cc2_n.jpg",
        "link_img": "https://live.staticflickr.com/65535/51810080280_f8cd5b4bf8_o.png",
        "id_image": "viral_2132656"
      }
    ],
    "hash_code_list_img": "2054552611",
    "list_definition_mean": [
      {
        "mean_english": "thuộc virus",
        "definition": "relating to or caused by a virus",
        "ex_of_definition_list": [
          "a viral infection/disease."
        ]
      }
    ],
    "hash_code_list_definition_mean": "38984366"
  },
  {
    "link_it": "https://github.com/lmbstudiocontact/cb_dmean_5000_it_5/raw/main/virtual_cb_dmean_5000_it.json",
    "id_item": "virtual_cb_dmean_5000_it",
    "id_album": "109468095",
    "english": "virtual",
    "list_mean": [
      "thực sự"
    ],
    "hash_code_list_mean": "1576910423",
    "list_img": [
      {
        "link_thumb": "https://live.staticflickr.com/65535/51809457593_1dea4f39aa_n.jpg",
        "link_img": "https://live.staticflickr.com/65535/51809457593_7c5c347f90_o.png",
        "id_image": "virtual_2598494"
      }
    ],
    "hash_code_list_img": "401882985",
    "list_definition_mean": [
      {
        "mean_english": "thực sự",
        "definition": "almost (as described), though not exactly in every way",
        "ex_of_definition_list": [
          "a virtual collapse of the economy."
        ]
      }
    ],
    "hash_code_list_definition_mean": "65407802"
  },
  {
    "link_it": "https://github.com/lmbstudiocontact/cb_dmean_5000_it_5/raw/main/visibility_cb_dmean_5000_it.json",
    "id_item": "visibility_cb_dmean_5000_it",
    "id_album": "109468095",
    "english": "visibility",
    "list_mean": [
      "tình trạng có thể thấy được"
    ],
    "hash_code_list_mean": "-582495513",
    "list_img": [
      {
        "link_thumb": "https://live.staticflickr.com/65535/51809697794_c44eb01c07_n.jpg",
        "link_img": "https://live.staticflickr.com/65535/51809697794_d7b951472f_o.png",
        "id_image": "visibility_2765236"
      },
      {
        "link_thumb": "https://live.staticflickr.com/65535/51810080115_e803712e88_n.jpg",
        "link_img": "https://live.staticflickr.com/65535/51810080115_fc3c57ba8a_o.png",
        "id_image": "visibility_283662"
      },
      {
        "link_thumb": "https://live.staticflickr.com/65535/51809342556_a4bcb77790_n.jpg",
        "link_img": "https://live.staticflickr.com/65535/51809342556_aab997b6d1_o.png",
        "id_image": "visibility_296926"
      }
    ],
    "hash_code_list_img": "-172354037",
    "list_definition_mean": [
      {
        "mean_english": "tình trạng có thể thấy được",
        "definition": "the range of distance over which things may be (clearly) seen",
        "ex_of_definition_list": [
          "Visibility is poor today",
          "Visibility in the fog was down to twenty yards in places."
        ]
      }
    ],
    "hash_code_list_definition_mean": "339393344"
  },
  {
    "link_it": "https://github.com/lmbstudiocontact/cb_dmean_5000_it_5/raw/main/visible_cb_dmean_5000_it.json",
    "id_item": "visible_cb_dmean_5000_it",
    "id_album": "109468095",
    "english": "visible",
    "list_mean": [
      "hữu hình"
    ],
    "hash_code_list_mean": "1526326639",
    "list_img": [
      {
        "link_thumb": "https://live.staticflickr.com/65535/51809342476_78075bc1e2_n.jpg",
        "link_img": "https://live.staticflickr.com/65535/51809342476_c9c5a42a47_o.png",
        "id_image": "visible_169124"
      },
      {
        "link_thumb": "https://live.staticflickr.com/65535/51808387512_345b9c1baf_n.jpg",
        "link_img": "https://live.staticflickr.com/65535/51808387512_b9f415a28e_o.png",
        "id_image": "visible_5875369"
      }
    ],
    "hash_code_list_img": "1987317065",
    "list_definition_mean": [
      {
        "mean_english": "hữu hình",
        "definition": "able to be seen",
        "ex_of_definition_list": [
          "The house is visible through the trees",
          "The scar on her face is scarcely visible now."
        ]
      }
    ],
    "hash_code_list_definition_mean": "470046179"
  },
  {
    "link_it": "https://github.com/lmbstudiocontact/cb_dmean_5000_it_5/raw/main/vision_cb_dmean_5000_it.json",
    "id_item": "vision_cb_dmean_5000_it",
    "id_album": "109468095",
    "english": "vision",
    "list_mean": [
      "điều mơ thấy, cảnh mộng",
      "tầm nhìn rộng",
      "thị lực"
    ],
    "hash_code_list_mean": "295854093",
    "list_img": [
      {
        "link_thumb": "https://live.staticflickr.com/65535/51809457213_5fa48b83f1_n.jpg",
        "link_img": "https://live.staticflickr.com/65535/51809457213_b55a8105b0_o.png",
        "id_image": "vision_1286107"
      },
      {
        "link_thumb": "https://live.staticflickr.com/65535/51810079780_f3938f6ee5_n.jpg",
        "link_img": "https://live.staticflickr.com/65535/51810079780_a1f9359b9d_o.png",
        "id_image": "vision_1640971"
      },
      {
        "link_thumb": "https://live.staticflickr.com/65535/51810079940_5c5504a1d0_n.jpg",
        "link_img": "https://live.staticflickr.com/65535/51810079940_f4024a8262_o.png",
        "id_image": "vision_562539"
      },
      {
        "link_thumb": "https://live.staticflickr.com/65535/51809342386_720d78dd62_n.jpg",
        "link_img": "https://live.staticflickr.com/65535/51809342386_000808d894_o.png",
        "id_image": "vision_997259"
      }
    ],
    "hash_code_list_img": "-345831327",
    "list_definition_mean": [
      {
        "mean_english": "điều mơ thấy, cảnh mộng",
        "definition": "something seen in the imagination or in a dream",
        "ex_of_definition_list": [
          "God appeared to him in a vision."
        ]
      },
      {
        "mean_english": "tầm nhìn rộng",
        "definition": "the ability to see or plan into the future",
        "ex_of_definition_list": [
          "Politicians should be men of vision."
        ]
      },
      {
        "mean_english": "thị lực",
        "definition": "the ability to see or the sense of sight",
        "ex_of_definition_list": [
          "He is slowly losing his vision."
        ]
      }
    ],
    "hash_code_list_definition_mean": "1866824050"
  },
  {
    "link_it": "https://github.com/lmbstudiocontact/cb_dmean_5000_it_5/raw/main/visitor_cb_dmean_5000_it.json",
    "id_item": "visitor_cb_dmean_5000_it",
    "id_album": "109468095",
    "english": "visitor",
    "list_mean": [
      "khách du lịch"
    ],
    "hash_code_list_mean": "-767080389",
    "list_img": [
      {
        "link_thumb": "https://live.staticflickr.com/65535/51810079640_9dfb56ffa0_n.jpg",
        "link_img": "https://live.staticflickr.com/65535/51810079640_18c3f5c908_o.png",
        "id_image": "visitor_4615753"
      },
      {
        "link_thumb": "https://live.staticflickr.com/65535/51809697444_2b9e9cbc26_n.jpg",
        "link_img": "https://live.staticflickr.com/65535/51809697444_ca80a0eeb7_o.png",
        "id_image": "visitor_827057"
      },
      {
        "link_thumb": "https://live.staticflickr.com/65535/51809342236_a972ac57bd_n.jpg",
        "link_img": "https://live.staticflickr.com/65535/51809342236_fe8fe044fc_o.png",
        "id_image": "visitor_874676"
      }
    ],
    "hash_code_list_img": "-1493036969",
    "list_definition_mean": [
      {
        "mean_english": "khách du lịch",
        "definition": "a person who visits, socially or professionally",
        "ex_of_definition_list": [
          "I’m expecting visitors from America",
          "We’re having visitors next week."
        ]
      }
    ],
    "hash_code_list_definition_mean": "399419032"
  },
  {
    "link_it": "https://github.com/lmbstudiocontact/cb_dmean_5000_it_5/raw/main/visualize_cb_dmean_5000_it.json",
    "id_item": "visualize_cb_dmean_5000_it",
    "id_album": "109468095",
    "english": "visualize",
    "list_mean": [
      "hình dung"
    ],
    "hash_code_list_mean": "1840912075",
    "list_img": [
      {
        "link_thumb": "https://live.staticflickr.com/65535/51809697059_06d36f57f9_n.jpg",
        "link_img": "https://live.staticflickr.com/65535/51809697059_5f3fca58fd_o.png",
        "id_image": "visualize_3062435"
      }
    ],
    "hash_code_list_img": "583361866",
    "list_definition_mean": [
      {
        "mean_english": "hình dung",
        "definition": "to form a picture of someone or something in your mind",
        "ex_of_definition_list": [
          "These models let forecasters visualize how the storm is forming and what direction it will move."
        ]
      }
    ],
    "hash_code_list_definition_mean": "1553169585"
  },
  {
    "link_it": "https://github.com/lmbstudiocontact/cb_dmean_5000_it_5/raw/main/visual_cb_dmean_5000_it.json",
    "id_item": "visual_cb_dmean_5000_it",
    "id_album": "109468095",
    "english": "visual",
    "list_mean": [
      "có liên quan đến thị giác"
    ],
    "hash_code_list_mean": "-2100734516",
    "list_img": [
      {
        "link_thumb": "https://live.staticflickr.com/65535/51809341991_ee821a3947_n.jpg",
        "link_img": "https://live.staticflickr.com/65535/51809341991_dc4a2a3e7e_o.png",
        "id_image": "visual_1296977"
      },
      {
        "link_thumb": "https://live.staticflickr.com/65535/51808386977_946250b423_n.jpg",
        "link_img": "https://live.staticflickr.com/65535/51808386977_0b20669bfb_o.png",
        "id_image": "visual_1792028"
      },
      {
        "link_thumb": "https://live.staticflickr.com/65535/51810079360_9173820193_n.jpg",
        "link_img": "https://live.staticflickr.com/65535/51810079360_fa5a4491c6_o.png",
        "id_image": "visual_6040780"
      }
    ],
    "hash_code_list_img": "-2013295345",
    "list_definition_mean": [
      {
        "mean_english": "có liên quan đến thị giác",
        "definition": "of sight or the process of seeing",
        "ex_of_definition_list": [
          "the visual arts",
          "The film makes use of a variety of spectacular visual effects."
        ]
      }
    ],
    "hash_code_list_definition_mean": "1508962189"
  },
  {
    "link_it": "https://github.com/lmbstudiocontact/cb_dmean_5000_it_5/raw/main/vitamin_cb_dmean_5000_it.json",
    "id_item": "vitamin_cb_dmean_5000_it",
    "id_album": "109468095",
    "english": "vitamin",
    "list_mean": [
      "sinh tố, vitamin"
    ],
    "hash_code_list_mean": "786328656",
    "list_img": [
      {
        "link_thumb": "https://live.staticflickr.com/65535/51810079215_33e6946778_n.jpg",
        "link_img": "https://live.staticflickr.com/65535/51810079215_c175dafcaf_o.png",
        "id_image": "vitamin_4005511"
      },
      {
        "link_thumb": "https://live.staticflickr.com/65535/51809697004_98d616f77e_n.jpg",
        "link_img": "https://live.staticflickr.com/65535/51809697004_ab4697c39f_o.png",
        "id_image": "vitamin_5046988"
      }
    ],
    "hash_code_list_img": "424352847",
    "list_definition_mean": [
      {
        "mean_english": "sinh tố, vitamin",
        "definition": "any of a group of substances necessary for healthy life, different ones occurring in different natural things such as raw fruit, dairy products, fish, meat etc",
        "ex_of_definition_list": [
          "A healthy diet is full of vitamins",
          "Vitamin C is found in fruit and vegetables",
          "(also adjective) vitamin pills."
        ]
      }
    ],
    "hash_code_list_definition_mean": "283618820"
  },
  {
    "link_it": "https://github.com/lmbstudiocontact/cb_dmean_5000_it_5/raw/main/vocabulary_cb_dmean_5000_it.json",
    "id_item": "vocabulary_cb_dmean_5000_it",
    "id_album": "109468095",
    "english": "vocabulary",
    "list_mean": [
      "từ vựng",
      "vốn từ",
      "bảng từ vựng"
    ],
    "hash_code_list_mean": "-342772369",
    "list_img": [
      {
        "link_thumb": "https://live.staticflickr.com/65535/51810078990_b35a096bf9_n.jpg",
        "link_img": "https://live.staticflickr.com/65535/51810078990_611bd06d7f_o.png",
        "id_image": "vocabulary_326905"
      }
    ],
    "hash_code_list_img": "1226651406",
    "list_definition_mean": [
      {
        "mean_english": "từ vựng",
        "definition": "words in general",
        "ex_of_definition_list": [
          "This book contains some difficult vocabulary."
        ]
      },
      {
        "mean_english": "vốn từ",
        "definition": "(the stock of) words known and used eg by one person, or within a particular trade or profession",
        "ex_of_definition_list": [
          "He has a vocabulary of about 20,000 words",
          "the specialized vocabulary of nuclear physics."
        ]
      },
      {
        "mean_english": "bảng từ vựng",
        "definition": "a list of words in alphabetical order with meanings eg added as a supplement to a book dealing with a particular subject",
        "ex_of_definition_list": [
          "This edition of Shakespeare’s plays has a good vocabulary at the back."
        ]
      }
    ],
    "hash_code_list_definition_mean": "1030594432"
  },
  {
    "link_it": "https://github.com/lmbstudiocontact/cb_dmean_5000_it_5/raw/main/vocal_cb_dmean_5000_it.json",
    "id_item": "vocal_cb_dmean_5000_it",
    "id_album": "109468095",
    "english": "vocal",
    "list_mean": [
      "thuộc phát âm",
      "to mồm, lắm tiếng"
    ],
    "hash_code_list_mean": "214727757",
    "list_img": [
      {
        "link_thumb": "https://live.staticflickr.com/65535/51810078950_3d164b3b8d_n.jpg",
        "link_img": "https://live.staticflickr.com/65535/51810078950_4e198fedd8_o.png",
        "id_image": "vocal_122871"
      },
      {
        "link_thumb": "https://live.staticflickr.com/65535/51809456378_1873edfe6e_n.jpg",
        "link_img": "https://live.staticflickr.com/65535/51809456378_b05169c767_o.png",
        "id_image": "vocal_4806603"
      }
    ],
    "hash_code_list_img": "-1107029912",
    "list_definition_mean": [
      {
        "mean_english": "thuộc phát âm",
        "definition": "of, or concerning, the voice",
        "ex_of_definition_list": [
          "the singer’s vocal style."
        ]
      },
      {
        "mean_english": "to mồm, lắm tiếng",
        "definition": "(of a person) talkative; keen to make one’s opinions heard by other people",
        "ex_of_definition_list": [
          "He’s always very vocal at meetings."
        ]
      }
    ],
    "hash_code_list_definition_mean": "2077051361"
  },
  {
    "link_it": "https://github.com/lmbstudiocontact/cb_dmean_5000_it_5/raw/main/voicemail_cb_dmean_5000_it.json",
    "id_item": "voicemail_cb_dmean_5000_it",
    "id_album": "109468095",
    "english": "voicemail",
    "list_mean": [
      "thư thoại"
    ],
    "hash_code_list_mean": "-466428834",
    "list_img": [
      {
        "link_thumb": "https://live.staticflickr.com/65535/51809341286_cd8fa1da02_n.jpg",
        "link_img": "https://live.staticflickr.com/65535/51809341286_d877d36329_o.png",
        "id_image": "voicemail_2482333"
      },
      {
        "link_thumb": "https://live.staticflickr.com/65535/51808386242_f364531009_n.jpg",
        "link_img": "https://live.staticflickr.com/65535/51808386242_28051267a8_o.png",
        "id_image": "voicemail_2934484"
      }
    ],
    "hash_code_list_img": "-1201637004",
    "list_definition_mean": [
      {
        "mean_english": "thư thoại",
        "definition": "a system that stores telephone messages for subscribers to this service",
        "ex_of_definition_list": [
          "Have you checked your voicemail?"
        ]
      }
    ],
    "hash_code_list_definition_mean": "760114129"
  },
  {
    "link_it": "https://github.com/lmbstudiocontact/cb_dmean_5000_it_5/raw/main/voice_cb_dmean_5000_it.json",
    "id_item": "voice_cb_dmean_5000_it",
    "id_album": "109468095",
    "english": "voice",
    "list_mean": [
      "giọng nói, hát",
      "tiếng nói, thế lực",
      "bày tỏ, nói lên",
      "phát thành âm kêu"
    ],
    "hash_code_list_mean": "957365376",
    "list_img": [
      {
        "link_thumb": "https://live.staticflickr.com/65535/51808386352_c8181769c9_n.jpg",
        "link_img": "https://live.staticflickr.com/65535/51808386352_6b1ab1e9b3_o.png",
        "id_image": "voice_2080863"
      },
      {
        "link_thumb": "https://live.staticflickr.com/65535/51808386307_92c2bc3d57_n.jpg",
        "link_img": "https://live.staticflickr.com/65535/51808386307_afdc95f510_o.png",
        "id_image": "voice_2597094"
      },
      {
        "link_thumb": "https://live.staticflickr.com/65535/51809456218_f29f16aa42_n.jpg",
        "link_img": "https://live.staticflickr.com/65535/51809456218_7661412653_o.png",
        "id_image": "voice_450461"
      }
    ],
    "hash_code_list_img": "-53513107",
    "list_definition_mean": [
      {
        "mean_english": "giọng nói, hát",
        "definition": "the sounds from the mouth made in speaking or singing",
        "ex_of_definition_list": [
          "He has a very deep voice",
          "He spoke in a quiet/loud/angry/kind voice."
        ]
      },
      {
        "mean_english": "tiếng nói, thế lực",
        "definition": "the voice regarded as the means of expressing opinion",
        "ex_of_definition_list": [
          "The voice of the people should not be ignored",
          "the voice of reason/conscience."
        ]
      },
      {
        "mean_english": "bày tỏ, nói lên",
        "definition": "to express (feelings etc)",
        "ex_of_definition_list": [
          "He voiced the discontent of the whole group."
        ]
      },
      {
        "mean_english": "phát thành âm kêu",
        "definition": "to produce the sound of (especially a consonant) with a vibration of the vocal cords as well as with the breath",
        "ex_of_definition_list": [
          "‘Th’ should be voiced in ‘this’ but not in ‘think’."
        ]
      }
    ],
    "hash_code_list_definition_mean": "-1437627782"
  },
  {
    "link_it": "https://github.com/lmbstudiocontact/cb_dmean_5000_it_5/raw/main/volcano_cb_dmean_5000_it.json",
    "id_item": "volcano_cb_dmean_5000_it",
    "id_album": "109468095",
    "english": "volcano",
    "list_mean": [
      "núi lửa"
    ],
    "hash_code_list_mean": "1801749916",
    "list_img": [
      {
        "link_thumb": "https://live.staticflickr.com/65535/51810078555_8419f2c2ca_n.jpg",
        "link_img": "https://live.staticflickr.com/65535/51810078555_91bd74ebaf_o.png",
        "id_image": "volcano_3722687"
      },
      {
        "link_thumb": "https://live.staticflickr.com/65535/51808386122_5f2aa48e15_n.jpg",
        "link_img": "https://live.staticflickr.com/65535/51808386122_978ae79c5e_o.png",
        "id_image": "volcano_5641124"
      },
      {
        "link_thumb": "https://live.staticflickr.com/65535/51809696349_0b13445e65_n.jpg",
        "link_img": "https://live.staticflickr.com/65535/51809696349_53fc07ee4b_o.png",
        "id_image": "volcano_6011044"
      }
    ],
    "hash_code_list_img": "1167433630",
    "list_definition_mean": [
      {
        "mean_english": "núi lửa",
        "definition": "a hill or mountain with an opening through which molten rock, ashes etc periodically erupt, or have erupted in the past, from inside the earth",
        "ex_of_definition_list": [
          "The village was destroyed when the volcano erupted."
        ]
      }
    ],
    "hash_code_list_definition_mean": "454897050"
  },
  {
    "link_it": "https://github.com/lmbstudiocontact/cb_dmean_5000_it_5/raw/main/volleyball_cb_dmean_5000_it.json",
    "id_item": "volleyball_cb_dmean_5000_it",
    "id_album": "109468095",
    "english": "volleyball",
    "list_mean": [
      "bóng chuyền"
    ],
    "hash_code_list_mean": "-1376847861",
    "list_img": [
      {
        "link_thumb": "https://live.staticflickr.com/65535/51809341006_9153d0ddc1_n.jpg",
        "link_img": "https://live.staticflickr.com/65535/51809341006_1a06881c6f_o.png",
        "id_image": "volleyball_3116403"
      },
      {
        "link_thumb": "https://live.staticflickr.com/65535/51809696229_b338412eda_n.jpg",
        "link_img": "https://live.staticflickr.com/65535/51809696229_2fa9de3e5d_o.png",
        "id_image": "volleyball_4645879"
      },
      {
        "link_thumb": "https://live.staticflickr.com/65535/51810078270_a192ae41d2_n.jpg",
        "link_img": "https://live.staticflickr.com/65535/51810078270_a9ab6ba4a2_o.png",
        "id_image": "volleyball_4669595"
      }
    ],
    "hash_code_list_img": "712533538",
    "list_definition_mean": [
      {
        "mean_english": "bóng chuyền",
        "definition": "a game in which a ball is volleyed over a high net, using the hands",
        "ex_of_definition_list": [
          "beach volleyball."
        ]
      }
    ],
    "hash_code_list_definition_mean": "1032688270"
  },
  {
    "link_it": "https://github.com/lmbstudiocontact/cb_dmean_5000_it_5/raw/main/volley_cb_dmean_5000_it.json",
    "id_item": "volley_cb_dmean_5000_it",
    "id_album": "109468095",
    "english": "volley",
    "list_mean": [
      "quả vô lê",
      "loạt , tràng ,chuỗi",
      "vô lê",
      "tuôn ra, bắn ra hàng loạt"
    ],
    "hash_code_list_mean": "1256145014",
    "list_img": [
      {
        "link_thumb": "https://live.staticflickr.com/65535/51809455858_5d968058ab_n.jpg",
        "link_img": "https://live.staticflickr.com/65535/51809455858_09604c0774_o.png",
        "id_image": "volley_4696264"
      },
      {
        "link_thumb": "https://live.staticflickr.com/65535/51809696274_17a3f2ee9f_n.jpg",
        "link_img": "https://live.staticflickr.com/65535/51809696274_6db08d63a6_o.png",
        "id_image": "volley_4792260"
      },
      {
        "link_thumb": "https://live.staticflickr.com/65535/51809455883_0480fe8f4e_n.jpg",
        "link_img": "https://live.staticflickr.com/65535/51809455883_70ff464b88_o.png",
        "id_image": "volley_907382"
      }
    ],
    "hash_code_list_img": "748119566",
    "list_definition_mean": [
      {
        "mean_english": "quả vô lê",
        "definition": "in tennis, the hitting of a ball before it bounces",
        "ex_of_definition_list": [
          "He hit a superb volley back across the net."
        ]
      },
      {
        "mean_english": "loạt , tràng ,chuỗi",
        "definition": "a burst of firing etc",
        "ex_of_definition_list": [
          "a volley of shots",
          "a volley of questions/curses."
        ]
      },
      {
        "mean_english": "vô lê",
        "definition": "to hit (a ball etc) before it bounces",
        "ex_of_definition_list": [
          "He volleyed the ball back to his opponent."
        ]
      },
      {
        "mean_english": "tuôn ra, bắn ra hàng loạt",
        "definition": "to fire a rapid burst of (bullets, questions etc)",
        "ex_of_definition_list": [
          "Democrats and Republicans are already volleying accusations of blame."
        ]
      }
    ],
    "hash_code_list_definition_mean": "-877188651"
  },
  {
    "link_it": "https://github.com/lmbstudiocontact/cb_dmean_5000_it_5/raw/main/voltage_cb_dmean_5000_it.json",
    "id_item": "voltage_cb_dmean_5000_it",
    "id_album": "109468095",
    "english": "voltage",
    "list_mean": [
      "điện áp"
    ],
    "hash_code_list_mean": "-828767857",
    "list_img": [
      {
        "link_thumb": "https://live.staticflickr.com/65535/51809696119_25236753e4_n.jpg",
        "link_img": "https://live.staticflickr.com/65535/51809696119_d8b2cc9fb8_o.png",
        "id_image": "voltage_4152051"
      },
      {
        "link_thumb": "https://live.staticflickr.com/65535/51809696089_91c2ce232f_n.jpg",
        "link_img": "https://live.staticflickr.com/65535/51809696089_d6ce645161_o.png",
        "id_image": "voltage_4276377"
      },
      {
        "link_thumb": "https://live.staticflickr.com/65535/51808385827_4174181b8a_n.jpg",
        "link_img": "https://live.staticflickr.com/65535/51808385827_121a6e8309_o.png",
        "id_image": "voltage_916066"
      }
    ],
    "hash_code_list_img": "-1591777202",
    "list_definition_mean": [
      {
        "mean_english": "điện áp",
        "definition": "(a) force measured in volts",
        "ex_of_definition_list": [
          "Low voltage reduces the current, making the lights burn dimly."
        ]
      }
    ],
    "hash_code_list_definition_mean": "884118755"
  },
  {
    "link_it": "https://github.com/lmbstudiocontact/cb_dmean_5000_it_5/raw/main/volume_cb_dmean_5000_it.json",
    "id_item": "volume_cb_dmean_5000_it",
    "id_album": "109468095",
    "english": "volume",
    "list_mean": [
      "quyển, cuốn sách",
      "tập",
      "dung tích, thể tích",
      "khối lượng, số lượng",
      "âm lượng"
    ],
    "hash_code_list_mean": "1185980347",
    "list_img": [
      {
        "link_thumb": "https://live.staticflickr.com/65535/51809455648_a4f746b03a_n.jpg",
        "link_img": "https://live.staticflickr.com/65535/51809455648_70cbfa361d_o.png",
        "id_image": "volume_227193"
      },
      {
        "link_thumb": "https://live.staticflickr.com/65535/51808385677_16eb7ae227_n.jpg",
        "link_img": "https://live.staticflickr.com/65535/51808385677_8f07bb3f92_o.png",
        "id_image": "volume_227194"
      },
      {
        "link_thumb": "https://live.staticflickr.com/65535/51809340716_eeb3403a8a_n.jpg",
        "link_img": "https://live.staticflickr.com/65535/51809340716_5434b61cdb_o.png",
        "id_image": "volume_227196"
      }
    ],
    "hash_code_list_img": "188325854",
    "list_definition_mean": [
      {
        "mean_english": "quyển, cuốn sách",
        "definition": "a book",
        "ex_of_definition_list": [
          "This library contains over a million volumes."
        ]
      },
      {
        "mean_english": "tập",
        "definition": "one of a series of connected books",
        "ex_of_definition_list": [
          "Where is volume fifteen of the encyclopedia?"
        ]
      },
      {
        "mean_english": "dung tích, thể tích",
        "definition": "the amount of space occupied by something, expressed in cubic measurement",
        "ex_of_definition_list": [
          "What is the volume of the petrol tank?"
        ]
      },
      {
        "mean_english": "khối lượng, số lượng",
        "definition": "amount",
        "ex_of_definition_list": [
          "A large volume of work remains to be done."
        ]
      },
      {
        "mean_english": "âm lượng",
        "definition": "level of sound eg on a radio, television etc",
        "ex_of_definition_list": [
          "Turn up the volume on the radio."
        ]
      }
    ],
    "hash_code_list_definition_mean": "316616651"
  },
  {
    "link_it": "https://github.com/lmbstudiocontact/cb_dmean_5000_it_5/raw/main/voluntary_cb_dmean_5000_it.json",
    "id_item": "voluntary_cb_dmean_5000_it",
    "id_album": "109468095",
    "english": "voluntary",
    "list_mean": [
      "tự nguyện",
      "tình nguyện"
    ],
    "hash_code_list_mean": "-1421784756",
    "list_img": [
      {
        "link_thumb": "https://live.staticflickr.com/65535/51809340651_015c22eb66_n.jpg",
        "link_img": "https://live.staticflickr.com/65535/51809340651_df60999d83_o.png",
        "id_image": "voluntary_1590696"
      },
      {
        "link_thumb": "https://live.staticflickr.com/65535/51808385582_0a7ffa051a_n.jpg",
        "link_img": "https://live.staticflickr.com/65535/51808385582_eeb7c13d4d_o.png",
        "id_image": "voluntary_1974645"
      }
    ],
    "hash_code_list_img": "-2061654618",
    "list_definition_mean": [
      {
        "mean_english": "tự nguyện",
        "definition": "done, given etc by choice, not by accident or because of being forced (often without pay)",
        "ex_of_definition_list": [
          "Their action was completely voluntary – nobody asked them to do that."
        ]
      },
      {
        "mean_english": "tình nguyện",
        "definition": "run, financed etc by such actions, contributions etc",
        "ex_of_definition_list": [
          "He does a lot of work for a voluntary organization."
        ]
      }
    ],
    "hash_code_list_definition_mean": "-578841518"
  },
  {
    "link_it": "https://github.com/lmbstudiocontact/cb_dmean_5000_it_5/raw/main/volunteer_cb_dmean_5000_it.json",
    "id_item": "volunteer_cb_dmean_5000_it",
    "id_album": "109468095",
    "english": "volunteer",
    "list_mean": [
      "tình nguyện",
      "xung phong làm",
      "quân tình nguyện, lính tình nguyện"
    ],
    "hash_code_list_mean": "1185508341",
    "list_img": [
      {
        "link_thumb": "https://live.staticflickr.com/65535/51809695889_ecd1f38cb5_n.jpg",
        "link_img": "https://live.staticflickr.com/65535/51809695889_2b7fb5e4c8_o.png",
        "id_image": "volunteer_1312494"
      },
      {
        "link_thumb": "https://live.staticflickr.com/65535/51810077890_fe21900a8d_n.jpg",
        "link_img": "https://live.staticflickr.com/65535/51810077890_b04b75d229_o.png",
        "id_image": "volunteer_4706857"
      },
      {
        "link_thumb": "https://live.staticflickr.com/65535/51809340486_5420287679_n.jpg",
        "link_img": "https://live.staticflickr.com/65535/51809340486_1db44f8955_o.png",
        "id_image": "volunteer_6183121"
      }
    ],
    "hash_code_list_img": "-1540575535",
    "list_definition_mean": [
      {
        "mean_english": "tình nguyện",
        "definition": "to offer oneself for a particular task, of one’s own free will (often without being paid for such work)",
        "ex_of_definition_list": [
          "He volunteered to act as messenger."
        ]
      },
      {
        "mean_english": "xung phong làm",
        "definition": "to offer (eg an opinion, information etc)",
        "ex_of_definition_list": [
          "Two or three people volunteered suggestions."
        ]
      },
      {
        "mean_english": "quân tình nguyện, lính tình nguyện",
        "definition": "a person who offers to do, or does, something (especially who joins the army) of his own free will",
        "ex_of_definition_list": [
          "If we can get enough volunteers, we shall not force people to join the Army."
        ]
      }
    ],
    "hash_code_list_definition_mean": "-473932329"
  },
  {
    "link_it": "https://github.com/lmbstudiocontact/cb_dmean_5000_it_5/raw/main/vomit_cb_dmean_5000_it.json",
    "id_item": "vomit_cb_dmean_5000_it",
    "id_album": "109468095",
    "english": "vomit",
    "list_mean": [
      "nôn, mửa",
      "sự nôn, mửa"
    ],
    "hash_code_list_mean": "-1937253021",
    "list_img": [
      {
        "link_thumb": "https://live.staticflickr.com/65535/51808385452_972eb0afac_n.jpg",
        "link_img": "https://live.staticflickr.com/65535/51808385452_6735939580_o.png",
        "id_image": "vomit_1754091"
      },
      {
        "link_thumb": "https://live.staticflickr.com/65535/51809455378_1bb128f584_n.jpg",
        "link_img": "https://live.staticflickr.com/65535/51809455378_368c77e6de_o.png",
        "id_image": "vomit_2269014"
      }
    ],
    "hash_code_list_img": "-1955595804",
    "list_definition_mean": [
      {
        "mean_english": "nôn, mửa",
        "definition": "to throw out (the contents of the stomach or other matter) through the mouth; to be sick",
        "ex_of_definition_list": [
          "Whenever the ship started to move, she felt like vomiting."
        ]
      },
      {
        "mean_english": "sự nôn, mửa",
        "definition": "food etc ejected from the stomach",
        "ex_of_definition_list": [
          "a pool of vomit."
        ]
      }
    ],
    "hash_code_list_definition_mean": "-1544965447"
  },
  {
    "link_it": "https://github.com/lmbstudiocontact/cb_dmean_5000_it_5/raw/main/voodoo_cb_dmean_5000_it.json",
    "id_item": "voodoo_cb_dmean_5000_it",
    "id_album": "109468095",
    "english": "voodoo",
    "list_mean": [
      "sự dùng tà thuật"
    ],
    "hash_code_list_mean": "-364333021",
    "list_img": [
      {
        "link_thumb": "https://live.staticflickr.com/65535/51809455268_7cf4fe5ebf_n.jpg",
        "link_img": "https://live.staticflickr.com/65535/51809455268_1f00ecc891_o.png",
        "id_image": "voodoo_5327140"
      }
    ],
    "hash_code_list_img": "1687037457",
    "list_definition_mean": [
      {
        "mean_english": "sự dùng tà thuật",
        "definition": "a type of witchcraft originally practised in the West Indies",
        "ex_of_definition_list": [
          "a voodoo doll."
        ]
      }
    ],
    "hash_code_list_definition_mean": "1633514760"
  },
  {
    "link_it": "https://github.com/lmbstudiocontact/cb_dmean_5000_it_5/raw/main/voter_cb_dmean_5000_it.json",
    "id_item": "voter_cb_dmean_5000_it",
    "id_album": "109468095",
    "english": "voter",
    "list_mean": [
      "người đi bầu cử, biểu quyết"
    ],
    "hash_code_list_mean": "1605213883",
    "list_img": [
      {
        "link_thumb": "https://live.staticflickr.com/65535/51809340211_2621f97221_n.jpg",
        "link_img": "https://live.staticflickr.com/65535/51809340211_70a65782f7_o.png",
        "id_image": "voter_5390701"
      },
      {
        "link_thumb": "https://live.staticflickr.com/65535/51810077435_c6743d5517_n.jpg",
        "link_img": "https://live.staticflickr.com/65535/51810077435_87f933b12b_o.png",
        "id_image": "voter_5608060"
      },
      {
        "link_thumb": "https://live.staticflickr.com/65535/51809455028_6915ab29bc_n.jpg",
        "link_img": "https://live.staticflickr.com/65535/51809455028_ac179da565_o.png",
        "id_image": "voter_5608074"
      }
    ],
    "hash_code_list_img": "-525007066",
    "list_definition_mean": [
      {
        "mean_english": "người đi bầu cử, biểu quyết",
        "definition": "a person who votes or has the right to vote",
        "ex_of_definition_list": [
          "How do voters choose one candidate over another?"
        ]
      }
    ],
    "hash_code_list_definition_mean": "2070422778"
  },
  {
    "link_it": "https://github.com/lmbstudiocontact/cb_dmean_5000_it_5/raw/main/vote_cb_dmean_5000_it.json",
    "id_item": "vote_cb_dmean_5000_it",
    "id_album": "109468095",
    "english": "vote",
    "list_mean": [
      "sự bỏ phiếu, bầu cử",
      "bỏ phiếu, bấu cử",
      "thông qua trợ cấp"
    ],
    "hash_code_list_mean": "-632464468",
    "list_img": [
      {
        "link_thumb": "https://live.staticflickr.com/65535/51810077575_bfdfdaa7f6_n.jpg",
        "link_img": "https://live.staticflickr.com/65535/51810077575_c8c394b667_o.png",
        "id_image": "vote_1666098"
      },
      {
        "link_thumb": "https://live.staticflickr.com/65535/51809695589_71fa0c0aca_n.jpg",
        "link_img": "https://live.staticflickr.com/65535/51809695589_8389f5847b_o.png",
        "id_image": "vote_1666102"
      },
      {
        "link_thumb": "https://live.staticflickr.com/65535/51810077505_0432f7e376_n.jpg",
        "link_img": "https://live.staticflickr.com/65535/51810077505_d81d5eb770_o.png",
        "id_image": "vote_2529798"
      }
    ],
    "hash_code_list_img": "1684068296",
    "list_definition_mean": [
      {
        "mean_english": "sự bỏ phiếu, bầu cử",
        "definition": "(the right to show) one’s wish or opinion, eg in a ballot or by raising a hand etc, especially at an election or in a debate",
        "ex_of_definition_list": [
          "In Britain, the vote was given to women over twenty-one in 1928",
          "Nowadays everyone over eighteen has a vote",
          "A vote was taken to decide the matter."
        ]
      },
      {
        "mean_english": "bỏ phiếu, bấu cử",
        "definition": "to cast or record one’s vote",
        "ex_of_definition_list": [
          "She voted for the Conservative candidate",
          "I always vote Labour",
          "I shall vote against the restoration of capital punishment."
        ]
      },
      {
        "mean_english": "thông qua trợ cấp",
        "definition": "to allow, by a vote, the provision of (something) eg to someone, for a purpose etc",
        "ex_of_definition_list": [
          "They were voted $5,000 to help them in their research."
        ]
      }
    ],
    "hash_code_list_definition_mean": "-1741774158"
  },
  {
    "link_it": "https://github.com/lmbstudiocontact/cb_dmean_5000_it_5/raw/main/voucher_cb_dmean_5000_it.json",
    "id_item": "voucher_cb_dmean_5000_it",
    "id_album": "109468095",
    "english": "voucher",
    "list_mean": [
      "giấy cam đoan"
    ],
    "hash_code_list_mean": "-708551163",
    "list_img": [
      {
        "link_thumb": "https://live.staticflickr.com/65535/51809695304_64172144a4_n.jpg",
        "link_img": "https://live.staticflickr.com/65535/51809695304_c20f892da7_o.png",
        "id_image": "voucher_2037349"
      },
      {
        "link_thumb": "https://live.staticflickr.com/65535/51809454908_1cbc386d16_n.jpg",
        "link_img": "https://live.staticflickr.com/65535/51809454908_85d8783b8d_o.png",
        "id_image": "voucher_4982304"
      }
    ],
    "hash_code_list_img": "348618247",
    "list_definition_mean": [
      {
        "mean_english": "giấy cam đoan",
        "definition": "a piece of paper which confirms that a sum of money has been, or will be, paid",
        "ex_of_definition_list": [
          "a sales voucher."
        ]
      }
    ],
    "hash_code_list_definition_mean": "1648701533"
  },
  {
    "link_it": "https://github.com/lmbstudiocontact/cb_dmean_5000_it_5/raw/main/wafer_cb_dmean_5000_it.json",
    "id_item": "wafer_cb_dmean_5000_it",
    "id_album": "109468095",
    "english": "wafer",
    "list_mean": [
      "bánh xốp"
    ],
    "hash_code_list_mean": "68152431",
    "list_img": [
      {
        "link_thumb": "https://live.staticflickr.com/65535/51809339836_a9a006008a_n.jpg",
        "link_img": "https://live.staticflickr.com/65535/51809339836_74da9fb29c_o.png",
        "id_image": "wafer_2218708"
      },
      {
        "link_thumb": "https://live.staticflickr.com/65535/51809339766_dcbd4444d4_n.jpg",
        "link_img": "https://live.staticflickr.com/65535/51809339766_e3d47a51a5_o.png",
        "id_image": "wafer_2269361"
      },
      {
        "link_thumb": "https://live.staticflickr.com/65535/51809454683_303b48dfb1_n.jpg",
        "link_img": "https://live.staticflickr.com/65535/51809454683_df9fbfec4a_o.png",
        "id_image": "wafer_3200505"
      },
      {
        "link_thumb": "https://live.staticflickr.com/65535/51808384632_8522100df8_n.jpg",
        "link_img": "https://live.staticflickr.com/65535/51808384632_6593296ba5_o.png",
        "id_image": "waffle_1999906"
      }
    ],
    "hash_code_list_img": "-1277519590",
    "list_definition_mean": [
      {
        "mean_english": "bánh xốp",
        "definition": "a type of very thin biscuit, often eaten with ice-cream",
        "ex_of_definition_list": [
          "The ice-cream was sandwiched between two wafers."
        ]
      }
    ],
    "hash_code_list_definition_mean": "848606816"
  },
  {
    "link_it": "https://github.com/lmbstudiocontact/cb_dmean_5000_it_5/raw/main/waffle_cb_dmean_5000_it.json",
    "id_item": "waffle_cb_dmean_5000_it",
    "id_album": "109468095",
    "english": "waffle",
    "list_mean": [
      "chuyện dông dài",
      "câu chuyện dông dài",
      "bánh quế"
    ],
    "hash_code_list_mean": "-1407289795",
    "list_img": [
      {
        "link_thumb": "https://live.staticflickr.com/65535/51808384632_8522100df8_n.jpg",
        "link_img": "https://live.staticflickr.com/65535/51808384632_6593296ba5_o.png",
        "id_image": "waffle_1999906"
      },
      {
        "link_thumb": "https://live.staticflickr.com/65535/51809339656_3085c42c13_n.jpg",
        "link_img": "https://live.staticflickr.com/65535/51809339656_5fa8909130_o.png",
        "id_image": "waffle_1999918"
      },
      {
        "link_thumb": "https://live.staticflickr.com/65535/51810076835_22bf8b6a88_n.jpg",
        "link_img": "https://live.staticflickr.com/65535/51810076835_8f75e246db_o.png",
        "id_image": "waffle_2442267"
      },
      {
        "link_thumb": "https://live.staticflickr.com/65535/51808384542_99153320ea_n.jpg",
        "link_img": "https://live.staticflickr.com/65535/51808384542_6382ab540d_o.png",
        "id_image": "waffle_3200286"
      },
      {
        "link_thumb": "https://live.staticflickr.com/65535/51809339571_5faac92e54_n.jpg",
        "link_img": "https://live.staticflickr.com/65535/51809339571_9ed0b411a4_o.png",
        "id_image": "waffle_4524549"
      }
    ],
    "hash_code_list_img": "-116451987",
    "list_definition_mean": [
      {
        "mean_english": "chuyện dông dài",
        "definition": "to talk on and on foolishly, pretending that one knows something which one does not",
        "ex_of_definition_list": [
          "The history lecturer was inclined to waffle on for hours."
        ]
      },
      {
        "mean_english": "câu chuyện dông dài",
        "definition": "talk of this kind",
        "ex_of_definition_list": [
          "His speech was pure waffle – he really has no idea what he’s talking about."
        ]
      },
      {
        "mean_english": "bánh quế",
        "definition": "a flat cake baked in a special appliance that leaves a pattern of squares on it",
        "ex_of_definition_list": [
          "Waffles are usually eaten with ice cream, syrup, or jam."
        ]
      }
    ],
    "hash_code_list_definition_mean": "1611825241"
  },
  {
    "link_it": "https://github.com/lmbstudiocontact/cb_dmean_5000_it_5/raw/main/wage_cb_dmean_5000_it.json",
    "id_item": "wage_cb_dmean_5000_it",
    "id_album": "109468095",
    "english": "wage",
    "list_mean": [
      "tiến hành",
      "lương tuần"
    ],
    "hash_code_list_mean": "1110693221",
    "list_img": [
      {
        "link_thumb": "https://live.staticflickr.com/65535/51809454458_117f8158b0_n.jpg",
        "link_img": "https://live.staticflickr.com/65535/51809454458_2f4a0d5af6_o.png",
        "id_image": "wage_2419709"
      },
      {
        "link_thumb": "https://live.staticflickr.com/65535/51809339506_9dd79c2e24_n.jpg",
        "link_img": "https://live.staticflickr.com/65535/51809339506_2656a7e727_o.png",
        "id_image": "wage_3003270"
      },
      {
        "link_thumb": "https://live.staticflickr.com/65535/51809454393_1a8a715b5c_n.jpg",
        "link_img": "https://live.staticflickr.com/65535/51809454393_7dd6200c87_o.png",
        "id_image": "wage_5308010"
      },
      {
        "link_thumb": "https://live.staticflickr.com/65535/51809694649_d98045efd5_n.jpg",
        "link_img": "https://live.staticflickr.com/65535/51809694649_edb8964ea3_o.png",
        "id_image": "wage_5796984"
      },
      {
        "link_thumb": "https://live.staticflickr.com/65535/51809694594_da064d4bea_n.jpg",
        "link_img": "https://live.staticflickr.com/65535/51809694594_56002ace0c_o.png",
        "id_image": "wage_6213869"
      }
    ],
    "hash_code_list_img": "-400441682",
    "list_definition_mean": [
      {
        "mean_english": "tiến hành",
        "definition": "to carry on or engage in (especially a war)",
        "ex_of_definition_list": [
          "The North waged war on/against the South."
        ]
      },
      {
        "mean_english": "lương tuần",
        "definition": "(also wagesnoun plural) a regular, usually weekly rather than monthly, payment for the work that one does",
        "ex_of_definition_list": [
          "He spends all his wages on clothes",
          "What is his weekly wage?"
        ]
      }
    ],
    "hash_code_list_definition_mean": "807198382"
  },
  {
    "link_it": "https://github.com/lmbstudiocontact/cb_dmean_5000_it_5/raw/main/wagon_cb_dmean_5000_it.json",
    "id_item": "wagon_cb_dmean_5000_it",
    "id_album": "109468095",
    "english": "wagon",
    "list_mean": [
      "xe ngựa; xe bò",
      "toa xe hàng"
    ],
    "hash_code_list_mean": "1816167113",
    "list_img": [
      {
        "link_thumb": "https://live.staticflickr.com/65535/51809454318_1c7d5c0646_n.jpg",
        "link_img": "https://live.staticflickr.com/65535/51809454318_407c778a49_o.png",
        "id_image": "wagon_1987431"
      },
      {
        "link_thumb": "https://live.staticflickr.com/65535/51808384262_40242fc016_n.jpg",
        "link_img": "https://live.staticflickr.com/65535/51808384262_2440e51a18_o.png",
        "id_image": "wagon_2893062"
      },
      {
        "link_thumb": "https://live.staticflickr.com/65535/51809694434_a8d09dbb9a_n.jpg",
        "link_img": "https://live.staticflickr.com/65535/51809694434_b1daa9aaf4_o.png",
        "id_image": "wagon_3745910"
      },
      {
        "link_thumb": "https://live.staticflickr.com/65535/51810076450_a061b04abe_n.jpg",
        "link_img": "https://live.staticflickr.com/65535/51810076450_ef78ae1482_o.png",
        "id_image": "wagon_5895733"
      }
    ],
    "hash_code_list_img": "-785697315",
    "list_definition_mean": [
      {
        "mean_english": "xe ngựa; xe bò",
        "definition": "a type of four-wheeled vehicle for carrying heavy loads",
        "ex_of_definition_list": [
          "a hay wagon."
        ]
      },
      {
        "mean_english": "toa xe hàng",
        "definition": "an open railway carriage for goods",
        "ex_of_definition_list": [
          "a goods wagon."
        ]
      }
    ],
    "hash_code_list_definition_mean": "2132145341"
  }
]