[
  {
    "link_it": "https://github.com/lmbstudiocontact/cb_dmean_5000_it_4/raw/main/rotten_cb_dmean_5000_it.json",
    "id_item": "rotten_cb_dmean_5000_it",
    "id_album": "105774007",
    "english": "rotten",
    "list_mean": [
      "thiu; ươn",
      "tồi tệ"
    ],
    "hash_code_list_mean": "-1788524686",
    "list_img": [
      {
        "link_thumb": "https://live.staticflickr.com/65535/51810078905_ee1f1d151b_n.jpg",
        "link_img": "https://live.staticflickr.com/65535/51810078905_f2e42d3d24_o.png",
        "id_image": "rotten_4172831"
      },
      {
        "link_thumb": "https://live.staticflickr.com/65535/51808386512_3c8143c99f_n.jpg",
        "link_img": "https://live.staticflickr.com/65535/51808386512_1ca6227528_o.png",
        "id_image": "rotten_5256354"
      },
      {
        "link_thumb": "https://live.staticflickr.com/65535/51808386487_81d6115958_n.jpg",
        "link_img": "https://live.staticflickr.com/65535/51808386487_34c7076fd6_o.png",
        "id_image": "rotten_5671101"
      }
    ],
    "hash_code_list_img": "1407514945",
    "list_definition_mean": [
      {
        "mean_english": "thiu; ươn",
        "definition": "(of meat, fruit etc) having gone bad; decayed",
        "ex_of_definition_list": [
          "rotten vegetables."
        ]
      },
      {
        "mean_english": "tồi tệ",
        "definition": "bad; mean",
        "ex_of_definition_list": [
          "What rotten luck!",
          "It was a rotten thing to do."
        ]
      }
    ],
    "hash_code_list_definition_mean": "1041417128"
  },
  {
    "link_it": "https://github.com/lmbstudiocontact/cb_dmean_5000_it_4/raw/main/roundabout_cb_dmean_5000_it.json",
    "id_item": "roundabout_cb_dmean_5000_it",
    "id_album": "105774007",
    "english": "roundabout",
    "list_mean": [
      "chỗ đường vòng",
      "vòng ngựa gỗ cho trẻ em",
      "thuộc vòng"
    ],
    "hash_code_list_mean": "791982128",
    "list_img": [
      {
        "link_thumb": "https://live.staticflickr.com/65535/51809341241_c3c51e3d73_n.jpg",
        "link_img": "https://live.staticflickr.com/65535/51809341241_c09b265296_o.png",
        "id_image": "roundabout_1434832"
      },
      {
        "link_thumb": "https://live.staticflickr.com/65535/51809456023_1359810021_n.jpg",
        "link_img": "https://live.staticflickr.com/65535/51809456023_d2ff70e6cc_o.png",
        "id_image": "roundabout_1581880"
      },
      {
        "link_thumb": "https://live.staticflickr.com/65535/51809696414_0aa1fe6159_n.jpg",
        "link_img": "https://live.staticflickr.com/65535/51809696414_83c9b65d19_o.png",
        "id_image": "roundabout_3752004"
      }
    ],
    "hash_code_list_img": "2012728470",
    "list_definition_mean": [
      {
        "mean_english": "thuộc vòng",
        "definition": "not direct",
        "ex_of_definition_list": [
          "a roundabout route."
        ]
      }
    ],
    "hash_code_list_definition_mean": "1805445058"
  },
  {
    "link_it": "https://github.com/lmbstudiocontact/cb_dmean_5000_it_4/raw/main/round_cb_dmean_5000_it.json",
    "id_item": "round_cb_dmean_5000_it",
    "id_album": "105774007",
    "english": "round",
    "list_mean": [
      "tròn",
      "bụ bẫm",
      "theo chiều ngược lại",
      "vòng tròn",
      "theo vòng tròn",
      "đi một vòng",
      "chu vi",
      "tới thăm một gia đình",
      "xung quanh",
      "vòng quanh",
      "hướng về",
      "khắp nơi",
      "sự quay vòng",
      "chuyến đi",
      "sự tán thưởng",
      "viên đạn",
      "vòng thi đấu",
      "ca nông (âm nhạc)",
      "đi vòng quanh"
    ],
    "hash_code_list_mean": "-2048691082",
    "list_img": [
      {
        "link_thumb": "https://live.staticflickr.com/65535/51809456168_7ccd0f87e1_n.jpg",
        "link_img": "https://live.staticflickr.com/65535/51809456168_49f61be415_o.png",
        "id_image": "round_2421597"
      },
      {
        "link_thumb": "https://live.staticflickr.com/65535/51808386292_fd36e0edf7_n.jpg",
        "link_img": "https://live.staticflickr.com/65535/51808386292_38bb491ef8_o.png",
        "id_image": "round_2736128"
      },
      {
        "link_thumb": "https://live.staticflickr.com/65535/51810078655_08b3e8aea8_n.jpg",
        "link_img": "https://live.staticflickr.com/65535/51810078655_6d3f9a0089_o.png",
        "id_image": "round_6006261"
      }
    ],
    "hash_code_list_img": "1956752440",
    "list_definition_mean": [
      {
        "mean_english": "tròn",
        "definition": "shaped like a circle or globe",
        "ex_of_definition_list": [
          "a round hole",
          "a round stone",
          "This plate isn’t quite round."
        ]
      },
      {
        "mean_english": "bụ bẫm",
        "definition": "rather fat; plump",
        "ex_of_definition_list": [
          "a round face."
        ]
      },
      {
        "mean_english": "theo chiều ngược lại",
        "definition": "in the opposite direction",
        "ex_of_definition_list": [
          "He turned round."
        ]
      },
      {
        "mean_english": "vòng tròn",
        "definition": "in a circle",
        "ex_of_definition_list": [
          "They all stood round and listened",
          "A wheel goes round",
          "All (the) year round."
        ]
      },
      {
        "mean_english": "theo vòng tròn",
        "definition": "from one person to another",
        "ex_of_definition_list": [
          "They passed the letter round",
          "The news went round."
        ]
      },
      {
        "mean_english": "đi một vòng",
        "definition": "from place to place",
        "ex_of_definition_list": [
          "We drove round for a while."
        ]
      },
      {
        "mean_english": "chu vi",
        "definition": "in circumference",
        "ex_of_definition_list": [
          "The tree measured two metres round."
        ]
      },
      {
        "mean_english": "tới thăm một gia đình",
        "definition": "to a particular place, usually a person’s home",
        "ex_of_definition_list": [
          "Are you coming round (to our house) tonight?"
        ]
      },
      {
        "mean_english": "xung quanh",
        "definition": "on all sides of",
        "ex_of_definition_list": [
          "There was a wall round the garden",
          "He looked round the room."
        ]
      },
      {
        "mean_english": "vòng quanh",
        "definition": "passing all sides of (and returning to the starting-place)",
        "ex_of_definition_list": [
          "They ran round the tree."
        ]
      },
      {
        "mean_english": "hướng về",
        "definition": "changing direction at",
        "ex_of_definition_list": [
          "He came round the corner."
        ]
      },
      {
        "mean_english": "khắp nơi",
        "definition": "in or to all parts of",
        "ex_of_definition_list": [
          "The news spread all round the town."
        ]
      },
      {
        "mean_english": "sự quay vòng",
        "definition": "a complete circuit",
        "ex_of_definition_list": [
          "a round of drinks (= one for everyone present)",
          "a round of golf."
        ]
      },
      {
        "mean_english": "chuyến đi",
        "definition": "a regular journey one takes to do one’s work",
        "ex_of_definition_list": [
          "a postman’s round."
        ]
      },
      {
        "mean_english": "sự tán thưởng",
        "definition": "a burst of cheering, shooting etc",
        "ex_of_definition_list": [
          "They gave him a round of applause",
          "The soldier fired several rounds."
        ]
      },
      {
        "mean_english": "viên đạn",
        "definition": "a single bullet, shell etc",
        "ex_of_definition_list": [
          "five hundred rounds of ammunition."
        ]
      },
      {
        "mean_english": "vòng thi đấu",
        "definition": "a stage in a competition etc",
        "ex_of_definition_list": [
          "The winners of the first round will go through to the next."
        ]
      },
      {
        "mean_english": "đi vòng quanh",
        "definition": "to go round",
        "ex_of_definition_list": [
          "The car rounded the corner."
        ]
      }
    ],
    "hash_code_list_definition_mean": "-734308145"
  },
  {
    "link_it": "https://github.com/lmbstudiocontact/cb_dmean_5000_it_4/raw/main/router_cb_dmean_5000_it.json",
    "id_item": "router_cb_dmean_5000_it",
    "id_album": "105774007",
    "english": "router",
    "list_mean": [
      "bộ định tuyến"
    ],
    "hash_code_list_mean": "-1194414397",
    "list_img": [
      {
        "link_thumb": "https://live.staticflickr.com/65535/51809455793_0d73ef09bd_n.jpg",
        "link_img": "https://live.staticflickr.com/65535/51809455793_ac151e9c97_o.png",
        "id_image": "router_294640"
      },
      {
        "link_thumb": "https://live.staticflickr.com/65535/51808385917_41e97660a7_n.jpg",
        "link_img": "https://live.staticflickr.com/65535/51808385917_5933a108ea_o.png",
        "id_image": "router_657952"
      },
      {
        "link_thumb": "https://live.staticflickr.com/65535/51810078260_ae69ac65ca_n.jpg",
        "link_img": "https://live.staticflickr.com/65535/51810078260_9b863a252e_o.png",
        "id_image": "router_741374"
      }
    ],
    "hash_code_list_img": "-1842905225",
    "list_definition_mean": [
      {
        "mean_english": "bộ định tuyến",
        "definition": "an electronic device that enables packets of data to be moved between computers or computer networks in an efficient way",
        "ex_of_definition_list": [
          "The router will choose the best route for the data packet so that you receive the information quickly."
        ]
      }
    ],
    "hash_code_list_definition_mean": "43426671"
  },
  {
    "link_it": "https://github.com/lmbstudiocontact/cb_dmean_5000_it_4/raw/main/route_cb_dmean_5000_it.json",
    "id_item": "route_cb_dmean_5000_it",
    "id_album": "105774007",
    "english": "route",
    "list_mean": [
      "lộ trình",
      "theo lộ trình"
    ],
    "hash_code_list_mean": "-1343920605",
    "list_img": [
      {
        "link_thumb": "https://live.staticflickr.com/65535/51809341126_b43018d937_n.jpg",
        "link_img": "https://live.staticflickr.com/65535/51809341126_c7eb9ba0b5_o.png",
        "id_image": "route_169493"
      },
      {
        "link_thumb": "https://live.staticflickr.com/65535/51809455903_4b67aee3ca_n.jpg",
        "link_img": "https://live.staticflickr.com/65535/51809455903_a0e73ef267_o.png",
        "id_image": "route_179677"
      },
      {
        "link_thumb": "https://live.staticflickr.com/65535/51808386042_425557859c_n.jpg",
        "link_img": "https://live.staticflickr.com/65535/51808386042_1c51f4bddf_o.png",
        "id_image": "route_2569907"
      },
      {
        "link_thumb": "https://live.staticflickr.com/65535/51809696269_a5b97ab6b8_n.jpg",
        "link_img": "https://live.staticflickr.com/65535/51809696269_ce4404f06c_o.png",
        "id_image": "route_3579797"
      }
    ],
    "hash_code_list_img": "-619298247",
    "list_definition_mean": [
      {
        "mean_english": "lộ trình",
        "definition": "a way of getting somewhere; a road",
        "ex_of_definition_list": [
          "Our route took us through the mountains."
        ]
      },
      {
        "mean_english": "theo lộ trình",
        "definition": "to arrange a route for",
        "ex_of_definition_list": [
          "Heavy traffic was routed round the outside of the town."
        ]
      }
    ],
    "hash_code_list_definition_mean": "-1812016936"
  },
  {
    "link_it": "https://github.com/lmbstudiocontact/cb_dmean_5000_it_4/raw/main/routine_cb_dmean_5000_it.json",
    "id_item": "routine_cb_dmean_5000_it",
    "id_album": "105774007",
    "english": "routine",
    "list_mean": [
      "thói quen",
      "thường xuyên"
    ],
    "hash_code_list_mean": "-645456744",
    "list_img": [
      {
        "link_thumb": "https://live.staticflickr.com/65535/51809340896_14dc484c43_n.jpg",
        "link_img": "https://live.staticflickr.com/65535/51809340896_3652d43155_o.png",
        "id_image": "routine_2738826"
      },
      {
        "link_thumb": "https://live.staticflickr.com/65535/51808385812_5946b4f6c6_n.jpg",
        "link_img": "https://live.staticflickr.com/65535/51808385812_2c1a5ec69e_o.png",
        "id_image": "routine_5101217"
      },
      {
        "link_thumb": "https://live.staticflickr.com/65535/51808385787_e85b7df918_n.jpg",
        "link_img": "https://live.staticflickr.com/65535/51808385787_db39cd1dae_o.png",
        "id_image": "routine_5775316"
      }
    ],
    "hash_code_list_img": "1335523696",
    "list_definition_mean": [
      {
        "mean_english": "thói quen",
        "definition": "a regular, fixed way of doing things",
        "ex_of_definition_list": [
          "her daily routine",
          "Everyone needs some routine in their lives."
        ]
      },
      {
        "mean_english": "thường xuyên",
        "definition": "regular; ordinary",
        "ex_of_definition_list": [
          "routine work."
        ]
      }
    ],
    "hash_code_list_definition_mean": "1253136726"
  },
  {
    "link_it": "https://github.com/lmbstudiocontact/cb_dmean_5000_it_4/raw/main/row_cb_dmean_5000_it.json",
    "id_item": "row_cb_dmean_5000_it",
    "id_album": "105774007",
    "english": "row",
    "list_mean": [
      "hàng; dãy",
      "chèo thuyền",
      "chèo thuyền chở khách",
      "chuyến đi bằng thuyền",
      "cuộc cãi vã",
      "sự huyên náo"
    ],
    "hash_code_list_mean": "1035432633",
    "list_img": [
      {
        "link_thumb": "https://live.staticflickr.com/65535/51809340606_53058f05be_n.jpg",
        "link_img": "https://live.staticflickr.com/65535/51809340606_43bb642d28_o.png",
        "id_image": "row_3603654"
      },
      {
        "link_thumb": "https://live.staticflickr.com/65535/51810078015_21631db3e5_n.jpg",
        "link_img": "https://live.staticflickr.com/65535/51810078015_8b4311f248_o.png",
        "id_image": "row_391242"
      },
      {
        "link_thumb": "https://live.staticflickr.com/65535/51809340656_aa7245b1fb_n.jpg",
        "link_img": "https://live.staticflickr.com/65535/51809340656_a0419cd7ba_o.png",
        "id_image": "row_708627"
      }
    ],
    "hash_code_list_img": "-656532455",
    "list_definition_mean": [
      {
        "mean_english": "hàng; dãy",
        "definition": "a line",
        "ex_of_definition_list": [
          "two rows of houses",
          "They were sitting in a row",
          "They sat in the front row in the theatre."
        ]
      },
      {
        "mean_english": "chèo thuyền",
        "definition": "to move (a boat) through the water using oars",
        "ex_of_definition_list": [
          "He rowed (the dinghy) up the river."
        ]
      },
      {
        "mean_english": "chèo thuyền chở khách",
        "definition": "to transport by rowing",
        "ex_of_definition_list": [
          "He rowed them across the lake."
        ]
      },
      {
        "mean_english": "chuyến đi bằng thuyền",
        "definition": "a trip in a rowing-boat",
        "ex_of_definition_list": [
          "They went for a row on the river."
        ]
      },
      {
        "mean_english": "cuộc cãi vã",
        "definition": "a noisy quarrel",
        "ex_of_definition_list": [
          "They had a terrible row",
          "a family row."
        ]
      },
      {
        "mean_english": "sự huyên náo",
        "definition": "a continuous loud noise",
        "ex_of_definition_list": [
          "They heard a row in the street."
        ]
      }
    ],
    "hash_code_list_definition_mean": "761173385"
  },
  {
    "link_it": "https://github.com/lmbstudiocontact/cb_dmean_5000_it_4/raw/main/royalty_cb_dmean_5000_it.json",
    "id_item": "royalty_cb_dmean_5000_it",
    "id_album": "105774007",
    "english": "royalty",
    "list_mean": [
      "nhuận bút",
      "hoàng tộc"
    ],
    "hash_code_list_mean": "1993152217",
    "list_img": [
      {
        "link_thumb": "https://live.staticflickr.com/65535/51808385322_5b33761ee3_n.jpg",
        "link_img": "https://live.staticflickr.com/65535/51808385322_58ea8bdd0a_o.png",
        "id_image": "royalty_2653360"
      }
    ],
    "hash_code_list_img": "2136672581",
    "list_definition_mean": [
      {
        "mean_english": "nhuận bút",
        "definition": "a payment made to a writer, recording artist etc for every book, record etc sold",
        "ex_of_definition_list": [
          "songwriting royalties."
        ]
      },
      {
        "mean_english": "hoàng tộc",
        "definition": "the state of being royal, or royal people in general",
        "ex_of_definition_list": [
          "The commands of royalty must be obeyed."
        ]
      }
    ],
    "hash_code_list_definition_mean": "-930469932"
  },
  {
    "link_it": "https://github.com/lmbstudiocontact/cb_dmean_5000_it_4/raw/main/royal_cb_dmean_5000_it.json",
    "id_item": "royal_cb_dmean_5000_it",
    "id_album": "105774007",
    "english": "royal",
    "list_mean": [
      "thuộc hoàng gia",
      "nguy nga",
      "thành viên hoàng gia"
    ],
    "hash_code_list_mean": "-1993666824",
    "list_img": [
      {
        "link_thumb": "https://live.staticflickr.com/65535/51809455373_c891e2007a_n.jpg",
        "link_img": "https://live.staticflickr.com/65535/51809455373_45232efe0c_o.png",
        "id_image": "royal_2653345"
      },
      {
        "link_thumb": "https://live.staticflickr.com/65535/51809340391_e93cec499d_n.jpg",
        "link_img": "https://live.staticflickr.com/65535/51809340391_4fc427b17d_o.png",
        "id_image": "royal_2653349"
      },
      {
        "link_thumb": "https://live.staticflickr.com/65535/51808385367_649be95693_n.jpg",
        "link_img": "https://live.staticflickr.com/65535/51808385367_bf7b3cb1df_o.png",
        "id_image": "royal_2653375"
      }
    ],
    "hash_code_list_img": "-957412498",
    "list_definition_mean": [
      {
        "mean_english": "thuộc hoàng gia",
        "definition": "of, concerning etc a king, queen etc",
        "ex_of_definition_list": [
          "the royal family",
          "His Royal Highness Prince Charles."
        ]
      },
      {
        "mean_english": "nguy nga",
        "definition": "magnificent",
        "ex_of_definition_list": [
          "a royal feast."
        ]
      }
    ],
    "hash_code_list_definition_mean": "-1350239851"
  },
  {
    "link_it": "https://github.com/lmbstudiocontact/cb_dmean_5000_it_4/raw/main/rubber_cb_dmean_5000_it.json",
    "id_item": "rubber_cb_dmean_5000_it",
    "id_album": "105774007",
    "english": "rubber",
    "list_mean": [
      "cao su",
      "cái tẩy",
      "bao cao su",
      "dây chun"
    ],
    "hash_code_list_mean": "-1910773343",
    "list_img": [
      {
        "link_thumb": "https://live.staticflickr.com/65535/51809695674_b991693eea_n.jpg",
        "link_img": "https://live.staticflickr.com/65535/51809695674_575faf58eb_o.png",
        "id_image": "rubber_1589262"
      },
      {
        "link_thumb": "https://live.staticflickr.com/65535/51810077585_944373f6a0_n.jpg",
        "link_img": "https://live.staticflickr.com/65535/51810077585_b1f5983558_o.png",
        "id_image": "rubber_3944332"
      },
      {
        "link_thumb": "https://live.staticflickr.com/65535/51809340276_946ff5dba9_n.jpg",
        "link_img": "https://live.staticflickr.com/65535/51809340276_fa992f6e17_o.png",
        "id_image": "rubber_5234023"
      },
      {
        "link_thumb": "https://live.staticflickr.com/65535/51810077510_f8a9a0dc9c_n.jpg",
        "link_img": "https://live.staticflickr.com/65535/51810077510_47a0b1e696_o.png",
        "id_image": "rubber_5848636"
      }
    ],
    "hash_code_list_img": "1301914249",
    "list_definition_mean": [
      {
        "mean_english": "cao su",
        "definition": "(also adjective) (of) a strong elastic substance made from the juice of certain plants (especially the rubber tree), or an artificial substitute for this",
        "ex_of_definition_list": [
          "Tyres are made of rubber",
          "rubber boots."
        ]
      },
      {
        "mean_english": "cái tẩy",
        "definition": "a piece of rubber used to rub out pencil etc marks; eraser American",
        "ex_of_definition_list": [
          "a pencil, a ruler and a rubber."
        ]
      }
    ],
    "hash_code_list_definition_mean": "2021486481"
  },
  {
    "link_it": "https://github.com/lmbstudiocontact/cb_dmean_5000_it_4/raw/main/rubbish_cb_dmean_5000_it.json",
    "id_item": "rubbish_cb_dmean_5000_it",
    "id_album": "105774007",
    "english": "rubbish",
    "list_mean": [
      "rác",
      "những điều vô nghĩa"
    ],
    "hash_code_list_mean": "136397396",
    "list_img": [
      {
        "link_thumb": "https://live.staticflickr.com/65535/51810077475_6221f2e91b_n.jpg",
        "link_img": "https://live.staticflickr.com/65535/51810077475_491a179094_o.png",
        "id_image": "rubbish_2371992"
      },
      {
        "link_thumb": "https://live.staticflickr.com/65535/51809455068_27eda7a780_n.jpg",
        "link_img": "https://live.staticflickr.com/65535/51809455068_2645c9ea21_o.png",
        "id_image": "rubbish_2372010"
      },
      {
        "link_thumb": "https://live.staticflickr.com/65535/51809455023_50eea1e441_n.jpg",
        "link_img": "https://live.staticflickr.com/65535/51809455023_89bbcc6d72_o.png",
        "id_image": "rubbish_5848282"
      }
    ],
    "hash_code_list_img": "-197643630",
    "list_definition_mean": [
      {
        "mean_english": "rác",
        "definition": "waste material; things that have been or are to be thrown away",
        "ex_of_definition_list": [
          "Our rubbish is taken away twice a week",
          "(also adjective) a rubbish bin/bag."
        ]
      },
      {
        "mean_english": "những điều vô nghĩa",
        "definition": "nonsense",
        "ex_of_definition_list": [
          "Don’t talk rubbish!"
        ]
      }
    ],
    "hash_code_list_definition_mean": "-1599840008"
  },
  {
    "link_it": "https://github.com/lmbstudiocontact/cb_dmean_5000_it_4/raw/main/ruby_cb_dmean_5000_it.json",
    "id_item": "ruby_cb_dmean_5000_it",
    "id_album": "105774007",
    "english": "ruby",
    "list_mean": [
      "hồng ngọc",
      "đỏ sẫm"
    ],
    "hash_code_list_mean": "604205513",
    "list_img": [
      {
        "link_thumb": "https://live.staticflickr.com/65535/51809340081_dd6078e8ba_n.jpg",
        "link_img": "https://live.staticflickr.com/65535/51809340081_b5a6ee0780_o.png",
        "id_image": "ruby_3521647"
      },
      {
        "link_thumb": "https://live.staticflickr.com/65535/51809695384_be8f472925_n.jpg",
        "link_img": "https://live.staticflickr.com/65535/51809695384_13c006e5f3_o.png",
        "id_image": "ruby_492063"
      }
    ],
    "hash_code_list_img": "-910318673",
    "list_definition_mean": [
      {
        "mean_english": "hồng ngọc",
        "definition": "a kind of deep red precious stone",
        "ex_of_definition_list": [
          "a ring set with rubies",
          "(also adjective) a ruby necklace."
        ]
      },
      {
        "mean_english": "đỏ sẫm",
        "definition": "(also adjective) (of) its colour/color",
        "ex_of_definition_list": [
          "a ruby dress."
        ]
      }
    ],
    "hash_code_list_definition_mean": "191488790"
  },
  {
    "link_it": "https://github.com/lmbstudiocontact/cb_dmean_5000_it_4/raw/main/rugby_cb_dmean_5000_it.json",
    "id_item": "rugby_cb_dmean_5000_it",
    "id_album": "105774007",
    "english": "rugby",
    "list_mean": [
      "môn bóng bầu dục"
    ],
    "hash_code_list_mean": "88157332",
    "list_img": [
      {
        "link_thumb": "https://live.staticflickr.com/65535/51809340001_ea0b959c9b_n.jpg",
        "link_img": "https://live.staticflickr.com/65535/51809340001_99bb2cb7c9_o.png",
        "id_image": "rugby_412770"
      },
      {
        "link_thumb": "https://live.staticflickr.com/65535/51809695174_dea4c717f0_n.jpg",
        "link_img": "https://live.staticflickr.com/65535/51809695174_50be7c4825_o.png",
        "id_image": "rugby_4645886"
      }
    ],
    "hash_code_list_img": "1890287081",
    "list_definition_mean": [
      {
        "mean_english": "môn bóng bầu dục",
        "definition": "(also rugby football",
        "ex_of_definition_list": [
          "abbreviation ruggerˈragə) a kind of football using an oval ball which can be carried.",
          "(also adjective) a rugby ball/player/match."
        ]
      }
    ],
    "hash_code_list_definition_mean": "1736800831"
  },
  {
    "link_it": "https://github.com/lmbstudiocontact/cb_dmean_5000_it_4/raw/main/ruin_cb_dmean_5000_it.json",
    "id_item": "ruin_cb_dmean_5000_it",
    "id_album": "105774007",
    "english": "ruin",
    "list_mean": [
      "sự đổ nát",
      "nguyên nhân thất bại",
      "phá sản",
      "làm tiêu tan",
      "làm hư hỏng"
    ],
    "hash_code_list_mean": "1956944398",
    "list_img": [
      {
        "link_thumb": "https://live.staticflickr.com/65535/51809695124_300fafe58d_n.jpg",
        "link_img": "https://live.staticflickr.com/65535/51809695124_6c1c7fc343_o.png",
        "id_image": "ruin_1171212"
      },
      {
        "link_thumb": "https://live.staticflickr.com/65535/51809339876_d000aa6aa2_n.jpg",
        "link_img": "https://live.staticflickr.com/65535/51809339876_e57e017f92_o.png",
        "id_image": "ruin_1594699"
      }
    ],
    "hash_code_list_img": "1222996026",
    "list_definition_mean": [
      {
        "mean_english": "sự đổ nát",
        "definition": "a broken, collapsed or decayed state",
        "ex_of_definition_list": [
          "The civil war led to the ruin of the city."
        ]
      },
      {
        "mean_english": "nguyên nhân thất bại",
        "definition": "a cause of collapse, decay etc",
        "ex_of_definition_list": [
          "Drink was his ruin."
        ]
      },
      {
        "mean_english": "phá sản",
        "definition": "financial disaster; complete loss of money",
        "ex_of_definition_list": [
          "The company is facing ruin."
        ]
      },
      {
        "mean_english": "làm tiêu tan",
        "definition": "to cause ruin to",
        "ex_of_definition_list": [
          "The scandal ruined his career."
        ]
      },
      {
        "mean_english": "làm hư hỏng",
        "definition": "to spoil; to treat too indulgently",
        "ex_of_definition_list": [
          "You are ruining that child!"
        ]
      }
    ],
    "hash_code_list_definition_mean": "-42286762"
  },
  {
    "link_it": "https://github.com/lmbstudiocontact/cb_dmean_5000_it_4/raw/main/ruler_cb_dmean_5000_it.json",
    "id_item": "ruler_cb_dmean_5000_it",
    "id_album": "105774007",
    "english": "ruler",
    "list_mean": [
      "người cai trị",
      "thước kẻ"
    ],
    "hash_code_list_mean": "554636082",
    "list_img": [
      {
        "link_thumb": "https://live.staticflickr.com/65535/51809454463_b4ef4fd0f8_n.jpg",
        "link_img": "https://live.staticflickr.com/65535/51809454463_0a930a4ec1_o.png",
        "id_image": "ruler_170615"
      },
      {
        "link_thumb": "https://live.staticflickr.com/65535/51809694739_31902ae06a_n.jpg",
        "link_img": "https://live.staticflickr.com/65535/51809694739_01e94c7f38_o.png",
        "id_image": "ruler_252500"
      }
    ],
    "hash_code_list_img": "1868683075",
    "list_definition_mean": [
      {
        "mean_english": "người cai trị",
        "definition": "a person who governs",
        "ex_of_definition_list": [
          "the ruler of the state."
        ]
      },
      {
        "mean_english": "thước kẻ",
        "definition": "a long narrow piece of wood, plastic etc for drawing straight lines",
        "ex_of_definition_list": [
          "I can’t draw straight lines without a ruler."
        ]
      }
    ],
    "hash_code_list_definition_mean": "357662622"
  },
  {
    "link_it": "https://github.com/lmbstudiocontact/cb_dmean_5000_it_4/raw/main/rule_cb_dmean_5000_it.json",
    "id_item": "rule_cb_dmean_5000_it",
    "id_album": "105774007",
    "english": "rule",
    "list_mean": [
      "sự thống trị",
      "quy tắc",
      "lệ thường",
      "nguyên tắc",
      "thước đo",
      "cai trị",
      "phán quyết",
      "kẻ dòng"
    ],
    "hash_code_list_mean": "779132397",
    "list_img": [
      {
        "link_thumb": "https://live.staticflickr.com/65535/51809454563_7a8392353c_n.jpg",
        "link_img": "https://live.staticflickr.com/65535/51809454563_d047eb29da_o.png",
        "id_image": "rule_309109"
      },
      {
        "link_thumb": "https://live.staticflickr.com/65535/51809454538_2a4e43ae0a_n.jpg",
        "link_img": "https://live.staticflickr.com/65535/51809454538_87a5fdd5e1_o.png",
        "id_image": "rule_452711"
      },
      {
        "link_thumb": "https://live.staticflickr.com/65535/51810076740_27e3f85e8b_n.jpg",
        "link_img": "https://live.staticflickr.com/65535/51810076740_b2f6438352_o.png",
        "id_image": "rule_645751"
      }
    ],
    "hash_code_list_img": "1013764514",
    "list_definition_mean": [
      {
        "mean_english": "sự thống trị",
        "definition": "government",
        "ex_of_definition_list": [
          "The country was under foreign rule for nearly thirty years."
        ]
      },
      {
        "mean_english": "quy tắc",
        "definition": "a regulation or order",
        "ex_of_definition_list": [
          "school rules."
        ]
      },
      {
        "mean_english": "lệ thường",
        "definition": "what usually happens or is done; a general principle",
        "ex_of_definition_list": [
          "He is an exception to the rule that fat people are usually happy."
        ]
      },
      {
        "mean_english": "nguyên tắc",
        "definition": "a general standard that guides one’s actions",
        "ex_of_definition_list": [
          "I make it a rule never to be late for appointments."
        ]
      },
      {
        "mean_english": "thước đo",
        "definition": "a marked strip of wood, metal etc for measuring",
        "ex_of_definition_list": [
          "He measured the windows with a rule."
        ]
      },
      {
        "mean_english": "cai trị",
        "definition": "to govern",
        "ex_of_definition_list": [
          "The king ruled (the people) wisely."
        ]
      },
      {
        "mean_english": "phán quyết",
        "definition": "to decide officially",
        "ex_of_definition_list": [
          "The judge ruled that the witness should be heard."
        ]
      },
      {
        "mean_english": "kẻ dòng",
        "definition": "to draw (a straight line)",
        "ex_of_definition_list": [
          "He ruled a line across the page."
        ]
      }
    ],
    "hash_code_list_definition_mean": "440840173"
  },
  {
    "link_it": "https://github.com/lmbstudiocontact/cb_dmean_5000_it_4/raw/main/rum_cb_dmean_5000_it.json",
    "id_item": "rum_cb_dmean_5000_it",
    "id_album": "105774007",
    "english": "rum",
    "list_mean": [
      "rượu rom"
    ],
    "hash_code_list_mean": "1107932095",
    "list_img": [
      {
        "link_thumb": "https://live.staticflickr.com/65535/51809454258_b73989b0cf_n.jpg",
        "link_img": "https://live.staticflickr.com/65535/51809454258_80be8d5cde_o.png",
        "id_image": "rum_1355973"
      },
      {
        "link_thumb": "https://live.staticflickr.com/65535/51810076470_3a27be8068_n.jpg",
        "link_img": "https://live.staticflickr.com/65535/51810076470_43583d5a0c_o.png",
        "id_image": "rum_2454602"
      },
      {
        "link_thumb": "https://live.staticflickr.com/65535/51809694509_8dfd4c9b8c_n.jpg",
        "link_img": "https://live.staticflickr.com/65535/51809694509_cde5506c48_o.png",
        "id_image": "rum_920565"
      }
    ],
    "hash_code_list_img": "-1606906375",
    "list_definition_mean": [
      {
        "mean_english": "rượu rom",
        "definition": "a type of alcoholic drink, a spirit made from sugar cane",
        "ex_of_definition_list": [
          "a bottle of rum."
        ]
      }
    ],
    "hash_code_list_definition_mean": "1576706831"
  },
  {
    "link_it": "https://github.com/lmbstudiocontact/cb_dmean_5000_it_4/raw/main/runner_cb_dmean_5000_it.json",
    "id_item": "runner_cb_dmean_5000_it",
    "id_album": "105774007",
    "english": "runner",
    "list_mean": [
      "người chạy",
      "đường trượt",
      "thực vật thân bò"
    ],
    "hash_code_list_mean": "147047762",
    "list_img": [
      {
        "link_thumb": "https://live.staticflickr.com/65535/51808383992_f11d3b1c55_n.jpg",
        "link_img": "https://live.staticflickr.com/65535/51808383992_77223cd233_o.png",
        "id_image": "runner_1397159"
      },
      {
        "link_thumb": "https://live.staticflickr.com/65535/51808383947_2dc63c26e0_n.jpg",
        "link_img": "https://live.staticflickr.com/65535/51808383947_2da83f2e5d_o.png",
        "id_image": "runner_6040288"
      }
    ],
    "hash_code_list_img": "613075577",
    "list_definition_mean": [
      {
        "mean_english": "người chạy",
        "definition": "a person who runs",
        "ex_of_definition_list": [
          "There are five runners in this race."
        ]
      },
      {
        "mean_english": "đường trượt",
        "definition": "the long narrow part on which a sledge etc moves",
        "ex_of_definition_list": [
          "He polished the runners of the sledge",
          "an ice-skate runner."
        ]
      }
    ],
    "hash_code_list_definition_mean": "-616395823"
  },
  {
    "link_it": "https://github.com/lmbstudiocontact/cb_dmean_5000_it_4/raw/main/runway_cb_dmean_5000_it.json",
    "id_item": "runway_cb_dmean_5000_it",
    "id_album": "105774007",
    "english": "runway",
    "list_mean": [
      "đường băng"
    ],
    "hash_code_list_mean": "857130690",
    "list_img": [
      {
        "link_thumb": "https://live.staticflickr.com/65535/51808383627_dd329ceb64_n.jpg",
        "link_img": "https://live.staticflickr.com/65535/51808383627_47ac108ef7_o.png",
        "id_image": "runway_1652888"
      },
      {
        "link_thumb": "https://live.staticflickr.com/65535/51810075775_cc37a7960d_n.jpg",
        "link_img": "https://live.staticflickr.com/65535/51810075775_13d61875cb_o.png",
        "id_image": "runway_5896862"
      },
      {
        "link_thumb": "https://live.staticflickr.com/65535/51809693904_af0deef3c3_n.jpg",
        "link_img": "https://live.staticflickr.com/65535/51809693904_9f7e3e4027_o.png",
        "id_image": "runway_825958"
      }
    ],
    "hash_code_list_img": "1868482395",
    "list_definition_mean": [
      {
        "mean_english": "đường băng",
        "definition": "a wide path from which aircraft take off and on which they land",
        "ex_of_definition_list": [
          "The plane landed on the runway."
        ]
      }
    ],
    "hash_code_list_definition_mean": "253648804"
  },
  {
    "link_it": "https://github.com/lmbstudiocontact/cb_dmean_5000_it_4/raw/main/run_cb_dmean_5000_it.json",
    "id_item": "run_cb_dmean_5000_it",
    "id_album": "105774007",
    "english": "run",
    "list_mean": [
      "chạy",
      "hoạt động",
      "chảy",
      "vận hành",
      "điều hành",
      "chạy đua",
      "chạy theo lộ trình",
      "kéo dài",
      "lái",
      "phai màu",
      "chở ai đi đâu; cho ai đi nhờ xe",
      "luồn, lướt",
      "trở nên",
      "sự chạy",
      "cuộc tham quan",
      "thời gian liên tục",
      "kẽ hở ở bít tất",
      "sự cho phép sử dụng",
      "ghi điểm trong môn crickit",
      "sân nuôi gà, vịt; bãi rào kín"
    ],
    "hash_code_list_mean": "711290876",
    "list_img": [
      {
        "link_thumb": "https://live.staticflickr.com/65535/51810076260_e882658655_n.jpg",
        "link_img": "https://live.staticflickr.com/65535/51810076260_0e78f62563_o.png",
        "id_image": "run_501115"
      },
      {
        "link_thumb": "https://live.staticflickr.com/65535/51809694169_bd77756e7d_n.jpg",
        "link_img": "https://live.staticflickr.com/65535/51809694169_48ecc00591_o.png",
        "id_image": "run_599543"
      }
    ],
    "hash_code_list_img": "-1840241782",
    "list_definition_mean": [
      {
        "mean_english": "chạy",
        "definition": "(of a person or animal) to move quickly, faster than walking",
        "ex_of_definition_list": [
          "He ran down the road."
        ]
      },
      {
        "mean_english": "hoạt động",
        "definition": "to move smoothly",
        "ex_of_definition_list": [
          "Trains run on rails."
        ]
      },
      {
        "mean_english": "chảy",
        "definition": "(of water etc) to flow",
        "ex_of_definition_list": [
          "Rivers run to the sea",
          "The tap is running."
        ]
      },
      {
        "mean_english": "vận hành",
        "definition": "(of a machine etc) to work or operate",
        "ex_of_definition_list": [
          "The engine is running",
          "He ran the motor to see if it was working."
        ]
      },
      {
        "mean_english": "điều hành",
        "definition": "to organize or manage",
        "ex_of_definition_list": [
          "He runs the business very efficiently."
        ]
      },
      {
        "mean_english": "chạy đua",
        "definition": "to race",
        "ex_of_definition_list": [
          "Is your horse running this afternoon?"
        ]
      },
      {
        "mean_english": "chạy theo lộ trình",
        "definition": "(of buses, trains etc) to travel regularly",
        "ex_of_definition_list": [
          "The buses run every half hour",
          "The train is running late."
        ]
      },
      {
        "mean_english": "kéo dài",
        "definition": "to last or continue; to go on",
        "ex_of_definition_list": [
          "The play ran for six weeks."
        ]
      },
      {
        "mean_english": "lái",
        "definition": "to own and use, especially of cars",
        "ex_of_definition_list": [
          "He runs a Rolls Royce."
        ]
      },
      {
        "mean_english": "phai màu",
        "definition": "(of colour/color) to spread",
        "ex_of_definition_list": [
          "When I washed my new dress the colour ran."
        ]
      },
      {
        "mean_english": "chở ai đi đâu; cho ai đi nhờ xe",
        "definition": "to drive (someone); to give (someone) a lift",
        "ex_of_definition_list": [
          "He ran me to the station."
        ]
      },
      {
        "mean_english": "luồn, lướt",
        "definition": "to move (something)",
        "ex_of_definition_list": [
          "She ran her fingers through his hair",
          "He ran his eyes over the letter."
        ]
      },
      {
        "mean_english": "trở nên",
        "definition": "(in certain phrases) to be or become",
        "ex_of_definition_list": [
          "The river ran dry",
          "My blood ran cold (= I was afraid)."
        ]
      },
      {
        "mean_english": "sự chạy",
        "definition": "the act of running",
        "ex_of_definition_list": [
          "He went for a run before breakfast."
        ]
      },
      {
        "mean_english": "cuộc tham quan",
        "definition": "a trip or drive",
        "ex_of_definition_list": [
          "We went for a run in the country."
        ]
      },
      {
        "mean_english": "thời gian liên tục",
        "definition": "a length of time (for which something continues)",
        "ex_of_definition_list": [
          "He’s had a run of bad luck."
        ]
      },
      {
        "mean_english": "kẽ hở ở bít tất",
        "definition": "a ladder (in a stocking etc)",
        "ex_of_definition_list": [
          "I’ve got a run in my tights."
        ]
      },
      {
        "mean_english": "sự cho phép sử dụng",
        "definition": "the free use (of a place)",
        "ex_of_definition_list": [
          "He gave me the run of his house."
        ]
      },
      {
        "mean_english": "ghi điểm trong môn crickit",
        "definition": "in cricket, a batsman’s act of running from one end of the wicket to the other, representing a single score",
        "ex_of_definition_list": [
          "He scored/made 50 runs for his team."
        ]
      },
      {
        "mean_english": "sân nuôi gà, vịt; bãi rào kín",
        "definition": "an enclosure or pen",
        "ex_of_definition_list": [
          "a chicken-run."
        ]
      }
    ],
    "hash_code_list_definition_mean": "1751999377"
  },
  {
    "link_it": "https://github.com/lmbstudiocontact/cb_dmean_5000_it_4/raw/main/rural_cb_dmean_5000_it.json",
    "id_item": "rural_cb_dmean_5000_it",
    "id_album": "105774007",
    "english": "rural",
    "list_mean": [
      "nông thôn"
    ],
    "hash_code_list_mean": "615539854",
    "list_img": [
      {
        "link_thumb": "https://live.staticflickr.com/65535/51809693829_5bd885603b_n.jpg",
        "link_img": "https://live.staticflickr.com/65535/51809693829_a5d57d2fe4_o.png",
        "id_image": "rural_1703523"
      },
      {
        "link_thumb": "https://live.staticflickr.com/65535/51808383537_10010db080_n.jpg",
        "link_img": "https://live.staticflickr.com/65535/51808383537_6c43608d2f_o.png",
        "id_image": "rural_3038937"
      }
    ],
    "hash_code_list_img": "-1652770918",
    "list_definition_mean": [
      {
        "mean_english": "nông thôn",
        "definition": "of the countryside",
        "ex_of_definition_list": [
          "a rural area."
        ]
      }
    ],
    "hash_code_list_definition_mean": "1181708920"
  },
  {
    "link_it": "https://github.com/lmbstudiocontact/cb_dmean_5000_it_4/raw/main/rust_cb_dmean_5000_it.json",
    "id_item": "rust_cb_dmean_5000_it",
    "id_album": "105774007",
    "english": "rust",
    "list_mean": [
      "gỉ sắt",
      "làm han gỉ"
    ],
    "hash_code_list_mean": "754118459",
    "list_img": [
      {
        "link_thumb": "https://live.staticflickr.com/65535/51809453643_8513ca1932_n.jpg",
        "link_img": "https://live.staticflickr.com/65535/51809453643_40852f97fa_o.png",
        "id_image": "rust_5660155"
      },
      {
        "link_thumb": "https://live.staticflickr.com/65535/51810075640_74cff592fa_n.jpg",
        "link_img": "https://live.staticflickr.com/65535/51810075640_ff2a60786b_o.png",
        "id_image": "rust_5825229"
      },
      {
        "link_thumb": "https://live.staticflickr.com/65535/51809693724_912f512eb3_n.jpg",
        "link_img": "https://live.staticflickr.com/65535/51809693724_481103b79f_o.png",
        "id_image": "rust_5931427"
      }
    ],
    "hash_code_list_img": "-866684793",
    "list_definition_mean": [
      {
        "mean_english": "gỉ sắt",
        "definition": "the reddish-brown substance which forms on iron and steel, caused by air and moisture",
        "ex_of_definition_list": [
          "The car was covered with rust."
        ]
      },
      {
        "mean_english": "làm han gỉ",
        "definition": "to (cause to) become covered with rust",
        "ex_of_definition_list": [
          "The rain has rusted the gate",
          "There’s a lot of old metal rusting in the garden."
        ]
      }
    ],
    "hash_code_list_definition_mean": "703756109"
  },
  {
    "link_it": "https://github.com/lmbstudiocontact/cb_dmean_5000_it_4/raw/main/sable_cb_dmean_5000_it.json",
    "id_item": "sable_cb_dmean_5000_it",
    "id_album": "105774007",
    "english": "sable",
    "list_mean": [
      "chồn zibêlin",
      "bút vẽ bằng lông chồn Zibêlin"
    ],
    "hash_code_list_mean": "-1477640195",
    "list_img": [
      {
        "link_thumb": "https://live.staticflickr.com/65535/51809693584_021b72b7be_n.jpg",
        "link_img": "https://live.staticflickr.com/65535/51809693584_0be4820295_o.png",
        "id_image": "sable_185751"
      }
    ],
    "hash_code_list_img": "1048340178",
    "list_definition_mean": [
      {
        "mean_english": "bút vẽ bằng lông chồn Zibêlin",
        "definition": "its fur",
        "ex_of_definition_list": [
          "Artists’ brushes are sometimes made of sable",
          "(also adjective) a sable coat."
        ]
      }
    ],
    "hash_code_list_definition_mean": "1975888792"
  },
  {
    "link_it": "https://github.com/lmbstudiocontact/cb_dmean_5000_it_4/raw/main/sachet_cb_dmean_5000_it.json",
    "id_item": "sachet_cb_dmean_5000_it",
    "id_album": "105774007",
    "english": "sachet",
    "list_mean": [
      "bao, túi , gói"
    ],
    "hash_code_list_mean": "-646058649",
    "list_img": [
      {
        "link_thumb": "https://live.staticflickr.com/65535/51809338251_40b459bb70_n.jpg",
        "link_img": "https://live.staticflickr.com/65535/51809338251_965d0af55b_o.png",
        "id_image": "sachet_1211055"
      },
      {
        "link_thumb": "https://live.staticflickr.com/65535/51809453153_bbffcbf843_n.jpg",
        "link_img": "https://live.staticflickr.com/65535/51809453153_305a3f093e_o.png",
        "id_image": "sachet_3219278"
      },
      {
        "link_thumb": "https://live.staticflickr.com/65535/51809338176_3e3e776e7c_n.jpg",
        "link_img": "https://live.staticflickr.com/65535/51809338176_361a97b019_o.png",
        "id_image": "sachet_4142980"
      }
    ],
    "hash_code_list_img": "-2115106253",
    "list_definition_mean": [
      {
        "mean_english": "bao, túi , gói",
        "definition": "a (small) sealed packet containing a product in liquid or powder form",
        "ex_of_definition_list": [
          "a sachet of shampoo."
        ]
      }
    ],
    "hash_code_list_definition_mean": "1345286025"
  },
  {
    "link_it": "https://github.com/lmbstudiocontact/cb_dmean_5000_it_4/raw/main/sack_cb_dmean_5000_it.json",
    "id_item": "sack_cb_dmean_5000_it",
    "id_album": "105774007",
    "english": "sack",
    "list_mean": [
      "bao tải",
      "sa thải, cách chức"
    ],
    "hash_code_list_mean": "1699428563",
    "list_img": [
      {
        "link_thumb": "https://live.staticflickr.com/65535/51810075210_19a0b54666_n.jpg",
        "link_img": "https://live.staticflickr.com/65535/51810075210_9cbf66c2ed_o.png",
        "id_image": "sack_1152966"
      },
      {
        "link_thumb": "https://live.staticflickr.com/65535/51809338106_034aa0ae3a_n.jpg",
        "link_img": "https://live.staticflickr.com/65535/51809338106_383275abe1_o.png",
        "id_image": "sack_1352327"
      },
      {
        "link_thumb": "https://live.staticflickr.com/65535/51810075100_11d082bec4_n.jpg",
        "link_img": "https://live.staticflickr.com/65535/51810075100_12c7a284e6_o.png",
        "id_image": "sack_2954789"
      },
      {
        "link_thumb": "https://live.staticflickr.com/65535/51809693304_9ae2c6d97a_n.jpg",
        "link_img": "https://live.staticflickr.com/65535/51809693304_c204692434_o.png",
        "id_image": "sack_6359685"
      }
    ],
    "hash_code_list_img": "-439617703",
    "list_definition_mean": [
      {
        "mean_english": "bao tải",
        "definition": "a large bag of coarse cloth, strong paper or plastic",
        "ex_of_definition_list": [
          "The potatoes were put into sacks."
        ]
      },
      {
        "mean_english": "sa thải, cách chức",
        "definition": "to dismiss (a person) from his job",
        "ex_of_definition_list": [
          "One of the workmen was sacked for drunkenness."
        ]
      }
    ],
    "hash_code_list_definition_mean": "552274499"
  },
  {
    "link_it": "https://github.com/lmbstudiocontact/cb_dmean_5000_it_4/raw/main/sacrament_cb_dmean_5000_it.json",
    "id_item": "sacrament_cb_dmean_5000_it",
    "id_album": "105774007",
    "english": "sacrament",
    "list_mean": [
      "lễ ban phước"
    ],
    "hash_code_list_mean": "1065402087",
    "list_img": [
      {
        "link_thumb": "https://live.staticflickr.com/65535/51809452913_aaee4dd263_n.jpg",
        "link_img": "https://live.staticflickr.com/65535/51809452913_dc9e5b82be_o.png",
        "id_image": "sacrament_280026"
      }
    ],
    "hash_code_list_img": "1033155772",
    "list_definition_mean": [
      {
        "mean_english": "lễ ban phước",
        "definition": "in the Christian church, a ceremony regarded as especially sacred, eg marriage, or baptism",
        "ex_of_definition_list": [
          "a religious sacrament."
        ]
      }
    ],
    "hash_code_list_definition_mean": "1465333919"
  },
  {
    "link_it": "https://github.com/lmbstudiocontact/cb_dmean_5000_it_4/raw/main/sacrifice_cb_dmean_5000_it.json",
    "id_item": "sacrifice_cb_dmean_5000_it",
    "id_album": "105774007",
    "english": "sacrifice",
    "list_mean": [
      "sự cúng tế, sự hi sinh",
      "sự hi sinh",
      "cúng",
      "hi sinh"
    ],
    "hash_code_list_mean": "-1547981389",
    "list_img": [
      {
        "link_thumb": "https://live.staticflickr.com/65535/51809452813_1656d3aff4_n.jpg",
        "link_img": "https://live.staticflickr.com/65535/51809452813_a2ebcf8229_o.png",
        "id_image": "sacrifice_5521210"
      },
      {
        "link_thumb": "https://live.staticflickr.com/65535/51808382887_43be83897c_n.jpg",
        "link_img": "https://live.staticflickr.com/65535/51808382887_1dcbe08394_o.png",
        "id_image": "sacrifice_5521294"
      }
    ],
    "hash_code_list_img": "-1562673437",
    "list_definition_mean": [
      {
        "mean_english": "sự cúng tế, sự hi sinh",
        "definition": "the act of offering something (eg an animal that is specially killed) to a god",
        "ex_of_definition_list": [
          "A lamb was offered in sacrifice."
        ]
      },
      {
        "mean_english": "sự hi sinh",
        "definition": "the thing that is offered in this way",
        "ex_of_definition_list": [
          "A slaughtered lamb was offered as a sacrifice."
        ]
      },
      {
        "mean_english": "sự hi sinh",
        "definition": "something of value given away or up in order to gain something more important or to benefit another person",
        "ex_of_definition_list": [
          "His parents made sacrifices to pay for his education."
        ]
      },
      {
        "mean_english": "cúng",
        "definition": "to offer as a sacrifice",
        "ex_of_definition_list": [
          "He sacrificed a sheep in the temple."
        ]
      },
      {
        "mean_english": "hi sinh",
        "definition": "to give away etc for the sake of something or someone else",
        "ex_of_definition_list": [
          "He sacrificed his life trying to save the children from the burning house."
        ]
      }
    ],
    "hash_code_list_definition_mean": "891805455"
  },
  {
    "link_it": "https://github.com/lmbstudiocontact/cb_dmean_5000_it_4/raw/main/saddle_cb_dmean_5000_it.json",
    "id_item": "saddle_cb_dmean_5000_it",
    "id_album": "105774007",
    "english": "saddle",
    "list_mean": [
      "yên ngựa, yên xe",
      "thắng yên ngựa"
    ],
    "hash_code_list_mean": "-1575362231",
    "list_img": [
      {
        "link_thumb": "https://live.staticflickr.com/65535/51809337781_505ed6d199_n.jpg",
        "link_img": "https://live.staticflickr.com/65535/51809337781_9db249dbdd_o.png",
        "id_image": "saddle_2464823"
      },
      {
        "link_thumb": "https://live.staticflickr.com/65535/51809452688_26b7b917b1_n.jpg",
        "link_img": "https://live.staticflickr.com/65535/51809452688_04df462e46_o.png",
        "id_image": "saddle_878991"
      }
    ],
    "hash_code_list_img": "-1061764629",
    "list_definition_mean": [
      {
        "mean_english": "yên ngựa, yên xe",
        "definition": "a seat for a rider",
        "ex_of_definition_list": [
          "The bicycle saddle is too high."
        ]
      },
      {
        "mean_english": "thắng yên ngựa",
        "definition": "(opposite unsaddle) to put a saddle on",
        "ex_of_definition_list": [
          "He saddled his horse and rode away."
        ]
      }
    ],
    "hash_code_list_definition_mean": "1861948829"
  },
  {
    "link_it": "https://github.com/lmbstudiocontact/cb_dmean_5000_it_4/raw/main/sad_cb_dmean_5000_it.json",
    "id_item": "sad_cb_dmean_5000_it",
    "id_album": "105774007",
    "english": "sad",
    "list_mean": [
      "buồn rầu"
    ],
    "hash_code_list_mean": "-1862306003",
    "list_img": [
      {
        "link_thumb": "https://live.staticflickr.com/65535/51809693139_7e052024e6_n.jpg",
        "link_img": "https://live.staticflickr.com/65535/51809693139_42d905b77f_o.png",
        "id_image": "sad_1128885"
      },
      {
        "link_thumb": "https://live.staticflickr.com/65535/51808382877_790f765923_n.jpg",
        "link_img": "https://live.staticflickr.com/65535/51808382877_83884b3c74_o.png",
        "id_image": "sad_599625"
      }
    ],
    "hash_code_list_img": "1129322139",
    "list_definition_mean": [
      {
        "mean_english": "buồn rầu",
        "definition": "unhappy or causing unhappiness",
        "ex_of_definition_list": [
          "She’s sad because her son is ill",
          "a sad face."
        ]
      }
    ],
    "hash_code_list_definition_mean": "1976547703"
  },
  {
    "link_it": "https://github.com/lmbstudiocontact/cb_dmean_5000_it_4/raw/main/safety_cb_dmean_5000_it.json",
    "id_item": "safety_cb_dmean_5000_it",
    "id_album": "105774007",
    "english": "safety",
    "list_mean": [
      "sự an toàn"
    ],
    "hash_code_list_mean": "461175353",
    "list_img": [
      {
        "link_thumb": "https://live.staticflickr.com/65535/51810074550_614c99cfe3_n.jpg",
        "link_img": "https://live.staticflickr.com/65535/51810074550_bd017462a3_o.png",
        "id_image": "safety_1998603"
      },
      {
        "link_thumb": "https://live.staticflickr.com/65535/51808382517_200f1b96e1_n.jpg",
        "link_img": "https://live.staticflickr.com/65535/51808382517_56d5befc35_o.png",
        "id_image": "safety_3684402"
      },
      {
        "link_thumb": "https://live.staticflickr.com/65535/51809337451_6fdfe77ba8_n.jpg",
        "link_img": "https://live.staticflickr.com/65535/51809337451_687b974e36_o.png",
        "id_image": "safety_5939776"
      }
    ],
    "hash_code_list_img": "-702502620",
    "list_definition_mean": [
      {
        "mean_english": "sự an toàn",
        "definition": "the state of being safe",
        "ex_of_definition_list": [
          "I worry about the children’s safety on these busy roads",
          "a place of safety",
          "(also adjective) safety goggles",
          "safety helmet."
        ]
      }
    ],
    "hash_code_list_definition_mean": "1121345563"
  },
  {
    "link_it": "https://github.com/lmbstudiocontact/cb_dmean_5000_it_4/raw/main/safe_cb_dmean_5000_it.json",
    "id_item": "safe_cb_dmean_5000_it",
    "id_album": "105774007",
    "english": "safe",
    "list_mean": [
      "an toàn",
      "có thể tin cậy",
      "vô hại, an toàn",
      "an toàn, đáng tin cậy",
      "tủ sắt , két sắt"
    ],
    "hash_code_list_mean": "-1537080974",
    "list_img": [
      {
        "link_thumb": "https://live.staticflickr.com/65535/51809452508_7237089d63_n.jpg",
        "link_img": "https://live.staticflickr.com/65535/51809452508_d6edf9a8ec_o.png",
        "id_image": "safe_2867912"
      },
      {
        "link_thumb": "https://live.staticflickr.com/65535/51809692869_647cb286b6_n.jpg",
        "link_img": "https://live.staticflickr.com/65535/51809692869_e79a38aeb3_o.png",
        "id_image": "safe_3064162"
      },
      {
        "link_thumb": "https://live.staticflickr.com/65535/51809337566_6a879e5e3e_n.jpg",
        "link_img": "https://live.staticflickr.com/65535/51809337566_d4bf03167a_o.png",
        "id_image": "safe_5448593"
      }
    ],
    "hash_code_list_img": "-1552337681",
    "list_definition_mean": [
      {
        "mean_english": "an toàn",
        "definition": "(opposite unsafe) protected, or free (from danger etc)",
        "ex_of_definition_list": [
          "The children are safe from danger in the garden."
        ]
      },
      {
        "mean_english": "có thể tin cậy",
        "definition": "providing good protection",
        "ex_of_definition_list": [
          "You should keep your money in a safe place."
        ]
      },
      {
        "mean_english": "an toàn",
        "definition": "unharmed",
        "ex_of_definition_list": [
          "The missing child has been found safe and well."
        ]
      },
      {
        "mean_english": "vô hại, an toàn",
        "definition": "not likely to cause harm",
        "ex_of_definition_list": [
          "These pills are safe for children."
        ]
      },
      {
        "mean_english": "an toàn, đáng tin cậy",
        "definition": "(of a person) reliable",
        "ex_of_definition_list": [
          "a safe driver",
          "He’s a very fast driver, but he’s safe enough."
        ]
      },
      {
        "mean_english": "tủ sắt , két sắt",
        "definition": "a heavy metal chest or box in which money etc can be locked away safely",
        "ex_of_definition_list": [
          "There is a small safe hidden behind that picture on the wall."
        ]
      }
    ],
    "hash_code_list_definition_mean": "-1041569783"
  },
  {
    "link_it": "https://github.com/lmbstudiocontact/cb_dmean_5000_it_4/raw/main/saffron_cb_dmean_5000_it.json",
    "id_item": "saffron_cb_dmean_5000_it",
    "id_album": "105774007",
    "english": "saffron",
    "list_mean": [
      "nghệ tây",
      "màu vàng nghệ",
      "có màu vàng nghệ"
    ],
    "hash_code_list_mean": "-246887086",
    "list_img": [
      {
        "link_thumb": "https://live.staticflickr.com/65535/51809692729_64d6c4a12f_n.jpg",
        "link_img": "https://live.staticflickr.com/65535/51809692729_eddeddfa6c_o.png",
        "id_image": "saffron_4139311"
      },
      {
        "link_thumb": "https://live.staticflickr.com/65535/51810074440_168f8d52df_n.jpg",
        "link_img": "https://live.staticflickr.com/65535/51810074440_ebf92f2297_o.png",
        "id_image": "saffron_5930619"
      }
    ],
    "hash_code_list_img": "562903645",
    "list_definition_mean": [
      {
        "mean_english": "nghệ tây",
        "definition": "a yellow colouring/coloring and flavouring/flavoring substance used in cooking",
        "ex_of_definition_list": [
          "We added some saffron to the rice."
        ]
      }
    ],
    "hash_code_list_definition_mean": "883782958"
  },
  {
    "link_it": "https://github.com/lmbstudiocontact/cb_dmean_5000_it_4/raw/main/sailor_cb_dmean_5000_it.json",
    "id_item": "sailor_cb_dmean_5000_it",
    "id_album": "105774007",
    "english": "sailor",
    "list_mean": [
      "thủy thủ"
    ],
    "hash_code_list_mean": "1373374424",
    "list_img": [
      {
        "link_thumb": "https://live.staticflickr.com/65535/51810074255_b6f15aa7d6_n.jpg",
        "link_img": "https://live.staticflickr.com/65535/51810074255_ceea91d524_o.png",
        "id_image": "sailor_4436814"
      },
      {
        "link_thumb": "https://live.staticflickr.com/65535/51810074215_c1c688cbd9_n.jpg",
        "link_img": "https://live.staticflickr.com/65535/51810074215_4956c943d4_o.png",
        "id_image": "sailor_5052563"
      },
      {
        "link_thumb": "https://live.staticflickr.com/65535/51810074200_3d79ffc47b_n.jpg",
        "link_img": "https://live.staticflickr.com/65535/51810074200_8cb1fe953a_o.png",
        "id_image": "sailor_6150489"
      }
    ],
    "hash_code_list_img": "-274722197",
    "list_definition_mean": [
      {
        "mean_english": "thủy thủ",
        "definition": "a member of a ship’s crew whose job is helping to sail a ship",
        "ex_of_definition_list": [
          "a sailor in the merchant navy."
        ]
      }
    ],
    "hash_code_list_definition_mean": "1435477609"
  },
  {
    "link_it": "https://github.com/lmbstudiocontact/cb_dmean_5000_it_4/raw/main/sail_cb_dmean_5000_it.json",
    "id_item": "sail_cb_dmean_5000_it",
    "id_album": "105774007",
    "english": "sail",
    "list_mean": [
      "cánh buồm",
      "chuyến đi xa bằng thuyền buồm",
      "bản hứng gió (ở cối xay gió)",
      "chạy bằng buồm",
      "điều khiển (thuyền buồm)",
      "đi thuyền buồm",
      "đi biển, chạy trên biển",
      "đi (du lịch) bằng đường biển",
      "lướt, trôi, lao, vượt qua…"
    ],
    "hash_code_list_mean": "1549575397",
    "list_img": [
      {
        "link_thumb": "https://live.staticflickr.com/65535/51809452148_2f3485aa1b_n.jpg",
        "link_img": "https://live.staticflickr.com/65535/51809452148_5932c86379_o.png",
        "id_image": "sail_1949309"
      },
      {
        "link_thumb": "https://live.staticflickr.com/65535/51809692654_bb835d8c6c_n.jpg",
        "link_img": "https://live.staticflickr.com/65535/51809692654_10f0ea3abf_o.png",
        "id_image": "sail_859139"
      }
    ],
    "hash_code_list_img": "-1759977206",
    "list_definition_mean": [
      {
        "mean_english": "cánh buồm",
        "definition": "a sheet of strong cloth spread to catch the wind, by which a ship is driven forward",
        "ex_of_definition_list": [
          "They are hoisting the sails."
        ]
      },
      {
        "mean_english": "chuyến đi xa bằng thuyền buồm",
        "definition": "a journey in a ship",
        "ex_of_definition_list": [
          "a sail in his yacht",
          "a week’s sail to the island."
        ]
      },
      {
        "mean_english": "chạy bằng buồm",
        "definition": "(of a ship) to be moved by sails",
        "ex_of_definition_list": [
          "The yacht sailed away."
        ]
      },
      {
        "mean_english": "điều khiển (thuyền buồm)",
        "definition": "to steer or navigate a ship or boat",
        "ex_of_definition_list": [
          "He sailed (the boat) to the island."
        ]
      },
      {
        "mean_english": "đi thuyền buồm",
        "definition": "to go in a ship or boat (with or without sails)",
        "ex_of_definition_list": [
          "I’ve never sailed through the Mediterranean."
        ]
      },
      {
        "mean_english": "đi biển, chạy trên biển",
        "definition": "to begin a voyage",
        "ex_of_definition_list": [
          "The ship sails today",
          "My aunt sailed today."
        ]
      },
      {
        "mean_english": "đi (du lịch) bằng đường biển",
        "definition": "to travel on (the sea etc) in a ship",
        "ex_of_definition_list": [
          "He sailed the North Sea."
        ]
      },
      {
        "mean_english": "lướt, trôi, lao, vượt qua…",
        "definition": "to move steadily and easily",
        "ex_of_definition_list": [
          "Clouds sailed across the sky",
          "He sailed through his exams",
          "She sailed into the room."
        ]
      }
    ],
    "hash_code_list_definition_mean": "635581798"
  },
  {
    "link_it": "https://github.com/lmbstudiocontact/cb_dmean_5000_it_4/raw/main/saint_cb_dmean_5000_it.json",
    "id_item": "saint_cb_dmean_5000_it",
    "id_album": "105774007",
    "english": "saint",
    "list_mean": [
      "vị thánh",
      "người thánh thiện"
    ],
    "hash_code_list_mean": "-1219881909",
    "list_img": [
      {
        "link_thumb": "https://live.staticflickr.com/65535/51810074165_71d1d02be4_n.jpg",
        "link_img": "https://live.staticflickr.com/65535/51810074165_8062fcc2f0_o.png",
        "id_image": "saint_2333251"
      }
    ],
    "hash_code_list_img": "1484649475",
    "list_definition_mean": [
      {
        "mean_english": "vị thánh",
        "definition": "(often abbreviated to St, especially when used in the names of places, plants etc) a title given especially by the Roman Catholic and Orthodox churches to a very good or holy person after his death",
        "ex_of_definition_list": [
          "Saint Matthew",
          "St John’s Road."
        ]
      },
      {
        "mean_english": "người thánh thiện",
        "definition": "a very good, kind person",
        "ex_of_definition_list": [
          "You really are a saint to put up with her."
        ]
      }
    ],
    "hash_code_list_definition_mean": "-1113120119"
  },
  {
    "link_it": "https://github.com/lmbstudiocontact/cb_dmean_5000_it_4/raw/main/sake_cb_dmean_5000_it.json",
    "id_item": "sake_cb_dmean_5000_it",
    "id_album": "105774007",
    "english": "sake",
    "list_mean": [
      "vì ai/ cái gì",
      "vì lợi ích của ai/ cái gì"
    ],
    "hash_code_list_mean": "395128256",
    "list_img": [
      {
        "link_thumb": "https://live.staticflickr.com/65535/51810074130_478c621d77_n.jpg",
        "link_img": "https://live.staticflickr.com/65535/51810074130_8345e4c6fd_o.png",
        "id_image": "sake_2700273"
      },
      {
        "link_thumb": "https://live.staticflickr.com/65535/51809692394_7927c0cfd7_n.jpg",
        "link_img": "https://live.staticflickr.com/65535/51809692394_c8231ff4ed_o.png",
        "id_image": "sake_2721385"
      }
    ],
    "hash_code_list_img": "31461917",
    "list_definition_mean": [
      {
        "mean_english": "vì ai/ cái gì",
        "definition": "in order to benefit",
        "ex_of_definition_list": [
          "He bought a house in the country for the sake of his wife’s health."
        ]
      },
      {
        "mean_english": "vì lợi ích của ai/ cái gì",
        "definition": "because of a desire for",
        "ex_of_definition_list": [
          "For the sake of peace, he said he agreed with her."
        ]
      }
    ],
    "hash_code_list_definition_mean": "-2100108794"
  },
  {
    "link_it": "https://github.com/lmbstudiocontact/cb_dmean_5000_it_4/raw/main/salad_cb_dmean_5000_it.json",
    "id_item": "salad_cb_dmean_5000_it",
    "id_album": "105774007",
    "english": "salad",
    "list_mean": [
      "rau trộn dầu giấm"
    ],
    "hash_code_list_mean": "-1895450742",
    "list_img": [
      {
        "link_thumb": "https://live.staticflickr.com/65535/51809692369_e6fa99b823_n.jpg",
        "link_img": "https://live.staticflickr.com/65535/51809692369_9209d5c4c3_o.png",
        "id_image": "salad_557811"
      },
      {
        "link_thumb": "https://live.staticflickr.com/65535/51810074020_6bf24b9526_n.jpg",
        "link_img": "https://live.staticflickr.com/65535/51810074020_0ce764d2cf_o.png",
        "id_image": "salad_590721"
      }
    ],
    "hash_code_list_img": "7540377",
    "list_definition_mean": [
      {
        "mean_english": "rau trộn dầu giấm",
        "definition": "(a dish of) mixed raw vegetables",
        "ex_of_definition_list": [
          "a mixed salad."
        ]
      }
    ],
    "hash_code_list_definition_mean": "1725312120"
  },
  {
    "link_it": "https://github.com/lmbstudiocontact/cb_dmean_5000_it_4/raw/main/salamander_cb_dmean_5000_it.json",
    "id_item": "salamander_cb_dmean_5000_it",
    "id_album": "105774007",
    "english": "salamander",
    "list_mean": [
      "con kỳ giông"
    ],
    "hash_code_list_mean": "-502500272",
    "list_img": [
      {
        "link_thumb": "https://live.staticflickr.com/65535/51809336916_7ebdbd8dfc_n.jpg",
        "link_img": "https://live.staticflickr.com/65535/51809336916_9048263788_o.png",
        "id_image": "salamander_2683205"
      },
      {
        "link_thumb": "https://live.staticflickr.com/65535/51809451798_0bb19c0979_n.jpg",
        "link_img": "https://live.staticflickr.com/65535/51809451798_3d23438205_o.png",
        "id_image": "salamander_371950"
      }
    ],
    "hash_code_list_img": "-1524434774",
    "list_definition_mean": [
      {
        "mean_english": "con kỳ giông",
        "definition": "an animal with a lizard-like appearance, having short legs and a long tail, that lives both on land and in water",
        "ex_of_definition_list": [
          "Salamanders and newts are in the amphibian family."
        ]
      }
    ],
    "hash_code_list_definition_mean": "288488732"
  },
  {
    "link_it": "https://github.com/lmbstudiocontact/cb_dmean_5000_it_4/raw/main/salami_cb_dmean_5000_it.json",
    "id_item": "salami_cb_dmean_5000_it",
    "id_album": "105774007",
    "english": "salami",
    "list_mean": [
      "xúc xích salami"
    ],
    "hash_code_list_mean": "-939409147",
    "list_img": [
      {
        "link_thumb": "https://live.staticflickr.com/65535/51808381937_ef96758b24_n.jpg",
        "link_img": "https://live.staticflickr.com/65535/51808381937_2b127c8e63_o.png",
        "id_image": "salami_2403314"
      },
      {
        "link_thumb": "https://live.staticflickr.com/65535/51809336846_6467b56017_n.jpg",
        "link_img": "https://live.staticflickr.com/65535/51809336846_5b1a92c0eb_o.png",
        "id_image": "salami_3390385"
      }
    ],
    "hash_code_list_img": "1565918755",
    "list_definition_mean": [
      {
        "mean_english": "xúc xích salami",
        "definition": "a type of large spicy sausage that is cut into thin slices and eaten cold",
        "ex_of_definition_list": [
          "pepper salami."
        ]
      }
    ],
    "hash_code_list_definition_mean": "1386009561"
  },
  {
    "link_it": "https://github.com/lmbstudiocontact/cb_dmean_5000_it_4/raw/main/salary_cb_dmean_5000_it.json",
    "id_item": "salary_cb_dmean_5000_it",
    "id_album": "105774007",
    "english": "salary",
    "list_mean": [
      "tiền lương"
    ],
    "hash_code_list_mean": "765640535",
    "list_img": [
      {
        "link_thumb": "https://live.staticflickr.com/65535/51809451663_a5119864a2_n.jpg",
        "link_img": "https://live.staticflickr.com/65535/51809451663_df523f4772_o.png",
        "id_image": "salary_4310786"
      },
      {
        "link_thumb": "https://live.staticflickr.com/65535/51808381887_807c666418_n.jpg",
        "link_img": "https://live.staticflickr.com/65535/51808381887_5f5ff16da1_o.png",
        "id_image": "salary_537223"
      },
      {
        "link_thumb": "https://live.staticflickr.com/65535/51808381832_cdbc7b0abf_n.jpg",
        "link_img": "https://live.staticflickr.com/65535/51808381832_02cde5fc25_o.png",
        "id_image": "salary_868890"
      }
    ],
    "hash_code_list_img": "358624884",
    "list_definition_mean": [
      {
        "mean_english": "tiền lương",
        "definition": "a fixed, regular usually monthly payment for work",
        "ex_of_definition_list": [
          "Secretarial salaries in London are quite high."
        ]
      }
    ],
    "hash_code_list_definition_mean": "1643219382"
  },
  {
    "link_it": "https://github.com/lmbstudiocontact/cb_dmean_5000_it_4/raw/main/sale_cb_dmean_5000_it.json",
    "id_item": "sale_cb_dmean_5000_it",
    "id_album": "105774007",
    "english": "sale",
    "list_mean": [
      "sự bán",
      "sự bán hạ giá",
      "việc bán hàng"
    ],
    "hash_code_list_mean": "-862331276",
    "list_img": [
      {
        "link_thumb": "https://live.staticflickr.com/65535/51810073745_9b34d7bed7_n.jpg",
        "link_img": "https://live.staticflickr.com/65535/51810073745_71492f6a79_o.png",
        "id_image": "sale_1027976"
      },
      {
        "link_thumb": "https://live.staticflickr.com/65535/51808381702_71cb0fcdf4_n.jpg",
        "link_img": "https://live.staticflickr.com/65535/51808381702_65d0cfe0bf_o.png",
        "id_image": "sale_2273409"
      }
    ],
    "hash_code_list_img": "995021324",
    "list_definition_mean": [
      {
        "mean_english": "sự bán",
        "definition": "the act of giving something to someone in exchange for money",
        "ex_of_definition_list": [
          "the sale of a house",
          "Sales of cars have increased."
        ]
      },
      {
        "mean_english": "sự bán hạ giá",
        "definition": "in a shop etc, an offer of goods at lowered prices for a short time",
        "ex_of_definition_list": [
          "I bought my dress in a sale."
        ]
      },
      {
        "mean_english": "việc bán hàng",
        "definition": "an event at which goods are sold",
        "ex_of_definition_list": [
          "an auction sale",
          "a book sale."
        ]
      }
    ],
    "hash_code_list_definition_mean": "340988547"
  },
  {
    "link_it": "https://github.com/lmbstudiocontact/cb_dmean_5000_it_4/raw/main/saline_cb_dmean_5000_it.json",
    "id_item": "saline_cb_dmean_5000_it",
    "id_album": "105774007",
    "english": "saline",
    "list_mean": [
      "có muối"
    ],
    "hash_code_list_mean": "363624623",
    "list_img": [
      {
        "link_thumb": "https://live.staticflickr.com/65535/51810073335_a7a4766e1e_n.jpg",
        "link_img": "https://live.staticflickr.com/65535/51810073335_cf15760820_o.png",
        "id_image": "saline_2941513"
      },
      {
        "link_thumb": "https://live.staticflickr.com/65535/51809691714_9797c0998e_n.jpg",
        "link_img": "https://live.staticflickr.com/65535/51809691714_56da76f613_o.png",
        "id_image": "saline_469426"
      },
      {
        "link_thumb": "https://live.staticflickr.com/65535/51810073375_66657408ab_n.jpg",
        "link_img": "https://live.staticflickr.com/65535/51810073375_3606c121fb_o.png",
        "id_image": "saline_813604"
      }
    ],
    "hash_code_list_img": "-2080866444",
    "list_definition_mean": [
      {
        "mean_english": "có muối",
        "definition": "containing salt",
        "ex_of_definition_list": [
          "a saline solution."
        ]
      }
    ],
    "hash_code_list_definition_mean": "82217021"
  },
  {
    "link_it": "https://github.com/lmbstudiocontact/cb_dmean_5000_it_4/raw/main/salmonellosis_cb_dmean_5000_it.json",
    "id_item": "salmonellosis_cb_dmean_5000_it",
    "id_album": "105774007",
    "english": "salmonellosis",
    "list_mean": [
      "ngộ độc thực phẩm do salmonella"
    ],
    "hash_code_list_mean": "1149658671",
    "list_img": [
      {
        "link_thumb": "https://live.staticflickr.com/65535/51809691579_d1269cbb51_n.jpg",
        "link_img": "https://live.staticflickr.com/65535/51809691579_44a1cf0da9_o.png",
        "id_image": "salmonellosis_3411476"
      }
    ],
    "hash_code_list_img": "1856036809",
    "list_definition_mean": [
      {
        "mean_english": "ngộ độc thực phẩm do salmonella",
        "definition": "food poisoning caused by eating food contaminated with salmonella bacteria; salmonella",
        "ex_of_definition_list": [
          "Salmonellosis is one of the most common foodborne diseases."
        ]
      }
    ],
    "hash_code_list_definition_mean": "34526973"
  },
  {
    "link_it": "https://github.com/lmbstudiocontact/cb_dmean_5000_it_4/raw/main/salon_cb_dmean_5000_it.json",
    "id_item": "salon_cb_dmean_5000_it",
    "id_album": "105774007",
    "english": "salon",
    "list_mean": [
      "thẩm mỹ viện"
    ],
    "hash_code_list_mean": "1488725061",
    "list_img": [
      {
        "link_thumb": "https://live.staticflickr.com/65535/51809336171_a6136238e5_n.jpg",
        "link_img": "https://live.staticflickr.com/65535/51809336171_15b46e3478_o.png",
        "id_image": "salon_1053051"
      },
      {
        "link_thumb": "https://live.staticflickr.com/65535/51808381132_708fb5c156_n.jpg",
        "link_img": "https://live.staticflickr.com/65535/51808381132_191973c35d_o.png",
        "id_image": "salon_2286608"
      },
      {
        "link_thumb": "https://live.staticflickr.com/65535/51810073040_01c6180ba3_n.jpg",
        "link_img": "https://live.staticflickr.com/65535/51810073040_1b332b78e5_o.png",
        "id_image": "salon_2377470"
      },
      {
        "link_thumb": "https://live.staticflickr.com/65535/51810073130_dbce65895f_n.jpg",
        "link_img": "https://live.staticflickr.com/65535/51810073130_3a825fb8e8_o.png",
        "id_image": "salon_452705"
      }
    ],
    "hash_code_list_img": "-152562090",
    "list_definition_mean": [
      {
        "mean_english": "thẩm mỹ viện",
        "definition": "a name sometimes given to a place where hairdressing etc is done",
        "ex_of_definition_list": [
          "a beauty salon",
          "My hairdresser has opened a new salon."
        ]
      }
    ],
    "hash_code_list_definition_mean": "1481793659"
  },
  {
    "link_it": "https://github.com/lmbstudiocontact/cb_dmean_5000_it_4/raw/main/saloon_cb_dmean_5000_it.json",
    "id_item": "saloon_cb_dmean_5000_it",
    "id_album": "105774007",
    "english": "saloon",
    "list_mean": [
      "phòng khách lớn",
      "ca-bin dành cho người lái và hành khách",
      "quán rượu"
    ],
    "hash_code_list_mean": "-1189351031",
    "list_img": [
      {
        "link_thumb": "https://live.staticflickr.com/65535/51809691329_3ec5588529_n.jpg",
        "link_img": "https://live.staticflickr.com/65535/51809691329_e89ac8eb86_o.png",
        "id_image": "saloon_1353835"
      },
      {
        "link_thumb": "https://live.staticflickr.com/65535/51809450953_66c5705d82_n.jpg",
        "link_img": "https://live.staticflickr.com/65535/51809450953_a07b576ef3_o.png",
        "id_image": "saloon_2396819"
      },
      {
        "link_thumb": "https://live.staticflickr.com/65535/51808381082_bc5dba0965_n.jpg",
        "link_img": "https://live.staticflickr.com/65535/51808381082_27805f73d3_o.png",
        "id_image": "saloon_683819"
      }
    ],
    "hash_code_list_img": "-812872324",
    "list_definition_mean": [
      {
        "mean_english": "phòng khách lớn",
        "definition": "a large public room on a ship",
        "ex_of_definition_list": [
          "the dining saloon."
        ]
      },
      {
        "mean_english": "ca-bin dành cho người lái và hành khách",
        "definition": "(American sedan) a motor car with enclosed seating space for driver and at least three passengers",
        "ex_of_definition_list": [
          "a family saloon."
        ]
      },
      {
        "mean_english": "quán rượu",
        "definition": "a place where alcoholic drinks are sold",
        "ex_of_definition_list": [
          "The police searched in all the saloons for the thief."
        ]
      }
    ],
    "hash_code_list_definition_mean": "208006446"
  },
  {
    "link_it": "https://github.com/lmbstudiocontact/cb_dmean_5000_it_4/raw/main/salty_cb_dmean_5000_it.json",
    "id_item": "salty_cb_dmean_5000_it",
    "id_album": "105774007",
    "english": "salty",
    "list_mean": [
      "mặn"
    ],
    "hash_code_list_mean": "348643",
    "list_img": [
      {
        "link_thumb": "https://live.staticflickr.com/65535/51808380947_3588fbcc24_n.jpg",
        "link_img": "https://live.staticflickr.com/65535/51808380947_84d68124e3_o.png",
        "id_image": "salt_4276022"
      }
    ],
    "hash_code_list_img": "983881140",
    "list_definition_mean": [
      {
        "mean_english": "mặn",
        "definition": "containing or tasting of salt",
        "ex_of_definition_list": [
          "Tears are salty water."
        ]
      }
    ],
    "hash_code_list_definition_mean": "1372050577"
  },
  {
    "link_it": "https://github.com/lmbstudiocontact/cb_dmean_5000_it_4/raw/main/salt_cb_dmean_5000_it.json",
    "id_item": "salt_cb_dmean_5000_it",
    "id_album": "105774007",
    "english": "salt",
    "list_mean": [
      "muối",
      "chất đậm đà",
      "thủy thủ lão luyện",
      "tẩm muối, ướp muối",
      "ướp muối, nêm muối"
    ],
    "hash_code_list_mean": "620641028",
    "list_img": [
      {
        "link_thumb": "https://live.staticflickr.com/65535/51809691204_64f77c6a42_n.jpg",
        "link_img": "https://live.staticflickr.com/65535/51809691204_7e663466e1_o.png",
        "id_image": "salt_4264778"
      },
      {
        "link_thumb": "https://live.staticflickr.com/65535/51808380947_3588fbcc24_n.jpg",
        "link_img": "https://live.staticflickr.com/65535/51808380947_84d68124e3_o.png",
        "id_image": "salt_4276022"
      },
      {
        "link_thumb": "https://live.staticflickr.com/65535/51809335956_d8be21bf99_n.jpg",
        "link_img": "https://live.staticflickr.com/65535/51809335956_bddc6d383f_o.png",
        "id_image": "salt_877702"
      }
    ],
    "hash_code_list_img": "-105645856",
    "list_definition_mean": [
      {
        "mean_english": "muối",
        "definition": "(also common salt) sodium chloride, a white substance frequently used for seasoning",
        "ex_of_definition_list": [
          "The soup needs more salt."
        ]
      },
      {
        "mean_english": "thủy thủ lão luyện",
        "definition": "a sailor, especially an experienced one",
        "ex_of_definition_list": [
          "an old salt."
        ]
      },
      {
        "mean_english": "tẩm muối, ướp muối",
        "definition": "containing, tasting of, preserved in salt",
        "ex_of_definition_list": [
          "salt water",
          "salt pork."
        ]
      },
      {
        "mean_english": "ướp muối, nêm muối",
        "definition": "to put salt on or in",
        "ex_of_definition_list": [
          "Have you salted the potatoes?"
        ]
      }
    ],
    "hash_code_list_definition_mean": "-1436775264"
  },
  {
    "link_it": "https://github.com/lmbstudiocontact/cb_dmean_5000_it_4/raw/main/salute_cb_dmean_5000_it.json",
    "id_item": "salute_cb_dmean_5000_it",
    "id_album": "105774007",
    "english": "salute",
    "list_mean": [
      "chào, chào hỏi",
      "chào mừng",
      "việc chào mừng"
    ],
    "hash_code_list_mean": "-856476564",
    "list_img": [
      {
        "link_thumb": "https://live.staticflickr.com/65535/51809335776_725057b1f0_n.jpg",
        "link_img": "https://live.staticflickr.com/65535/51809335776_47ff3b8b80_o.png",
        "id_image": "salute_1000394"
      },
      {
        "link_thumb": "https://live.staticflickr.com/65535/51810072760_592bc489f9_n.jpg",
        "link_img": "https://live.staticflickr.com/65535/51810072760_3d9be53b5c_o.png",
        "id_image": "salute_599540"
      }
    ],
    "hash_code_list_img": "16941319",
    "list_definition_mean": [
      {
        "mean_english": "chào, chào hỏi",
        "definition": "(especially in the forces) to raise the (usually right) hand to the forehead to show respect",
        "ex_of_definition_list": [
          "They saluted their commanding officer."
        ]
      },
      {
        "mean_english": "chào mừng",
        "definition": "to honour by firing eg large guns",
        "ex_of_definition_list": [
          "They saluted the Queen by firing one hundred guns."
        ]
      },
      {
        "mean_english": "việc chào mừng",
        "definition": "an act of saluting",
        "ex_of_definition_list": [
          "The officer gave a salute",
          "a 21-gun salute."
        ]
      }
    ],
    "hash_code_list_definition_mean": "614363636"
  },
  {
    "link_it": "https://github.com/lmbstudiocontact/cb_dmean_5000_it_4/raw/main/salvation_cb_dmean_5000_it.json",
    "id_item": "salvation_cb_dmean_5000_it",
    "id_album": "105774007",
    "english": "salvation",
    "list_mean": [
      "sự cứu rỗi linh hồn",
      "sự cứu tế, sự cứu giúp"
    ],
    "hash_code_list_mean": "-765337327",
    "list_img": [
      {
        "link_thumb": "https://live.staticflickr.com/65535/51809335751_ae4f95fee8_n.jpg",
        "link_img": "https://live.staticflickr.com/65535/51809335751_9926e24e4b_o.png",
        "id_image": "salvation_252068"
      }
    ],
    "hash_code_list_img": "180820982",
    "list_definition_mean": [
      {
        "mean_english": "sự cứu tế, sự cứu giúp",
        "definition": "the cause, means, or act of saving",
        "ex_of_definition_list": [
          "This delay was the salvation of the army."
        ]
      }
    ],
    "hash_code_list_definition_mean": "1321697319"
  },
  {
    "link_it": "https://github.com/lmbstudiocontact/cb_dmean_5000_it_4/raw/main/salver_cb_dmean_5000_it.json",
    "id_item": "salver_cb_dmean_5000_it",
    "id_album": "105774007",
    "english": "salver",
    "list_mean": [
      "khay, mâm"
    ],
    "hash_code_list_mean": "138920430",
    "list_img": [
      {
        "link_thumb": "https://live.staticflickr.com/65535/51810072650_a3272ab010_n.jpg",
        "link_img": "https://live.staticflickr.com/65535/51810072650_816630664c_o.png",
        "id_image": "salver_4797370"
      }
    ],
    "hash_code_list_img": "1584080480",
    "list_definition_mean": [
      {
        "mean_english": "khay, mâm",
        "definition": "a small tray, often made of silver",
        "ex_of_definition_list": [
          "He received a silver salver as a retirement present."
        ]
      }
    ],
    "hash_code_list_definition_mean": "1692847564"
  }
]