[
  {
    "link_it": "https://github.com/lmbstudiocontact/cb_dmean_5000_it_3/raw/main/perch_cb_dmean_5000_it.json",
    "id_item": "perch_cb_dmean_5000_it",
    "id_album": "102079919",
    "english": "perch",
    "list_mean": [
      "chỗ chim đậu",
      "vị trí cao",
      "đậu",
      "đặt lên cao"
    ],
    "hash_code_list_mean": "-810949252",
    "list_img": [
      {
        "link_thumb": "https://live.staticflickr.com/65535/51810057835_cc9eafdec4_n.jpg",
        "link_img": "https://live.staticflickr.com/65535/51810057835_190ac1c09c_o.png",
        "id_image": "perch_311600"
      }
    ],
    "hash_code_list_img": "205343734",
    "list_example": [
      "He looked down from his perch on the roof."
    ],
    "hash_code_list_example": "1026188300"
  },
  {
    "link_it": "https://github.com/lmbstudiocontact/cb_dmean_5000_it_3/raw/main/percussion_cb_dmean_5000_it.json",
    "id_item": "percussion_cb_dmean_5000_it",
    "id_album": "102079919",
    "english": "percussion",
    "list_mean": [
      "bộ gõ",
      "sự đập"
    ],
    "hash_code_list_mean": "-766052068",
    "list_img": [
      {
        "link_thumb": "https://live.staticflickr.com/65535/51809676099_f6d52c0093_n.jpg",
        "link_img": "https://live.staticflickr.com/65535/51809676099_cc100d1cff_o.png",
        "id_image": "percussion_4457239"
      },
      {
        "link_thumb": "https://live.staticflickr.com/65535/51809320961_d90ed79c31_n.jpg",
        "link_img": "https://live.staticflickr.com/65535/51809320961_b2b497d4eb_o.png",
        "id_image": "percussion_5391309"
      }
    ],
    "hash_code_list_img": "-78157520",
    "list_example": [
      "He plays (the) percussion in the orchestra",
      "(also adjective) a percussion instrument.",
      "It assumes that electronic keyboards and pitched percussion instruments are available, alongside standard classroom percussion and at least one suitably loaded computer.",
      "The voices adopt the rhythm given by the percussion section, and sentences are rendered mechanical by being broken into short pieces.",
      "In any case, the gently thudding accompaniment is certainly not to be found anywhere in the percussion parts.",
      "Bifacial points are pointed tools shaped from large flake blanks by collateral bifacial percussion and pressure flaking."
    ],
    "hash_code_list_example": "-859975763"
  },
  {
    "link_it": "https://github.com/lmbstudiocontact/cb_dmean_5000_it_3/raw/main/perfection_cb_dmean_5000_it.json",
    "id_item": "perfection_cb_dmean_5000_it",
    "id_album": "102079919",
    "english": "perfection",
    "list_mean": [
      "sự hoàn hảo"
    ],
    "hash_code_list_mean": "-1487100438",
    "list_img": [
      {
        "link_thumb": "https://live.staticflickr.com/65535/51808365857_e42f6dbeae_n.jpg",
        "link_img": "https://live.staticflickr.com/65535/51808365857_5bbc3a0c0a_o.png",
        "id_image": "perfection_4401389"
      },
      {
        "link_thumb": "https://live.staticflickr.com/65535/51809320886_e2cd9d8c48_n.jpg",
        "link_img": "https://live.staticflickr.com/65535/51809320886_9667cc55e9_o.png",
        "id_image": "perfection_5266062"
      }
    ],
    "hash_code_list_img": "1789733849",
    "list_example": [
      "He wants to achieve absolute perfection with everything he cooks.",
      "Two of the video sequences in this act portray this perfection by processing television adverts which feature female and male models.",
      "No production was ever the same, but there was an underlying technique and obsessive search for perfection underlying them all.",
      "They cut all sorts of capers and whiffed the meat as it slowly came to perfection with the seasoning penetrating to the bone."
    ],
    "hash_code_list_example": "-1923771059"
  },
  {
    "link_it": "https://github.com/lmbstudiocontact/cb_dmean_5000_it_3/raw/main/perfect_cb_dmean_5000_it.json",
    "id_item": "perfect_cb_dmean_5000_it",
    "id_album": "102079919",
    "english": "perfect",
    "list_mean": [
      "hoàn hảo",
      "chính xác",
      "hoàn toàn",
      "hoàn thiện"
    ],
    "hash_code_list_mean": "41520753",
    "list_img": [
      {
        "link_thumb": "https://live.staticflickr.com/65535/51809436158_9c776c5d60_n.jpg",
        "link_img": "https://live.staticflickr.com/65535/51809436158_a1e0266aef_o.png",
        "id_image": "perfect_2166016"
      }
    ],
    "hash_code_list_img": "964736110",
    "list_example": [
      "a perfect day for a holiday",
      "a perfect end to the day.",
      "a perfect copy.",
      "a perfect stranger.",
      "He went to France to perfect his French."
    ],
    "hash_code_list_example": "1240219220"
  },
  {
    "link_it": "https://github.com/lmbstudiocontact/cb_dmean_5000_it_3/raw/main/performance_cb_dmean_5000_it.json",
    "id_item": "performance_cb_dmean_5000_it",
    "id_album": "102079919",
    "english": "performance",
    "list_mean": [
      "sự thực hiện",
      "cuộc biểu diễn"
    ],
    "hash_code_list_mean": "-619019118",
    "list_img": [
      {
        "link_thumb": "https://live.staticflickr.com/65535/51810057610_600cb72a24_n.jpg",
        "link_img": "https://live.staticflickr.com/65535/51810057610_3881b8f978_o.png",
        "id_image": "performance_1624387"
      },
      {
        "link_thumb": "https://live.staticflickr.com/65535/51810057590_b718a3c2c8_n.jpg",
        "link_img": "https://live.staticflickr.com/65535/51810057590_d795d697c9_o.png",
        "id_image": "performance_1945765"
      },
      {
        "link_thumb": "https://live.staticflickr.com/65535/51809435968_d59d6c9dba_n.jpg",
        "link_img": "https://live.staticflickr.com/65535/51809435968_6ce337c212_o.png",
        "id_image": "performance_2617907"
      }
    ],
    "hash_code_list_img": "-374234433",
    "list_example": [
      "He is very conscientious in the performance of his duties.",
      "His performance in the exams was not very good.",
      "The company gave a performance of ‘Othello’"
    ],
    "hash_code_list_example": "-404258711"
  },
  {
    "link_it": "https://github.com/lmbstudiocontact/cb_dmean_5000_it_3/raw/main/performer_cb_dmean_5000_it.json",
    "id_item": "performer_cb_dmean_5000_it",
    "id_album": "102079919",
    "english": "performer",
    "list_mean": [
      "người biểu diễn"
    ],
    "hash_code_list_mean": "2010278775",
    "list_img": [
      {
        "link_thumb": "https://live.staticflickr.com/65535/51809320766_564a24a216_n.jpg",
        "link_img": "https://live.staticflickr.com/65535/51809320766_d77bfac9fc_o.png",
        "id_image": "performer_4090140"
      }
    ],
    "hash_code_list_img": "1432768677",
    "list_example": [
      "The concert attracted some of the country’s top performers.",
      "The market is further enhanced by live performers who act out the varied timeless arts.",
      "Their electronic specialists work closely with performers to develop individualised electronic instruments.",
      "Chapter 4 discusses many central considerations for performers: setting up goals and planning the path, structuring time of practice and preparation towards achieving such goals.",
      "The affect of poor performers on agencies' performance and morale can far exceed their small numbers.",
      "In music, the act of revisiting existing technology brings about new relationships between composers, performers and listeners as well as between notation and sonic material.",
      "In spite of an increasing number of females engaging in the musical profession, the textbooks hardly mention famous female composers and performers.",
      "Perhaps both performers, if in very different ways, ultimately show some uncertainty about how to handle this music.",
      "We must be careful to add all information sources, publications and interviews with the composer, other performers, musicologists, listeners and others."
    ],
    "hash_code_list_example": "1488940736"
  },
  {
    "link_it": "https://github.com/lmbstudiocontact/cb_dmean_5000_it_3/raw/main/perfume_cb_dmean_5000_it.json",
    "id_item": "perfume_cb_dmean_5000_it",
    "id_album": "102079919",
    "english": "perfume",
    "list_mean": [
      "hương thơm",
      "nước hoa",
      "xịt nước hoa",
      "tỏa hương"
    ],
    "hash_code_list_mean": "1587384972",
    "list_img": [
      {
        "link_thumb": "https://live.staticflickr.com/65535/51810057370_60a796e5b6_n.jpg",
        "link_img": "https://live.staticflickr.com/65535/51810057370_8ee4124688_o.png",
        "id_image": "perfume_1660259"
      },
      {
        "link_thumb": "https://live.staticflickr.com/65535/51809320646_6176db297c_n.jpg",
        "link_img": "https://live.staticflickr.com/65535/51809320646_258c0e9731_o.png",
        "id_image": "perfume_410448"
      }
    ],
    "hash_code_list_img": "-1901068474",
    "list_example": [
      "the perfume of roses."
    ],
    "hash_code_list_example": "1936222311"
  },
  {
    "link_it": "https://github.com/lmbstudiocontact/cb_dmean_5000_it_3/raw/main/perimeter_cb_dmean_5000_it.json",
    "id_item": "perimeter_cb_dmean_5000_it",
    "id_album": "102079919",
    "english": "perimeter",
    "list_mean": [
      "chu vi"
    ],
    "hash_code_list_mean": "-1361115070",
    "list_img": [
      {
        "link_thumb": "https://live.staticflickr.com/65535/51809320511_8e03820144_n.jpg",
        "link_img": "https://live.staticflickr.com/65535/51809320511_1b00724a42_o.png",
        "id_image": "perimeter_390048"
      }
    ],
    "hash_code_list_img": "1717136491",
    "list_example": [
      "the perimeter of the city",
      "the perimeter of a circle.",
      "First, for any given shape, the area:perimeter ratio of a control area increases with size."
    ],
    "hash_code_list_example": "-1339153883"
  },
  {
    "link_it": "https://github.com/lmbstudiocontact/cb_dmean_5000_it_3/raw/main/period_cb_dmean_5000_it.json",
    "id_item": "period_cb_dmean_5000_it",
    "id_album": "102079919",
    "english": "period",
    "list_mean": [
      "giai đoạn",
      "kỷ",
      "dấu chấm",
      "cổ/ lâu"
    ],
    "hash_code_list_mean": "509031439",
    "list_img": [
      {
        "link_thumb": "https://live.staticflickr.com/65535/51808365462_7befbcc5d7_n.jpg",
        "link_img": "https://live.staticflickr.com/65535/51808365462_35189b1220_o.png",
        "id_image": "period_4277930"
      },
      {
        "link_thumb": "https://live.staticflickr.com/65535/51809320491_4ce173a9f5_n.jpg",
        "link_img": "https://live.staticflickr.com/65535/51809320491_f40f3c2820_o.png",
        "id_image": "period_5746612"
      }
    ],
    "hash_code_list_img": "2130924550",
    "list_example": [
      "a period of three days",
      "a period of waiting.",
      "period costumes",
      "His house is full of period furniture (=antique furniture).",
      "The changes that took place in this period are beyond the scope of this article.",
      "Respondents reported retrospectively on experience of 17 premenstrual symptoms ' just before the start of your period ' over the previous 12 months.",
      "A 3-min period of dark adaptation was followed by a 1-min period of light adaptation to the two surrounds.",
      "Beetles were removed from the three traps and baits replaced each week for the three-week period following pat placement.",
      "The decline in residence with children was most rapid during the period from 1940 to 1980, when more than half the total change took place."
    ],
    "hash_code_list_example": "1474748932"
  },
  {
    "link_it": "https://github.com/lmbstudiocontact/cb_dmean_5000_it_3/raw/main/permission_cb_dmean_5000_it.json",
    "id_item": "permission_cb_dmean_5000_it",
    "id_album": "102079919",
    "english": "permission",
    "list_mean": [
      "sự cho phép"
    ],
    "hash_code_list_mean": "1756177270",
    "list_img": [
      {
        "link_thumb": "https://live.staticflickr.com/65535/51810057200_8a4f962fff_n.jpg",
        "link_img": "https://live.staticflickr.com/65535/51810057200_6848e2e5e7_o.png",
        "id_image": "permission_2172839"
      },
      {
        "link_thumb": "https://live.staticflickr.com/65535/51808365367_38e9119abd_n.jpg",
        "link_img": "https://live.staticflickr.com/65535/51808365367_471cf897ff_o.png",
        "id_image": "permission_3663412"
      },
      {
        "link_thumb": "https://live.staticflickr.com/65535/51809675384_79814c3e19_n.jpg",
        "link_img": "https://live.staticflickr.com/65535/51809675384_3484555e79_o.png",
        "id_image": "permission_4391723"
      }
    ],
    "hash_code_list_img": "-921249746",
    "list_example": [
      "She gave me permission to leave.",
      "If not, should parents be required to give their permission when their children want to have themselves cloned?",
      "He considered leaving the fort without consulting him or getting his permission as intolerable behaviour.",
      "Between 1719 and 1730, for example, the provincial gave permission for the entry of 23 girls to live with the nuns in their cells.",
      "Provincial involvement came down to granting permission for large-scale water management works and formulating rules for the reduction of negative side effects for third parties.",
      "Additionally, hospital permission must be obtained for continued utilization of hospital resources, and investigators are required to provide letters documenting such approval."
    ],
    "hash_code_list_example": "-133884715"
  },
  {
    "link_it": "https://github.com/lmbstudiocontact/cb_dmean_5000_it_3/raw/main/permissive_cb_dmean_5000_it.json",
    "id_item": "permissive_cb_dmean_5000_it",
    "id_album": "102079919",
    "english": "permissive",
    "list_mean": [
      "cho phép"
    ],
    "hash_code_list_mean": "1761465972",
    "list_img": [
      {
        "link_thumb": "https://live.staticflickr.com/65535/51810057170_06647d89d0_n.jpg",
        "link_img": "https://live.staticflickr.com/65535/51810057170_bd9e91d8f6_o.png",
        "id_image": "permissive_5101278"
      }
    ],
    "hash_code_list_img": "965190151",
    "list_example": [
      "the permissive society of the Sixties."
    ],
    "hash_code_list_example": "-1295353898"
  },
  {
    "link_it": "https://github.com/lmbstudiocontact/cb_dmean_5000_it_3/raw/main/permit_cb_dmean_5000_it.json",
    "id_item": "permit_cb_dmean_5000_it",
    "id_album": "102079919",
    "english": "permit",
    "list_mean": [
      "cho phép",
      "giấy phép"
    ],
    "hash_code_list_mean": "-580339787",
    "list_img": [
      {
        "link_thumb": "https://live.staticflickr.com/65535/51810057140_4cc62c6070_n.jpg",
        "link_img": "https://live.staticflickr.com/65535/51810057140_50cc94faaa_o.png",
        "id_image": "permit_2904496"
      },
      {
        "link_thumb": "https://live.staticflickr.com/65535/51810057125_1dacfa0af9_n.jpg",
        "link_img": "https://live.staticflickr.com/65535/51810057125_67a954e930_o.png",
        "id_image": "permit_3965937"
      },
      {
        "link_thumb": "https://live.staticflickr.com/65535/51809675344_1d9ed4b594_n.jpg",
        "link_img": "https://live.staticflickr.com/65535/51809675344_4d3cfb5b84_o.png",
        "id_image": "permit_5965877"
      }
    ],
    "hash_code_list_img": "-850550162",
    "list_example": [
      "We have a permit to export our product."
    ],
    "hash_code_list_example": "-1360097095"
  },
  {
    "link_it": "https://github.com/lmbstudiocontact/cb_dmean_5000_it_3/raw/main/perm_cb_dmean_5000_it.json",
    "id_item": "perm_cb_dmean_5000_it",
    "id_album": "102079919",
    "english": "perm",
    "list_mean": [
      "quăn",
      "làm tóc quăn"
    ],
    "hash_code_list_mean": "214770244",
    "list_img": [
      {
        "link_thumb": "https://live.staticflickr.com/65535/51809320426_c9a49b8871_n.jpg",
        "link_img": "https://live.staticflickr.com/65535/51809320426_c40cfccf46_o.png",
        "id_image": "perm_3125044"
      }
    ],
    "hash_code_list_img": "257999213",
    "list_example": [
      "I suggest that he might do it like the pools and perm two from four.",
      "The offers read like a full perm on a football pool coupon.",
      "It is open to any landowner to perm it these activities to take place on his land by permission and that excludes those which are criminal offences.",
      "I wish to goodness we had decided on a perm and not a large haircut.",
      "I would perm them in favour of those which relate to the harm test based on prejudice in one way or another."
    ],
    "hash_code_list_example": "864645370"
  },
  {
    "link_it": "https://github.com/lmbstudiocontact/cb_dmean_5000_it_3/raw/main/personality_cb_dmean_5000_it.json",
    "id_item": "personality_cb_dmean_5000_it",
    "id_album": "102079919",
    "english": "personality",
    "list_mean": [
      "tính cách",
      "cá tính",
      "người nổi tiếng"
    ],
    "hash_code_list_mean": "1141736994",
    "list_img": [
      {
        "link_thumb": "https://live.staticflickr.com/65535/51809435398_aea55221f8_n.jpg",
        "link_img": "https://live.staticflickr.com/65535/51809435398_5e83cd2a2b_o.png",
        "id_image": "personality_1474710"
      },
      {
        "link_thumb": "https://live.staticflickr.com/65535/51810056980_8b53f82cc9_n.jpg",
        "link_img": "https://live.staticflickr.com/65535/51810056980_682b6531ef_o.png",
        "id_image": "personality_1945688"
      },
      {
        "link_thumb": "https://live.staticflickr.com/65535/51809435378_cb8d6f66ca_n.jpg",
        "link_img": "https://live.staticflickr.com/65535/51809435378_5611132da0_o.png",
        "id_image": "personality_2072729"
      },
      {
        "link_thumb": "https://live.staticflickr.com/65535/51808365112_310cbd1410_n.jpg",
        "link_img": "https://live.staticflickr.com/65535/51808365112_716c76938d_o.png",
        "id_image": "personality_4525542"
      }
    ],
    "hash_code_list_img": "-1423521716",
    "list_example": [
      "(also adjective) a personality cult (= very great, usually too great, admiration for a person, usually a political leader)."
    ],
    "hash_code_list_example": "-267987595"
  },
  {
    "link_it": "https://github.com/lmbstudiocontact/cb_dmean_5000_it_3/raw/main/personal_cb_dmean_5000_it.json",
    "id_item": "personal_cb_dmean_5000_it",
    "id_album": "102079919",
    "english": "personal",
    "list_mean": [
      "cá nhân",
      "riêng tư",
      "đích thân",
      "nhận xét về cá nhân một người"
    ],
    "hash_code_list_mean": "1205876906",
    "list_img": [
      {
        "link_thumb": "https://live.staticflickr.com/65535/51810057045_a653ef888a_n.jpg",
        "link_img": "https://live.staticflickr.com/65535/51810057045_1ba4901ff6_o.png",
        "id_image": "personal_1471063"
      },
      {
        "link_thumb": "https://live.staticflickr.com/65535/51808365192_682fec68b0_n.jpg",
        "link_img": "https://live.staticflickr.com/65535/51808365192_28d432c362_o.png",
        "id_image": "personal_2596477"
      },
      {
        "link_thumb": "https://live.staticflickr.com/65535/51808365152_67b290612c_n.jpg",
        "link_img": "https://live.staticflickr.com/65535/51808365152_cd9227ed91_o.png",
        "id_image": "personal_3306801"
      }
    ],
    "hash_code_list_img": "-1305875338",
    "list_example": [
      "This is his personal opinion",
      "The matter will have my personal attention.",
      "This is a personal matter between him and me.",
      "The Prime Minister will make a personal appearance.",
      "personal remarks"
    ],
    "hash_code_list_example": "-1576560873"
  },
  {
    "link_it": "https://github.com/lmbstudiocontact/cb_dmean_5000_it_3/raw/main/personnel_cb_dmean_5000_it.json",
    "id_item": "personnel_cb_dmean_5000_it",
    "id_album": "102079919",
    "english": "personnel",
    "list_mean": [
      "nhân sự"
    ],
    "hash_code_list_mean": "2030623831",
    "list_img": [
      {
        "link_thumb": "https://live.staticflickr.com/65535/51809435338_bf0bb09999_n.jpg",
        "link_img": "https://live.staticflickr.com/65535/51809435338_fb8bb47504_o.png",
        "id_image": "personnel_1643823"
      },
      {
        "link_thumb": "https://live.staticflickr.com/65535/51809675179_e59c8ec583_n.jpg",
        "link_img": "https://live.staticflickr.com/65535/51809675179_67904fd19f_o.png",
        "id_image": "personnel_5102337"
      }
    ],
    "hash_code_list_img": "-1956727283",
    "list_example": [
      "Our personnel are very highly trained",
      "(also adjective) a personnel manager.",
      "Table 1 indicates the valuation for hourly costs (social security contributions included), and tariffs for personnel involved in either health care or coordination.",
      "Most of the urban factories cancelled some or all of their personnel transportation services when the crisis hit.",
      "Assessment has traditionally been regarded as the responsibility of psychiatrists, but in recent years the role of non-medically qualified personnel has been examined.",
      "The chancellery very actively dealt with personnel questions and staffing for all state institutions with f unctionaries of different specialties and ranks.",
      "Owing to limited personnel resources, the midday home visit could not be conducted for the first 37 families."
    ],
    "hash_code_list_example": "684128310"
  },
  {
    "link_it": "https://github.com/lmbstudiocontact/cb_dmean_5000_it_3/raw/main/person_cb_dmean_5000_it.json",
    "id_item": "person_cb_dmean_5000_it",
    "id_album": "102079919",
    "english": "person",
    "list_mean": [
      "người",
      "theo người"
    ],
    "hash_code_list_mean": "-667310177",
    "list_img": [
      {
        "link_thumb": "https://live.staticflickr.com/65535/51809435473_4cfa0c6de0_n.jpg",
        "link_img": "https://live.staticflickr.com/65535/51809435473_7822f2e351_o.png",
        "id_image": "person_6003230"
      },
      {
        "link_thumb": "https://live.staticflickr.com/65535/51809435448_5788ffec1c_n.jpg",
        "link_img": "https://live.staticflickr.com/65535/51809435448_c2daf44a72_o.png",
        "id_image": "person_6146116"
      },
      {
        "link_thumb": "https://live.staticflickr.com/65535/51809320331_af9a3a8a7b_n.jpg",
        "link_img": "https://live.staticflickr.com/65535/51809320331_692d092437_o.png",
        "id_image": "person_992636"
      }
    ],
    "hash_code_list_img": "-1399539988",
    "list_example": [
      "There’s a person outside who wants to speak to you",
      "He never carried money on his person (= with him"
    ],
    "hash_code_list_example": "-592226164"
  },
  {
    "link_it": "https://github.com/lmbstudiocontact/cb_dmean_5000_it_3/raw/main/perspective_cb_dmean_5000_it.json",
    "id_item": "perspective_cb_dmean_5000_it",
    "id_album": "102079919",
    "english": "perspective",
    "list_mean": [
      "hình phối cảnh",
      "cái nhìn"
    ],
    "hash_code_list_mean": "-1666518710",
    "list_img": [
      {
        "link_thumb": "https://live.staticflickr.com/65535/51809675149_80b3ff9531_n.jpg",
        "link_img": "https://live.staticflickr.com/65535/51809675149_c3fbf13cd6_o.png",
        "id_image": "perspective_1589434"
      },
      {
        "link_thumb": "https://live.staticflickr.com/65535/51809435308_94b3179074_n.jpg",
        "link_img": "https://live.staticflickr.com/65535/51809435308_7688d1038f_o.png",
        "id_image": "perspective_2209882"
      },
      {
        "link_thumb": "https://live.staticflickr.com/65535/51808364987_edd599c893_n.jpg",
        "link_img": "https://live.staticflickr.com/65535/51808364987_c84b5b3b87_o.png",
        "id_image": "perspective_2254984"
      },
      {
        "link_thumb": "https://live.staticflickr.com/65535/51808364977_177c0e260c_n.jpg",
        "link_img": "https://live.staticflickr.com/65535/51808364977_7b3bc2e9a3_o.png",
        "id_image": "perspective_2547587"
      },
      {
        "link_thumb": "https://live.staticflickr.com/65535/51809435323_eb7565c24f_n.jpg",
        "link_img": "https://live.staticflickr.com/65535/51809435323_f6ecb5aa2c_o.png",
        "id_image": "perspective_992637"
      }
    ],
    "hash_code_list_img": "-569349990",
    "list_example": [
      "I would like a clearer perspective of the situation.",
      "Therefore, with this easier criterion, the sequence from visual perspective taking to pronoun acquisition was reversed, contradicting our first two hypotheses.",
      "Attempting to write a global geographical perspective on organic agriculture is a major challenge."
    ],
    "hash_code_list_example": "-1403916153"
  },
  {
    "link_it": "https://github.com/lmbstudiocontact/cb_dmean_5000_it_3/raw/main/pestilence_cb_dmean_5000_it.json",
    "id_item": "pestilence_cb_dmean_5000_it",
    "id_album": "102079919",
    "english": "pestilence",
    "list_mean": [
      "bệnh dịch hạch"
    ],
    "hash_code_list_mean": "1684170704",
    "list_img": [
      {
        "link_thumb": "https://live.staticflickr.com/65535/51809674984_176e252dc9_n.jpg",
        "link_img": "https://live.staticflickr.com/65535/51809674984_5d7aea6243_o.png",
        "id_image": "pestilence_3805746"
      }
    ],
    "hash_code_list_img": "933347026",
    "list_example": [
      "You have brought that happy state of things to pass—peace, prosperity, law and order, and protection from war, pestilence and famine.",
      "The day has gone by when we had famine, pestilence and epidemics.",
      "He asserted that famine, war and pestilence were positive ways of checking the growth in population, sweeping away excess peoples, and then maintaining a rough equilibrium between people and necessities.",
      "We face the gravest economic difficulties which have come upon us even though we have not suffered from war, pestilence or famine.",
      "Pollution and pestilence have broken out, contagion made more terrible by their sheer numbers overwhelms them."
    ],
    "hash_code_list_example": "-1720251307"
  },
  {
    "link_it": "https://github.com/lmbstudiocontact/cb_dmean_5000_it_3/raw/main/pestle_cb_dmean_5000_it.json",
    "id_item": "pestle_cb_dmean_5000_it",
    "id_album": "102079919",
    "english": "pestle",
    "list_mean": [
      "cái chày"
    ],
    "hash_code_list_mean": "1603066514",
    "list_img": [
      {
        "link_thumb": "https://live.staticflickr.com/65535/51809435113_ff3d430ab0_n.jpg",
        "link_img": "https://live.staticflickr.com/65535/51809435113_75236ef7cc_o.png",
        "id_image": "pestle_3006167"
      },
      {
        "link_thumb": "https://live.staticflickr.com/65535/51808364687_223d8b0ea6_n.jpg",
        "link_img": "https://live.staticflickr.com/65535/51808364687_d8fc247ba7_o.png",
        "id_image": "pestle_3360549"
      },
      {
        "link_thumb": "https://live.staticflickr.com/65535/51808364672_370f719dd8_n.jpg",
        "link_img": "https://live.staticflickr.com/65535/51808364672_91155ec507_o.png",
        "id_image": "pestle_5332528"
      },
      {
        "link_thumb": "https://live.staticflickr.com/65535/51808364637_7fa2271e20_n.jpg",
        "link_img": "https://live.staticflickr.com/65535/51808364637_f67ba9d133_o.png",
        "id_image": "pestle_6199070"
      }
    ],
    "hash_code_list_img": "1860302212",
    "list_example": [
      "He ground the nutmeg to a powder with a pestle and mortar.",
      "Finally, dying or freshly dead individuals from the infected cultures were homogenized with a plastic pestle in vials containing 1.5 ml of medium to produce the spore suspensions.",
      "Corroded iron, metal bracelets, and a brass pestle have been dug up that however have yet to be dated.",
      "Furious, he runs to his father's home with a brass pestle in his hand, and spies on him from the window.",
      "The most widely used implement for breast ironing is a wooden pestle normally used for pounding tubers.",
      "The gut of each insect was removed before individual insects were ground with a pestle within an 1.5 ml microcentrifuge tube."
    ],
    "hash_code_list_example": "389204638"
  },
  {
    "link_it": "https://github.com/lmbstudiocontact/cb_dmean_5000_it_3/raw/main/pest_cb_dmean_5000_it.json",
    "id_item": "pest_cb_dmean_5000_it",
    "id_album": "102079919",
    "english": "pest",
    "list_mean": [
      "loài phá hoại",
      "kẻ quấy rầy"
    ],
    "hash_code_list_mean": "31789363",
    "list_img": [
      {
        "link_thumb": "https://live.staticflickr.com/65535/51808364787_6ecc64b1e1_n.jpg",
        "link_img": "https://live.staticflickr.com/65535/51808364787_8f61629fda_o.png",
        "id_image": "pest_1345383"
      },
      {
        "link_thumb": "https://live.staticflickr.com/65535/51809320016_9cfbd053ef_n.jpg",
        "link_img": "https://live.staticflickr.com/65535/51809320016_19b769ccb7_o.png",
        "id_image": "pest_2674474"
      },
      {
        "link_thumb": "https://live.staticflickr.com/65535/51809320011_6fb1dbe270_n.jpg",
        "link_img": "https://live.staticflickr.com/65535/51809320011_6be14bbcb1_o.png",
        "id_image": "pest_4212893"
      }
    ],
    "hash_code_list_img": "-1584969193",
    "list_example": [
      "(also adjective) pest control."
    ],
    "hash_code_list_example": "525576107"
  },
  {
    "link_it": "https://github.com/lmbstudiocontact/cb_dmean_5000_it_3/raw/main/petal_cb_dmean_5000_it.json",
    "id_item": "petal_cb_dmean_5000_it",
    "id_album": "102079919",
    "english": "petal",
    "list_mean": [
      "cánh hoa"
    ],
    "hash_code_list_mean": "1810706257",
    "list_img": [
      {
        "link_thumb": "https://live.staticflickr.com/65535/51809674889_16cf6e6d8d_n.jpg",
        "link_img": "https://live.staticflickr.com/65535/51809674889_961b936c09_o.png",
        "id_image": "petal_4119832"
      }
    ],
    "hash_code_list_img": "147043923",
    "list_example": [
      "This rose has yellow petals edged with pink.",
      "A polymerous daylily flower is one with more than three sepals and more than three petals.",
      "However, floral rewards appeared to be tissues of the fleshy staminate petals and pollen that were readily devoured by the beetles.",
      "Abscission is the process by which leaves, petals, and fruits separate from a plant.",
      "The inflorescence is a terminal spike of flowers with purple petals under a centimeter long.",
      "The front part of the pot has 3-4 petals (sabots) which are covered with a centering band (often a nylon derivative).",
      "The flowers are 20 mm diameter, with five white petals and 20 yellowish-white stamens; they are produced in corymbs 611 cm diameter in late spring.",
      "Both forms have flat flowers, with untwisted petals, unusual in the genus.",
      "Many species visit flowers for pollen and nectar, or browse on the petals."
    ],
    "hash_code_list_example": "1091284451"
  },
  {
    "link_it": "https://github.com/lmbstudiocontact/cb_dmean_5000_it_3/raw/main/petition_cb_dmean_5000_it.json",
    "id_item": "petition_cb_dmean_5000_it",
    "id_album": "102079919",
    "english": "petition",
    "list_mean": [
      "đơn",
      "kiến nghị"
    ],
    "hash_code_list_mean": "-992240782",
    "list_img": [
      {
        "link_thumb": "https://live.staticflickr.com/65535/51809705374_0b982681ed_n.jpg",
        "link_img": "https://live.staticflickr.com/65535/51809705374_9c4aba340f_o.png",
        "id_image": "petition_3530521"
      },
      {
        "link_thumb": "https://live.staticflickr.com/65535/51809350811_4d807f3f65_n.jpg",
        "link_img": "https://live.staticflickr.com/65535/51809350811_ac3c37a401_o.png",
        "id_image": "petition_3842692"
      },
      {
        "link_thumb": "https://live.staticflickr.com/65535/51809705319_e056148833_n.jpg",
        "link_img": "https://live.staticflickr.com/65535/51809705319_d6696a20b9_o.png",
        "id_image": "petition_6330595"
      }
    ],
    "hash_code_list_img": "-1175073648",
    "list_example": [
      "She asked me to sign the petition.",
      "They petitioned the government for the release of the prisoners.",
      "While the social importance of legal aid cannot be discounted, the trend of petitioning since 1951 shows no constant relationship to such provision.",
      "The petitions argue that 'women of the town' and 'corrupt women' would choose to live with their paramours as husband and wife.",
      "However, more systematic regional comparisons are hindered by the intrinsically fragmentary and self-selecting nature of much of the evidence (community petitions and individual letters).",
      "With population pressure rising, some residents petitioned to fill-in the palace moat and use that land for new construction.",
      "Litigation masters were required to possess the ability to write brilliantly for their petitions to stand out, being apparently worthy of trial, among countless documents.",
      "She is also petitioned by healers seeking cures for sick children.",
      "Citizens' wives and daughters were far more likely to be the subjects of petitions and pleas for mercy than were marginal women and outsiders.",
      "Lower-class women frequently contested the city's efforts to control their activities through strikes, negotiations, petitions to the cabildo and civil disobedience."
    ],
    "hash_code_list_example": "-1419131219"
  },
  {
    "link_it": "https://github.com/lmbstudiocontact/cb_dmean_5000_it_3/raw/main/petrol_cb_dmean_5000_it.json",
    "id_item": "petrol_cb_dmean_5000_it",
    "id_album": "102079919",
    "english": "petrol",
    "list_mean": [
      "xăng"
    ],
    "hash_code_list_mean": "3827363",
    "list_img": [
      {
        "link_thumb": "https://live.staticflickr.com/65535/51810087895_60d26e51ec_n.jpg",
        "link_img": "https://live.staticflickr.com/65535/51810087895_2d66e9b7a6_o.png",
        "id_image": "petrol_169795"
      },
      {
        "link_thumb": "https://live.staticflickr.com/65535/51809705244_0492e603d8_n.jpg",
        "link_img": "https://live.staticflickr.com/65535/51809705244_89f438ccf4_o.png",
        "id_image": "petrol_1965909"
      },
      {
        "link_thumb": "https://live.staticflickr.com/65535/51809350686_044b20234e_n.jpg",
        "link_img": "https://live.staticflickr.com/65535/51809350686_30149ff726_o.png",
        "id_image": "petrol_2289563"
      },
      {
        "link_thumb": "https://live.staticflickr.com/65535/51809350636_0d7df33fdb_n.jpg",
        "link_img": "https://live.staticflickr.com/65535/51809350636_eeb2e175a2_o.png",
        "id_image": "petrol_2540886"
      }
    ],
    "hash_code_list_img": "-1960987680",
    "list_example": [
      "(also adjective) a petrol engine.",
      "The main occupations are : drivers, tractor drivers, petrol station workers, irrigation workers (men and women), weeders (men and women), gardeners and loaders.",
      "From an architectural point of view, it isn't the branding itself that makes the petrol station interesting, but the standardization of form and building technology that branding encourages.",
      "Very soon petrol companies were building chains of standardized stations.",
      "It may be noted, that petrol driven vehicles also emit pollutants into the atmosphere that impose a cost on the society.",
      "The petrol station is the branded building par ex cellence, though it is hard to see quite why.",
      "Chapter 6 on volatility is not only well written, but the part about petrol shortage and near-crisis situations at the pump is also funny.",
      "An instance of this is the use of the example of price-fixing by petrol companies in a discussion of evolutionary stable strategies in animal species."
    ],
    "hash_code_list_example": "-841252769"
  },
  {
    "link_it": "https://github.com/lmbstudiocontact/cb_dmean_5000_it_3/raw/main/petticoat_cb_dmean_5000_it.json",
    "id_item": "petticoat_cb_dmean_5000_it",
    "id_album": "102079919",
    "english": "petticoat",
    "list_mean": [
      "váy lót dài"
    ],
    "hash_code_list_mean": "1555187783",
    "list_img": [
      {
        "link_thumb": "https://live.staticflickr.com/65535/51809705089_1113fdd17b_n.jpg",
        "link_img": "https://live.staticflickr.com/65535/51809705089_6fae4c3962_o.png",
        "id_image": "petticoat_4977253"
      }
    ],
    "hash_code_list_img": "812381410",
    "list_example": [
      "a lace-trimmed petticoat."
    ],
    "hash_code_list_example": "259415271"
  },
  {
    "link_it": "https://github.com/lmbstudiocontact/cb_dmean_5000_it_3/raw/main/pet_cb_dmean_5000_it.json",
    "id_item": "pet_cb_dmean_5000_it",
    "id_album": "102079919",
    "english": "pet",
    "list_mean": [
      "động vật cảnh",
      "con cưng",
      "nhất",
      "vuốt ve",
      "âu yếm"
    ],
    "hash_code_list_mean": "-101052371",
    "list_img": [
      {
        "link_thumb": "https://live.staticflickr.com/65535/51809705454_9e027c8eca_n.jpg",
        "link_img": "https://live.staticflickr.com/65535/51809705454_e8b867c96b_o.png",
        "id_image": "pet_2377405"
      },
      {
        "link_thumb": "https://live.staticflickr.com/65535/51809350901_14af4b83cd_n.jpg",
        "link_img": "https://live.staticflickr.com/65535/51809350901_4fddbc46ee_o.png",
        "id_image": "pet_2590819"
      },
      {
        "link_thumb": "https://live.staticflickr.com/65535/51809705494_6edb4a275f_n.jpg",
        "link_img": "https://live.staticflickr.com/65535/51809705494_797fcdf7fc_o.png",
        "id_image": "pet_437494"
      },
      {
        "link_thumb": "https://live.staticflickr.com/65535/51809705404_78f0cdddd6_n.jpg",
        "link_img": "https://live.staticflickr.com/65535/51809705404_d9df593244_o.png",
        "id_image": "pet_5798376"
      }
    ],
    "hash_code_list_img": "1466810277",
    "list_example": [
      "(also adjective) a pet rabbit/goldfish.",
      "What is your pet ambition/hate?"
    ],
    "hash_code_list_example": "-1245912782"
  },
  {
    "link_it": "https://github.com/lmbstudiocontact/cb_dmean_5000_it_3/raw/main/phantom_cb_dmean_5000_it.json",
    "id_item": "phantom_cb_dmean_5000_it",
    "id_album": "102079919",
    "english": "phantom",
    "list_mean": [
      "bóng ma"
    ],
    "hash_code_list_mean": "-452346039",
    "list_img": [
      {
        "link_thumb": "https://live.staticflickr.com/65535/51809350446_1832f61809_n.jpg",
        "link_img": "https://live.staticflickr.com/65535/51809350446_72edb0bc4d_o.png",
        "id_image": "phantom_675147"
      },
      {
        "link_thumb": "https://live.staticflickr.com/65535/51808395227_7ed850710e_n.jpg",
        "link_img": "https://live.staticflickr.com/65535/51808395227_85ee1d48f4_o.png",
        "id_image": "phantom_821772"
      }
    ],
    "hash_code_list_img": "216257068",
    "list_example": [
      "Daily checks by radiographers on the unit can be done quickly and easily with a cube phantom (which assumes the couch to be level).",
      "It is not an implausible position on its own, but it seems to be in conflict with the case of paralyzed phantom limb patients.",
      "Pitches that exceed the piano's tessitura hover, canopy-like, over the resonance: phantom pitches produced through the interaction of harmonics.",
      "What if, instead of adding artificial connectivity between pairs of objects, a phantom object were introduced with which each real object was artificially connected?",
      "The \"single white drop of blood\" is a phantom sign, imagined and not empirically visible.",
      "The interface is parameterized by an encoding, via phantom types, of the subtyping hierarchy.",
      "The phantom includes a 'flood field' module for image uniformity assessment."
    ],
    "hash_code_list_example": "1449569030"
  },
  {
    "link_it": "https://github.com/lmbstudiocontact/cb_dmean_5000_it_3/raw/main/pharmacy_cb_dmean_5000_it.json",
    "id_item": "pharmacy_cb_dmean_5000_it",
    "id_album": "102079919",
    "english": "pharmacy",
    "list_mean": [
      "ngành dược",
      "hiệu thuốc"
    ],
    "hash_code_list_mean": "-118523432",
    "list_img": [
      {
        "link_thumb": "https://live.staticflickr.com/65535/51809704894_1c916683d3_n.jpg",
        "link_img": "https://live.staticflickr.com/65535/51809704894_c594cf89e8_o.png",
        "id_image": "pharmacy_1152749"
      },
      {
        "link_thumb": "https://live.staticflickr.com/65535/51808395107_8f4cc50083_n.jpg",
        "link_img": "https://live.staticflickr.com/65535/51808395107_1c8ac65f94_o.png",
        "id_image": "pharmacy_3974939"
      },
      {
        "link_thumb": "https://live.staticflickr.com/65535/51809704854_9e6b782d1e_n.jpg",
        "link_img": "https://live.staticflickr.com/65535/51809704854_2c6980ce48_o.png",
        "id_image": "pharmacy_4534978"
      },
      {
        "link_thumb": "https://live.staticflickr.com/65535/51809350251_ea2a881694_n.jpg",
        "link_img": "https://live.staticflickr.com/65535/51809350251_4acf3381f5_o.png",
        "id_image": "pharmacy_5880158"
      }
    ],
    "hash_code_list_img": "-1584690681",
    "list_example": [
      "He is studying pharmacy.",
      "the hospital pharmacy."
    ],
    "hash_code_list_example": "-1278713794"
  },
  {
    "link_it": "https://github.com/lmbstudiocontact/cb_dmean_5000_it_3/raw/main/phase_cb_dmean_5000_it.json",
    "id_item": "phase_cb_dmean_5000_it",
    "id_album": "102079919",
    "english": "phase",
    "list_mean": [
      "thời kỳ",
      "tuần trăng"
    ],
    "hash_code_list_mean": "-742076193",
    "list_img": [
      {
        "link_thumb": "https://live.staticflickr.com/65535/51809464838_6d629f344e_n.jpg",
        "link_img": "https://live.staticflickr.com/65535/51809464838_4d9ae5d05f_o.png",
        "id_image": "phase_2116980"
      }
    ],
    "hash_code_list_img": "1447901535",
    "list_example": [
      "We are entering a new phase in the war.",
      "This represents the expansion phase of the infection.",
      "At this stage, the wire remains in a liquid- solid phase with a low-density plasma corona.",
      "The maximum relative phase 8, occurs at the intersections of the trajectories with the dashed lines.",
      "The insert represents a phase plane plot of the two variables recorded in the figure.",
      "The spatial phase of surround stimuli was the same as the stimulus on the classical receptive field."
    ],
    "hash_code_list_example": "1890313850"
  },
  {
    "link_it": "https://github.com/lmbstudiocontact/cb_dmean_5000_it_3/raw/main/pheasant_cb_dmean_5000_it.json",
    "id_item": "pheasant_cb_dmean_5000_it",
    "id_album": "102079919",
    "english": "pheasant",
    "list_mean": [
      "chim trĩ",
      "thịt gà lôi"
    ],
    "hash_code_list_mean": "-1341260470",
    "list_img": [
      {
        "link_thumb": "https://live.staticflickr.com/65535/51810087430_cf065e9309_n.jpg",
        "link_img": "https://live.staticflickr.com/65535/51810087430_19f444c724_o.png",
        "id_image": "pheasant_1018385"
      }
    ],
    "hash_code_list_img": "1487734181",
    "list_example": [
      "We had roast pheasant for dinner.",
      "We hypothesize that: (i) pheasant releases may have low effectiveness; and (ii) parasitized pheasants will survive less than non-parasitized ones.",
      "No significant relationship was found between parasite excretion abundance and pheasant survival."
    ],
    "hash_code_list_example": "1956228770"
  },
  {
    "link_it": "https://github.com/lmbstudiocontact/cb_dmean_5000_it_3/raw/main/philosopher_cb_dmean_5000_it.json",
    "id_item": "philosopher_cb_dmean_5000_it",
    "id_album": "102079919",
    "english": "philosopher",
    "list_mean": [
      "nhà triết học"
    ],
    "hash_code_list_mean": "255840483",
    "list_img": [
      {
        "link_thumb": "https://live.staticflickr.com/65535/51808394882_6b13ce5be0_n.jpg",
        "link_img": "https://live.staticflickr.com/65535/51808394882_47b58b9c11_o.png",
        "id_image": "philosopher_5234434"
      },
      {
        "link_thumb": "https://live.staticflickr.com/65535/51810087380_806e65b0f5_n.jpg",
        "link_img": "https://live.staticflickr.com/65535/51810087380_c197e47a28_o.png",
        "id_image": "philosopher_827355"
      }
    ],
    "hash_code_list_img": "1089185502",
    "list_example": [
      "Firstly, one might hold that philosophical ideas should stand or fall on their content, rather than upon the reputation of the philosopher concerned."
    ],
    "hash_code_list_example": "-2003711474"
  },
  {
    "link_it": "https://github.com/lmbstudiocontact/cb_dmean_5000_it_3/raw/main/philosophy_cb_dmean_5000_it.json",
    "id_item": "philosophy_cb_dmean_5000_it",
    "id_album": "102079919",
    "english": "philosophy",
    "list_mean": [
      "triết lý",
      "triết học"
    ],
    "hash_code_list_mean": "1123486254",
    "list_img": [
      {
        "link_thumb": "https://live.staticflickr.com/65535/51810087300_d5882996f7_n.jpg",
        "link_img": "https://live.staticflickr.com/65535/51810087300_58a351abca_o.png",
        "id_image": "philosophy_1651657"
      },
      {
        "link_thumb": "https://live.staticflickr.com/65535/51810087270_89f2fdb0cf_n.jpg",
        "link_img": "https://live.staticflickr.com/65535/51810087270_c7feaed4cf_o.png",
        "id_image": "philosophy_2244711"
      },
      {
        "link_thumb": "https://live.staticflickr.com/65535/51809464723_0dc701a6d2_n.jpg",
        "link_img": "https://live.staticflickr.com/65535/51809464723_107a8913e2_o.png",
        "id_image": "philosophy_401540"
      },
      {
        "link_thumb": "https://live.staticflickr.com/65535/51808394782_7e01223cf7_n.jpg",
        "link_img": "https://live.staticflickr.com/65535/51808394782_7ef0ed96eb_o.png",
        "id_image": "philosophy_4601310"
      },
      {
        "link_thumb": "https://live.staticflickr.com/65535/51809349971_8a37032486_n.jpg",
        "link_img": "https://live.staticflickr.com/65535/51809349971_abd60acd69_o.png",
        "id_image": "philosophy_4635451"
      }
    ],
    "hash_code_list_img": "172763788",
    "list_example": [
      "I have a very simple philosophy (=attitude to life) – enjoy life!",
      "Applying a knowledge-focused management philosophy to immature economies.",
      "At this stage, it could appear that the book is all philosophy with no practical applications.",
      "The philosophy of these homes is characterized by a very strong emphasis on training the staff.",
      "The concept of 'mutuality' is a very helpful one for the reader to use in understanding the author's underpinning philosophy to music with young children."
    ],
    "hash_code_list_example": "487704992"
  },
  {
    "link_it": "https://github.com/lmbstudiocontact/cb_dmean_5000_it_3/raw/main/phobia_cb_dmean_5000_it.json",
    "id_item": "phobia_cb_dmean_5000_it",
    "id_album": "102079919",
    "english": "phobia",
    "list_mean": [
      "sự ám ảnh"
    ],
    "hash_code_list_mean": "-331962678",
    "list_img": [
      {
        "link_thumb": "https://live.staticflickr.com/65535/51809464558_fee5d72357_n.jpg",
        "link_img": "https://live.staticflickr.com/65535/51809464558_a793aaf304_o.png",
        "id_image": "phobia_4525546"
      },
      {
        "link_thumb": "https://live.staticflickr.com/65535/51810087185_3bd797f154_n.jpg",
        "link_img": "https://live.staticflickr.com/65535/51810087185_439beab91b_o.png",
        "id_image": "phobia_555687"
      },
      {
        "link_thumb": "https://live.staticflickr.com/65535/51809349861_8509e0eb9a_n.jpg",
        "link_img": "https://live.staticflickr.com/65535/51809349861_f25b9d9ed1_o.png",
        "id_image": "phobia_6366045"
      }
    ],
    "hash_code_list_img": "-2014716383",
    "list_example": [
      "She has a phobia about spiders.",
      "The fourth column displays odds ratios and confidence intervals comparing individuals with current social phobia to individuals with no lifetime history of the disorder.",
      "Six of the 45 patients (13 %) had a relapse of social phobia at some time during follow-up.",
      "Treatment of generalized social phobia : results at long-term follow-up.",
      "The high prevalence of simple phobia has not inflated the overall prevalence of mental disorder since all of these patients also had another mental disorder."
    ],
    "hash_code_list_example": "-918691517"
  },
  {
    "link_it": "https://github.com/lmbstudiocontact/cb_dmean_5000_it_3/raw/main/phone_cb_dmean_5000_it.json",
    "id_item": "phone_cb_dmean_5000_it",
    "id_album": "102079919",
    "english": "phone",
    "list_mean": [
      "điện thoại",
      "gọi điện thoại"
    ],
    "hash_code_list_mean": "-1203901858",
    "list_img": [
      {
        "link_thumb": "https://live.staticflickr.com/65535/51809704474_893d0a9ea1_n.jpg",
        "link_img": "https://live.staticflickr.com/65535/51809704474_c0f2cf15ef_o.png",
        "id_image": "phone_523104"
      },
      {
        "link_thumb": "https://live.staticflickr.com/65535/51809349811_ee2452b5ec_n.jpg",
        "link_img": "https://live.staticflickr.com/65535/51809349811_df929b79f3_o.png",
        "id_image": "phone_523122"
      },
      {
        "link_thumb": "https://live.staticflickr.com/65535/51809464423_bc77269185_n.jpg",
        "link_img": "https://live.staticflickr.com/65535/51809464423_35d6c4aff8_o.png",
        "id_image": "phone_656275"
      }
    ],
    "hash_code_list_img": "242651594",
    "list_example": [
      "I’ll phone you this evening."
    ],
    "hash_code_list_example": "439585252"
  },
  {
    "link_it": "https://github.com/lmbstudiocontact/cb_dmean_5000_it_3/raw/main/photocopy_cb_dmean_5000_it.json",
    "id_item": "photocopy_cb_dmean_5000_it",
    "id_album": "102079919",
    "english": "photocopy",
    "list_mean": [
      "sao chụp"
    ],
    "hash_code_list_mean": "1958919758",
    "list_img": [
      {
        "link_thumb": "https://live.staticflickr.com/65535/51809349536_fd2676884f_n.jpg",
        "link_img": "https://live.staticflickr.com/65535/51809349536_51747fbc26_o.png",
        "id_image": "photocopy_5068570"
      }
    ],
    "hash_code_list_img": "1458013527",
    "list_example": [
      "Will you photocopy this letter for me?",
      "Then, photocopy and distribute the poems to the class."
    ],
    "hash_code_list_example": "2069298668"
  },
  {
    "link_it": "https://github.com/lmbstudiocontact/cb_dmean_5000_it_3/raw/main/photographic_cb_dmean_5000_it.json",
    "id_item": "photographic_cb_dmean_5000_it",
    "id_album": "102079919",
    "english": "photographic",
    "list_mean": [
      "thuật nhiếp ảnh"
    ],
    "hash_code_list_mean": "-1712231196",
    "list_img": [
      {
        "link_thumb": "https://live.staticflickr.com/65535/51809704009_d78b7e54c6_n.jpg",
        "link_img": "https://live.staticflickr.com/65535/51809704009_f598ffb86b_o.png",
        "id_image": "photographic_223235"
      }
    ],
    "hash_code_list_img": "7544781",
    "list_example": [
      "a photographic record of his journey.",
      "The photographic illustrations, reproduced in black and white, are disappointing.",
      "A photodigitizing machine and a modified photographic streak geometry were employed in the present experiments.",
      "Then follow the five sections, each adhering to the same presentational structure: an essay on the thematic concept, and interpretative photographic essays.",
      "An extremely beautiful photographic record of a row of vortices in the case of 8 = 75\" is shown in figure 15.",
      "He worked with a number of photographic artists over the years.",
      "They bring to the photographic milieu some of the energy that the live acts conjured directly.",
      "The ground floor level contains photographic stores that have to be mechanically cooled whereas the upper levels accommodate the special passively controlled storerooms."
    ],
    "hash_code_list_example": "-997272220"
  },
  {
    "link_it": "https://github.com/lmbstudiocontact/cb_dmean_5000_it_3/raw/main/photography_cb_dmean_5000_it.json",
    "id_item": "photography_cb_dmean_5000_it",
    "id_album": "102079919",
    "english": "photography",
    "list_mean": [
      "sự chụp ảnh"
    ],
    "hash_code_list_mean": "1746929134",
    "list_img": [
      {
        "link_thumb": "https://live.staticflickr.com/65535/51809349261_913d73dfce_n.jpg",
        "link_img": "https://live.staticflickr.com/65535/51809349261_f0c6bda8e3_o.png",
        "id_image": "photography_2389249"
      },
      {
        "link_thumb": "https://live.staticflickr.com/65535/51809463933_a00f24865d_n.jpg",
        "link_img": "https://live.staticflickr.com/65535/51809463933_313581a881_o.png",
        "id_image": "photography_2450937"
      },
      {
        "link_thumb": "https://live.staticflickr.com/65535/51809703969_e81d8017d1_n.jpg",
        "link_img": "https://live.staticflickr.com/65535/51809703969_185e4769ee_o.png",
        "id_image": "photography_250583"
      },
      {
        "link_thumb": "https://live.staticflickr.com/65535/51808393992_534a5870d4_n.jpg",
        "link_img": "https://live.staticflickr.com/65535/51808393992_4eab81b2bf_o.png",
        "id_image": "photography_5683958"
      }
    ],
    "hash_code_list_img": "428615662",
    "list_example": [
      "Using remote photography in wildlife ecology: a review.",
      "Conversely, at another level, photography is a series of different practices, different strands, all of which have different intentions, different cultural expectations and social usages.",
      "It begins with photography in portraiture, proceeding to documentary and then aesthetic treatments.",
      "Since the method of photography displays regions of strong shear, the hypotenuse of the rectangle should appear bright.",
      "The singular significance attached to images of fisherfolk in the material available owes much to the circumstances in which photography first developed.",
      "Where possible, four random points (one from each quarter) of each vegetation type based on the 2004 aerial photography were sampled."
    ],
    "hash_code_list_example": "621704301"
  },
  {
    "link_it": "https://github.com/lmbstudiocontact/cb_dmean_5000_it_3/raw/main/photograph_cb_dmean_5000_it.json",
    "id_item": "photograph_cb_dmean_5000_it",
    "id_album": "102079919",
    "english": "photograph",
    "list_mean": [
      "bức ảnh",
      "chụp ảnh"
    ],
    "hash_code_list_mean": "96669621",
    "list_img": [
      {
        "link_thumb": "https://live.staticflickr.com/65535/51809349511_4cecbeff5f_n.jpg",
        "link_img": "https://live.staticflickr.com/65535/51809349511_dcaa6421a7_o.png",
        "id_image": "photograph_238303"
      },
      {
        "link_thumb": "https://live.staticflickr.com/65535/51808394262_63fee50f9d_n.jpg",
        "link_img": "https://live.staticflickr.com/65535/51808394262_7f19bc8161_o.png",
        "id_image": "photograph_238322"
      },
      {
        "link_thumb": "https://live.staticflickr.com/65535/51809464133_4f17d0fccb_n.jpg",
        "link_img": "https://live.staticflickr.com/65535/51809464133_6af36afb0e_o.png",
        "id_image": "photograph_238348"
      },
      {
        "link_thumb": "https://live.staticflickr.com/65535/51810086645_979c000cca_n.jpg",
        "link_img": "https://live.staticflickr.com/65535/51810086645_3ae5f3e7c9_o.png",
        "id_image": "photograph_238350"
      }
    ],
    "hash_code_list_img": "-1370385547",
    "list_example": [
      "I took a lot of photographs during my holiday.",
      "He spends all his time photographing old buildings.",
      "Where several photographs make up a plate, they should be accurately mounted on card and labelled.",
      "The narrative is supported throughout by numerous photographs that depict environments that were approved or rejected by the older research participants and their families.",
      "The channel radius is obtained from optical images of the channel, that are photographed with another digital camera again 10 ns exposure time!.",
      "They visited the mining areas, under the guidance of one of the main proprietors and made a gesture, duly photographed, towards panning for gold themselves.",
      "We next corrected the large-scale variation in brightness found in most fundus photographs.",
      "Reproduction of some of the photographs is poor.",
      "A comprehensive introduction to all these topics is accompanied by excellent illustrations and photographs, with a very useful 'further reading' list in each section.",
      "Long-term study of solar radiation regimes in a tropical wet forest using quantum sensors and hemispherical photographs."
    ],
    "hash_code_list_example": "934825218"
  },
  {
    "link_it": "https://github.com/lmbstudiocontact/cb_dmean_5000_it_3/raw/main/photon_cb_dmean_5000_it.json",
    "id_item": "photon_cb_dmean_5000_it",
    "id_album": "102079919",
    "english": "photon",
    "list_mean": [
      "phôton"
    ],
    "hash_code_list_mean": "-985072138",
    "list_img": [
      {
        "link_thumb": "https://live.staticflickr.com/65535/51808393962_aaa7f01834_n.jpg",
        "link_img": "https://live.staticflickr.com/65535/51808393962_43d4963a39_o.png",
        "id_image": "photon_4647341"
      }
    ],
    "hash_code_list_img": "721840187",
    "list_example": [
      "This process is analogous to treating the photon or plasmon field as particles.",
      "We can see that the photon energy is enlarged greatly in the laboratory frame because of the relativistic effect.",
      "The entrapment of radiation will make a photon be emitted and resonance-reabsorbed many times inside the laser material.",
      "Suppression of the potential well prevents the free electrons from recombination and, thus, no high-energy photon can be emitted."
    ],
    "hash_code_list_example": "-149427728"
  },
  {
    "link_it": "https://github.com/lmbstudiocontact/cb_dmean_5000_it_3/raw/main/photosynthesis_cb_dmean_5000_it.json",
    "id_item": "photosynthesis_cb_dmean_5000_it",
    "id_album": "102079919",
    "english": "photosynthesis",
    "list_mean": [
      "quang hợp"
    ],
    "hash_code_list_mean": "-1194373494",
    "list_img": [
      {
        "link_thumb": "https://live.staticflickr.com/65535/51809349151_f18cc79857_n.jpg",
        "link_img": "https://live.staticflickr.com/65535/51809349151_56c317a699_o.png",
        "id_image": "photosynthesis_1373958"
      },
      {
        "link_thumb": "https://live.staticflickr.com/65535/51809349126_4064c1237f_n.jpg",
        "link_img": "https://live.staticflickr.com/65535/51809349126_84bccb45bf_o.png",
        "id_image": "photosynthesis_2176957"
      },
      {
        "link_thumb": "https://live.staticflickr.com/65535/51809703849_5e8cc2f153_n.jpg",
        "link_img": "https://live.staticflickr.com/65535/51809703849_4ceda6f963_o.png",
        "id_image": "photosynthesis_4157643"
      }
    ],
    "hash_code_list_img": "-1564434620",
    "list_example": [
      "The primary reaction in photosynthesis depends on light.",
      "Photosynthetic induction strongly affects the light compensation point of net photosynthesis and coincidentally the apparent quantum yield.",
      "This then allows photosynthesis to operate effectively over a wide range of incident light-intensities.",
      "After these immediate measurements, samples were then placed on ice and tested for active photosynthesis at various time intervals afterward.",
      "Either the purple bacteria have acquired the photosynthesis genes recently by lateral gene transfer or selective pressure forced various species to retain these organizational patterns.",
      "Understanding photosynthesis is important for understanding life, the development of the atmosphere on earth and possibly renewable hydrogen generation in the future.",
      "The basis of photosynthesis is the trapping of light energy from the sun by chlorophyll."
    ],
    "hash_code_list_example": "-1576317250"
  },
  {
    "link_it": "https://github.com/lmbstudiocontact/cb_dmean_5000_it_3/raw/main/photo_cb_dmean_5000_it.json",
    "id_item": "photo_cb_dmean_5000_it",
    "id_album": "102079919",
    "english": "photo",
    "list_mean": [
      "ảnh"
    ],
    "hash_code_list_mean": "7540668",
    "list_img": [
      {
        "link_thumb": "https://live.staticflickr.com/65535/51809349611_e9119ec5e5_n.jpg",
        "link_img": "https://live.staticflickr.com/65535/51809349611_a98a9e3be8_o.png",
        "id_image": "photo_529259"
      },
      {
        "link_thumb": "https://live.staticflickr.com/65535/51809349591_be4c80f265_n.jpg",
        "link_img": "https://live.staticflickr.com/65535/51809349591_14ecacf178_o.png",
        "id_image": "photo_648202"
      },
      {
        "link_thumb": "https://live.staticflickr.com/65535/51810086775_910007037a_n.jpg",
        "link_img": "https://live.staticflickr.com/65535/51810086775_b3bbeb7ded_o.png",
        "id_image": "photo_779091"
      }
    ],
    "hash_code_list_img": "98542665",
    "list_example": [
      "Did you take any photos?"
    ],
    "hash_code_list_example": "460485298"
  },
  {
    "link_it": "https://github.com/lmbstudiocontact/cb_dmean_5000_it_3/raw/main/physical_cb_dmean_5000_it.json",
    "id_item": "physical_cb_dmean_5000_it",
    "id_album": "102079919",
    "english": "physical",
    "list_mean": [
      "thân thể",
      "vật chất",
      "quy luật tự nhiên",
      "thuộc tự nhiên",
      "liên quan đến vật lý",
      "khám sức khỏe"
    ],
    "hash_code_list_mean": "1085937778",
    "list_img": [
      {
        "link_thumb": "https://live.staticflickr.com/65535/51809463798_619f66dbdf_n.jpg",
        "link_img": "https://live.staticflickr.com/65535/51809463798_f750d1a838_o.png",
        "id_image": "physical_1813488"
      },
      {
        "link_thumb": "https://live.staticflickr.com/65535/51810086325_9f3e9da571_n.jpg",
        "link_img": "https://live.staticflickr.com/65535/51810086325_6402270c91_o.png",
        "id_image": "physical_2718110"
      },
      {
        "link_thumb": "https://live.staticflickr.com/65535/51810086295_6fa87b8d2b_n.jpg",
        "link_img": "https://live.staticflickr.com/65535/51810086295_c9bdd07af6_o.png",
        "id_image": "physical_2885288"
      },
      {
        "link_thumb": "https://live.staticflickr.com/65535/51808393777_73540172d7_n.jpg",
        "link_img": "https://live.staticflickr.com/65535/51808393777_b8a80a3855_o.png",
        "id_image": "physical_3527121"
      }
    ],
    "hash_code_list_img": "-1924254567",
    "list_example": [
      "Doing exercises is one form of physical fitness.",
      "the physical world.",
      "It’s a physical impossibility for a man to fly like a bird.",
      "physical geography.",
      "physical chemistry."
    ],
    "hash_code_list_example": "627406692"
  },
  {
    "link_it": "https://github.com/lmbstudiocontact/cb_dmean_5000_it_3/raw/main/physician_cb_dmean_5000_it.json",
    "id_item": "physician_cb_dmean_5000_it",
    "id_album": "102079919",
    "english": "physician",
    "list_mean": [
      "bác sĩ điều trị"
    ],
    "hash_code_list_mean": "-334119290",
    "list_img": [
      {
        "link_thumb": "https://live.staticflickr.com/65535/51808393757_83e61cda7a_n.jpg",
        "link_img": "https://live.staticflickr.com/65535/51808393757_61ffa711cc_o.png",
        "id_image": "physician_3527126"
      },
      {
        "link_thumb": "https://live.staticflickr.com/65535/51810086220_721d16eb01_n.jpg",
        "link_img": "https://live.staticflickr.com/65535/51810086220_5a8132d973_o.png",
        "id_image": "physician_6036788"
      }
    ],
    "hash_code_list_img": "-1446049359",
    "list_example": [
      "A physician was permitted to overrule these recommendations by providing the reason at the bottom of the sheet.",
      "Really, the physician is the only one who has to communicate with the patient, do the right thing, and be responsible.",
      "The costs of hospitalization (1;11), surgical procedures (4;33), physician visits (4), and diagnostic tests (4;24) were all included."
    ],
    "hash_code_list_example": "-2045619061"
  },
  {
    "link_it": "https://github.com/lmbstudiocontact/cb_dmean_5000_it_3/raw/main/physics_cb_dmean_5000_it.json",
    "id_item": "physics_cb_dmean_5000_it",
    "id_album": "102079919",
    "english": "physics",
    "list_mean": [
      "môn vật lý"
    ],
    "hash_code_list_mean": "232767980",
    "list_img": [
      {
        "link_thumb": "https://live.staticflickr.com/65535/51809703654_cd3418909d_n.jpg",
        "link_img": "https://live.staticflickr.com/65535/51809703654_b2b2e82842_o.png",
        "id_image": "physics_195821"
      },
      {
        "link_thumb": "https://live.staticflickr.com/65535/51809703624_000557d084_n.jpg",
        "link_img": "https://live.staticflickr.com/65535/51809703624_0d89f823bb_o.png",
        "id_image": "physics_2161370"
      },
      {
        "link_thumb": "https://live.staticflickr.com/65535/51810086145_fbbd3e34be_n.jpg",
        "link_img": "https://live.staticflickr.com/65535/51810086145_3ef4e33c74_o.png",
        "id_image": "physics_4819810"
      },
      {
        "link_thumb": "https://live.staticflickr.com/65535/51810086130_ec8843721b_n.jpg",
        "link_img": "https://live.staticflickr.com/65535/51810086130_59f975c95a_o.png",
        "id_image": "physics_5190400"
      }
    ],
    "hash_code_list_img": "-1463464672",
    "list_example": [
      "The author covers the physics and practical use of such sensors in considerable detail, explaining the benefits and limitations of each technique in turn.",
      "The turbulence physics appears to vary smoothly between the different extremes.",
      "A microscopic system in which microscopic physics plays a crucial role exists in the vicinity of the reconnection point.",
      "Chemists came to believe that essentially physics was no more than mechanics.",
      "This, in addition, settles the question of the relation that the conceptual system of physics can entertain with any other science.",
      "Note that the meaning of 'continuous' is less ambiguous in physics than in mathematics, where set-theoretic, topological and measure-theoretic notions of continuity are superimposed."
    ],
    "hash_code_list_example": "1964772262"
  },
  {
    "link_it": "https://github.com/lmbstudiocontact/cb_dmean_5000_it_3/raw/main/physiology_cb_dmean_5000_it.json",
    "id_item": "physiology_cb_dmean_5000_it",
    "id_album": "102079919",
    "english": "physiology",
    "list_mean": [
      "sinh lý học",
      "chức năng sinh lý"
    ],
    "hash_code_list_mean": "1080501266",
    "list_img": [
      {
        "link_thumb": "https://live.staticflickr.com/65535/51809348776_d76700f18b_n.jpg",
        "link_img": "https://live.staticflickr.com/65535/51809348776_a20ed6354b_o.png",
        "id_image": "physiology_2721196"
      },
      {
        "link_thumb": "https://live.staticflickr.com/65535/51809703509_e5f67fef07_n.jpg",
        "link_img": "https://live.staticflickr.com/65535/51809703509_a20ed6354b_o.png",
        "id_image": "physiology_4072381"
      },
      {
        "link_thumb": "https://live.staticflickr.com/65535/51809703454_cab60063b9_n.jpg",
        "link_img": "https://live.staticflickr.com/65535/51809703454_f24bb534fc_o.png",
        "id_image": "physiology_4178727"
      }
    ],
    "hash_code_list_img": "1289490590",
    "list_example": [
      "In the remainder of cases, the division was purely histological, as the physiology appeared uniform in the factors we tested.",
      "Cuticular detachment is likely to influence the physiology of the nematodes, including development of eggs and juveniles.",
      "It needs to be directed by someone very familiar with neonatal physiology and pharmacology, and fully trained in pediatric interventional cardiology.",
      "There were reliable correlations between the physiology and the person's self-reported anxiety levels.",
      "Parasitological similarity is generated by the interaction of the ecology, physiology and evolutionary history of both parasites and hosts.",
      "This suggests that the operation of adverse influences during intrauterine life leads to permanent alterations in fetal structure and physiology which predispose to adult disease."
    ],
    "hash_code_list_example": "461862567"
  },
  {
    "link_it": "https://github.com/lmbstudiocontact/cb_dmean_5000_it_3/raw/main/pianist_cb_dmean_5000_it.json",
    "id_item": "pianist_cb_dmean_5000_it",
    "id_album": "102079919",
    "english": "pianist",
    "list_mean": [
      "nghệ sĩ pianô"
    ],
    "hash_code_list_mean": "1624104107",
    "list_img": [
      {
        "link_thumb": "https://live.staticflickr.com/65535/51809703394_a5b5659895_n.jpg",
        "link_img": "https://live.staticflickr.com/65535/51809703394_0b50503aa6_o.png",
        "id_image": "pianist_1995318"
      }
    ],
    "hash_code_list_img": "70231530",
    "list_example": [
      "A pianist (1967) who spends roughly a tenth of the time writing for music magazines.",
      "For example, the experienced pianist responds with a voice of expertise: 'could have practised more', 'original and good for someone who doesn't play the piano'.",
      "The tape has a percussive sound at 13915.50, and the pianist is to come in a half second later.",
      "A broken finger will likely have more significance for a professional pianist than for a retired poker player.",
      "With appropriate cues, the pianist is constantly reminded of the exact tempo and directed to the next phrase at the right time.",
      "The pianist is encouraged to experiment with the timing with chunks of 30 seconds of music to determine how the piano part flows."
    ],
    "hash_code_list_example": "-1795961931"
  },
  {
    "link_it": "https://github.com/lmbstudiocontact/cb_dmean_5000_it_3/raw/main/piano_cb_dmean_5000_it.json",
    "id_item": "piano_cb_dmean_5000_it",
    "id_album": "102079919",
    "english": "piano",
    "list_mean": [
      "đàn pianô"
    ],
    "hash_code_list_mean": "-102389012",
    "list_img": [
      {
        "link_thumb": "https://live.staticflickr.com/65535/51809348646_f4ce9c3796_n.jpg",
        "link_img": "https://live.staticflickr.com/65535/51809348646_12ef2929db_o.png",
        "id_image": "piano_1238802"
      }
    ],
    "hash_code_list_img": "988315223",
    "list_example": [
      "She plays the piano very well",
      "(also adjective) piano music.",
      "Another advantage is that with group lessons there is less pressure on the children than in a one-to-one relationship with a piano teacher.",
      "More than half of them had taken piano lessons, for example, and all but one had given up.",
      "The book is aimed at early level, new or returning adult piano students.",
      "Those who could read music usually attributed what skill they had to a previous more formal experience, often their piano lessons."
    ],
    "hash_code_list_example": "-1193983405"
  },
  {
    "link_it": "https://github.com/lmbstudiocontact/cb_dmean_5000_it_3/raw/main/picket_cb_dmean_5000_it.json",
    "id_item": "picket_cb_dmean_5000_it",
    "id_album": "102079919",
    "english": "picket",
    "list_mean": [
      "nhóm người đứng gác không cho ai vào làm khi đình công",
      "nhóm cảnh sát làm nhiệm vụ",
      "gác",
      "chặn gác"
    ],
    "hash_code_list_mean": "-1061731480",
    "list_img": [
      {
        "link_thumb": "https://live.staticflickr.com/65535/51810085695_101e2d5125_n.jpg",
        "link_img": "https://live.staticflickr.com/65535/51810085695_212478fbbe_o.png",
        "id_image": "picket_351802"
      },
      {
        "link_thumb": "https://live.staticflickr.com/65535/51809463208_814e880c99_n.jpg",
        "link_img": "https://live.staticflickr.com/65535/51809463208_6a4fc6145a_o.png",
        "id_image": "picket_422069"
      }
    ],
    "hash_code_list_img": "-1471663754",
    "list_example": [
      "The men set up a picket to stop lorries/trucks getting into the factory",
      "(also adjective) a picket line.",
      "(also adjective) picket duty.",
      "The strikers’ leaders decided to picket the factory"
    ],
    "hash_code_list_example": "-619261565"
  },
  {
    "link_it": "https://github.com/lmbstudiocontact/cb_dmean_5000_it_3/raw/main/pickle_cb_dmean_5000_it.json",
    "id_item": "pickle_cb_dmean_5000_it",
    "id_album": "102079919",
    "english": "pickle",
    "list_mean": [
      "dưa chua",
      "tình trạng khó chịu",
      "ngâm dấm"
    ],
    "hash_code_list_mean": "-1110904384",
    "list_img": [
      {
        "link_thumb": "https://live.staticflickr.com/65535/51810085580_471c92750a_n.jpg",
        "link_img": "https://live.staticflickr.com/65535/51810085580_fb70d05625_o.png",
        "id_image": "pickle_1411022"
      },
      {
        "link_thumb": "https://live.staticflickr.com/65535/51808393142_6b47960960_n.jpg",
        "link_img": "https://live.staticflickr.com/65535/51808393142_02b5ea869f_o.png",
        "id_image": "pickle_5588946"
      },
      {
        "link_thumb": "https://live.staticflickr.com/65535/51810085610_4b0cdc0891_n.jpg",
        "link_img": "https://live.staticflickr.com/65535/51810085610_78314dae1b_o.png",
        "id_image": "pickle_933232"
      }
    ],
    "hash_code_list_img": "1916029054",
    "list_example": [
      "I think I will pickle these cucumbers."
    ],
    "hash_code_list_example": "-554199951"
  },
  {
    "link_it": "https://github.com/lmbstudiocontact/cb_dmean_5000_it_3/raw/main/pickpocket_cb_dmean_5000_it.json",
    "id_item": "pickpocket_cb_dmean_5000_it",
    "id_album": "102079919",
    "english": "pickpocket",
    "list_mean": [
      "kẻ móc túi"
    ],
    "hash_code_list_mean": "-1811192273",
    "list_img": [
      {
        "link_thumb": "https://live.staticflickr.com/65535/51810085500_9f9633ddae_n.jpg",
        "link_img": "https://live.staticflickr.com/65535/51810085500_207d021d2b_o.png",
        "id_image": "pickpocket_4321377"
      }
    ],
    "hash_code_list_img": "2062904133",
    "list_example": [
      "He kept his wallet in his hand because he knew there would be pickpockets in the crowd."
    ],
    "hash_code_list_example": "-962230348"
  }
]